Workbook

Sheet Consolidado
C2: CashFlow | OG2: ORÇADO
C3: Consolidado | E3: 46023 | F3: =E3+1 -> 46024 | G3: =F3+1 -> 46025 | H3: =G3+1 -> 46026 | I3: =H3+1 -> 46027 | J3: =I3+1 -> 46028 | K3: =J3+1 -> 46029 | L3: =K3+1 -> 46030 | M3: =L3+1 -> 46031 | ... AI3: =AH3+1 -> 46053 | AJ3: Jan-26 | AK3: =AI3+1 -> 46054 | AL3: =AK3+1 -> 46055 | AM3: =AL3+1 -> 46056 | AN3: =AM3+1 -> 46057 | AO3: =AN3+1 -> 46058 | AP3: =AO3+1 -> 46059 | AQ3: =AP3+1 -> 46060 | AR3: =AQ3+1 -> 46061 | AS3: =AR3+1 -> 46062 | ... BL3: =BK3+1 -> 46081 | BP3: Fev-26 | BQ3: =BL3+1 -> 46082 | BR3: =BQ3+1 -> 46083 | BS3: =BR3+1 -> 46084 | BT3: =BS3+1 -> 46085 | BU3: =BT3+1 -> 46086 | BV3: =BU3+1 -> 46087 | BW3: =BV3+1 -> 46088 | BX3: =BW3+1 -> 46089 | BY3: =BX3+1 -> 46090 | ... CU3: =CT3+1 -> 46112 | CV3: Mar-26 | CW3: =CU3+1 -> 46113 | CX3: =CW3+1 -> 46114 | CY3: =CX3+1 -> 46115 | CZ3: =CY3+1 -> 46116 | DA3: =CZ3+1 -> 46117 | DB3: =DA3+1 -> 46118 | DC3: =DB3+1 -> 46119 | DD3: =DC3+1 -> 46120 | DE3: =DD3+1 -> 46121 | ... DZ3: =DY3+1 -> 46142 | EB3: Abr-26 | EC3: =DZ3+1 -> 46143 | ED3: =EC3+1 -> 46144 | EE3: =ED3+1 -> 46145 | EF3: =EE3+1 -> 46146 | EG3: =EF3+1 -> 46147 | EH3: =EG3+1 -> 46148 | EI3: =EH3+1 -> 46149 | EJ3: =EI3+1 -> 46150 | EK3: =EJ3+1 -> 46151 | ... FG3: =FF3+1 -> 46173 | FH3: Mai-26 | FI3: =FG3+1 -> 46174 | FJ3: =FI3+1 -> 46175 | FK3: =FJ3+1 -> 46176 | FL3: =FK3+1 -> 46177 | FM3: =FL3+1 -> 46178 | FN3: =FM3+1 -> 46179 | FO3: =FN3+1 -> 46180 | FP3: =FO3+1 -> 46181 | FQ3: =FP3+1 -> 46182 | ... GL3: =GK3+1 -> 46203 | GN3: Jun-26 | GO3: =GL3+1 -> 46204 | GP3: =GO3+1 -> 46205 | GQ3: =GP3+1 -> 46206 | GR3: =GQ3+1 -> 46207 | GS3: =GR3+1 -> 46208 | GT3: =GS3+1 -> 46209 | GU3: =GT3+1 -> 46210 | GV3: =GU3+1 -> 46211 | GW3: =GV3+1 -> 46212 | ... HS3: =HR3+1 -> 46234 | HT3: Jul-26 | HU3: =HS3+1 -> 46235 | HV3: =HU3+1 -> 46236 | HW3: =HV3+1 -> 46237 | HX3: =HW3+1 -> 46238 | HY3: =HX3+1 -> 46239 | HZ3: =HY3+1 -> 46240 | IA3: =HZ3+1 -> 46241 | IB3: =IA3+1 -> 46242 | IC3: =IB3+1 -> 46243 | ... IY3: =IX3+1 -> 46265 | IZ3: Ago-26 | JA3: =IY3+1 -> 46266 | JB3: =JA3+1 -> 46267 | JC3: =JB3+1 -> 46268 | JD3: =JC3+1 -> 46269 | JE3: =JD3+1 -> 46270 | JF3: =JE3+1 -> 46271 | JG3: =JF3+1 -> 46272 | JH3: =JG3+1 -> 46273 | JI3: =JH3+1 -> 46274 | ... KD3: =KC3+1 -> 46295 | KF3: Set-26 | KG3: =KD3+1 -> 46296 | KH3: =KG3+1 -> 46297 | KI3: =KH3+1 -> 46298 | KJ3: =KI3+1 -> 46299 | KK3: =KJ3+1 -> 46300 | KL3: =KK3+1 -> 46301 | KM3: =KL3+1 -> 46302 | KN3: =KM3+1 -> 46303 | KO3: =KN3+1 -> 46304 | ... LK3: =LJ3+1 -> 46326 | LL3: Out-26 | LM3: =LK3+1 -> 46327 | LN3: =LM3+1 -> 46328 | LO3: =LN3+1 -> 46329 | LP3: =LO3+1 -> 46330 | LQ3: =LP3+1 -> 46331 | LR3: =LQ3+1 -> 46332 | LS3: =LR3+1 -> 46333 | LT3: =LS3+1 -> 46334 | LU3: =LT3+1 -> 46335 | ... MP3: =MO3+1 -> 46356 | MR3: Nov-26 | MS3: =MP3+1 -> 46357 | MT3: =MS3+1 -> 46358 | MU3: =MT3+1 -> 46359 | MV3: =MU3+1 -> 46360 | MW3: =MV3+1 -> 46361 | MX3: =MW3+1 -> 46362 | MY3: =MX3+1 -> 46363 | MZ3: =MY3+1 -> 46364 | NA3: =MZ3+1 -> 46365 | ... NW3: =NV3+1 -> 46387 | NX3: Dez-26 | NZ3: Acumulado | OA3: Orçado | OB3: Var% | OG3: CONSOLIDADO | OI3: Jan-26 | OJ3: Fev-26 | OK3: Mar-26 | OL3: Abr-26 | OM3: Mai-26 | ON3: Jun-26 | OO3: Jul-26 | OP3: Ago-26 | OQ3: Set-26 | OR3: Out-26 | OS3: Nov-26 | OT3: Dez-26 | OV3: Acumulado
C5: (A) Saldo Inicial | E5: =SUM(LARM:RM!E5) -> 9666474 | F5: =E66 -> 9666474 | G5: =F66 -> 9557534 | H5: =G66 -> 9557534 | I5: =H66 -> 9557534 | J5: =I66 -> 9568564.6 | K5: =J66 -> 9610003.3 | L5: =K66 -> 9600051.9 | M5: =L66 -> 9504902 | ... AI5: =AH66 -> 9402648.5 | AJ5: =E5 -> 9666474 | AK5: =AJ66 -> 9416986.5 | AL5: =AK66 -> 9416986.5 | AM5: =AL66 -> 9317787.7 | AN5: =AM66 -> 9404151 | AO5: =AN66 -> 9421184 | AP5: =AO66 -> 9417996.4 | AQ5: =AP66 -> 9445722.9 | AR5: =AQ66 -> 9445722.9 | ... BO5: =BN66 -> 9434402.6 | BP5: =AK5 -> 9416986.5 | BQ5: =BP66 -> 9434402.6 | BR5: =BQ66 -> 9434402.6 | BS5: =BR66 -> 9281310.6 | BT5: =BS66 -> 9305044.1 | BU5: =BT66 -> 9328619.4 | BV5: =BU66 -> 9322788.6 | BW5: =BV66 -> 9323256.5 | BX5: =BW66 -> 9323256.5 | ... CU5: =CT66 -> 9197990.2 | CV5: =BQ5 -> 9434402.6 | CW5: =CV66 -> 9214203.8 | CX5: =CW66 -> 9073948.1 | CY5: =CX66 -> 9044133.1 | CZ5: =CY66 -> 9044133.1 | DA5: =CZ66 -> 9044133.1 | DB5: =DA66 -> 9044133.1 | DC5: =DB66 -> 9039172.9 | DD5: =DC66 -> 9068507.7 | ... EA5: =DZ66 -> 8963918.1 | EB5: =CW5 -> 9214203.8 | EC5: =EB66 -> 8963918.1 | ED5: =EC66 -> 8963918.1 | EE5: =ED66 -> 8963918.1 | EF5: =EE66 -> 8963918.1 | EG5: =EF66 -> 9250122.9 | EH5: =EG66 -> 9269303.2 | EI5: =EH66 -> 9263341.3 | EJ5: =EI66 -> 9247341.3 | ... FG5: =FF66 -> 8741427.6 | FH5: =EC5 -> 8963918.1 | FI5: =FH66 -> 8766038.4 | FJ5: =FI66 -> 8766038.4 | FK5: =FJ66 -> 8695353.8 | FL5: =FK66 -> 8697984.4 | FM5: =FL66 -> 8707531.4 | FN5: =FM66 -> 8713171.1 | FO5: =FN66 -> 8727890 | FP5: =FO66 -> 8729138.3 | ... GM5: =GL66 -> 8427355.9 | GN5: =FI5 -> 8766038.4 | GO5: =GN66 -> 8427355.9 | GP5: =GO66 -> 8357391.5 | GQ5: =GP66 -> 8361949 | GR5: =GQ66 -> 8373641.3 | GS5: =GR66 -> 8274749.8 | GT5: =GS66 -> 8280143.1 | GU5: =GT66 -> 8285875.4 | GV5: =GU66 -> 8272125.3 | ... HS5: =HR66 -> 8093017.1 | HT5: =GO5 -> 8427355.9 | HU5: =HT66 -> 8115092.3 | HV5: =HU66 -> 8021236.9 | HW5: =HV66 -> 8025881.2 | HX5: =HW66 -> 8028617 | HY5: =HX66 -> 7927869.5 | HZ5: =HY66 -> 7934778.9 | IA5: =HZ66 -> 7950262.7 | IB5: =IA66 -> 7950784.4 | ... IY5: =IX66 -> 7870292.4 | IZ5: =HU5 -> 8115092.3 | JA5: =IZ66 -> 7876475.2 | JB5: =JA66 -> 7804904 | JC5: =JB66 -> 7809073.3 | JD5: =JC66 -> 7820247.7 | JE5: =JD66 -> 7815247.7 | JF5: =JE66 -> 7814020.4 | JG5: =JF66 -> 7831487.3 | JH5: =JG66 -> 7824235.6 | ... KE5: =KD66 -> 7548467.5 | KF5: =JA5 -> 7876475.2 | KG5: =KF66 -> 7548467.5 | KH5: =KG66 -> 7437549.5 | KI5: =KH66 -> 7442107 | KJ5: =KI66 -> 7444554.8 | KK5: =KJ66 -> 7444554.8 | KL5: =KK66 -> 7451982.1 | KM5: =KL66 -> 7445433.6 | KN5: =KM66 -> 7446681.9 | ... LK5: =LJ66 -> 7155969.7 | LL5: =KG5 -> 7548467.5 | LM5: =LL66 -> 7169151.8 | LN5: =LM66 -> 7169151.8 | LO5: =LN66 -> 7173796.1 | LP5: =LO66 -> 7120463.7 | LQ5: =LP66 -> 7110463.7 | LR5: =LQ66 -> 7103162.8 | LS5: =LR66 -> 7113646.6 | LT5: =LS66 -> 7111394.9 | ... MQ5: =MP66 -> 6865375.4 | MR5: =LM5 -> 7169151.8 | MS5: =MR66 -> 6865375.4 | MT5: =MS66 -> 6849936 | MU5: =MT66 -> 6821087.7 | MV5: =MU66 -> 6783055.3 | MW5: =MV66 -> 6782905.3 | MX5: =MW66 -> 6784854.2 | MY5: =MX66 -> 6794809.6 | MZ5: =MY66 -> 6793563.9 | ... NW5: =NV66 -> 6455753 | NX5: =MS5 -> 6865375.4 | NZ5: =AJ5 -> 9666474 | OA5: =NZ5 -> 9666474 | OG5: (A) Saldo Inicial | OI5: =SUM(LARM:RM!OI5) -> 9666474 | OJ5: =SUM(LARM:RM!OJ5) -> 9318743 | OK5: =SUM(LARM:RM!OK5) -> 8870547.8 | OL5: =SUM(LARM:RM!OL5) -> 8557368.7 | OM5: =SUM(LARM:RM!OM5) -> 8201602.8 | ON5: =SUM(LARM:RM!ON5) -> 8044399.7 | OO5: =SUM(LARM:RM!OO5) -> 7825930.4 | OP5: =SUM(LARM:RM!OP5) -> 7637207.4 | ... OT5: =SUM(LARM:RM!OT5) -> 6908418.4 | OV5: =OI5 -> 9666474
B7: 1. | C7: Receitas Brutas | E7: =SUM(E8:E11) -> 0 | F7: =SUM(F8:F11) -> 5609.2 | G7: =SUM(G8:G11) -> 0 | H7: =SUM(H8:H11) -> 0 | I7: =SUM(I8:I11) -> 13569.03 | J7: =SUM(J8:J11) -> 42403.73 | K7: =SUM(K8:K11) -> 6934.1 | L7: =SUM(L8:L11) -> 4030.18 | ... NX7: =SUM(NX8:NX11) -> 252682.25 | NZ7: =SUM(NZ8:NZ11) -> 3893041.9 | OA7: =SUM(OA8:OA12) -> 2409155.6 | OB7: =IF(NZ7=0,"",(OA7/NZ7)-1) -> -0.38116371 | OG7: Receitas Brutas | OI7: =SUM(OI8:OI11) -> 299175.36 | OJ7: =SUM(OJ8:OJ11) -> 283317.91 | OK7: =SUM(OK8:OK11) -> 434755.18 | OL7: =SUM(OL8:OL11) -> 293546.88 | OM7: =SUM(OM8:OM11) -> 299094.24 | ON7: =SUM(ON8:ON11) -> 292750.18 | OO7: =SUM(OO8:OO11) -> 306379.46 | OP7: =SUM(OP8:OP11) -> 450349.35 | ... OT7: =SUM(OT8:OT11) -> 354228.86 | OV7: =SUM(OV8:OV11) -> 4014790.9
B8: 1.1 | C8: VENDA DE IMÓVEIS | E8: =SUM(LARM:RM!E8) -> 0 | F8: =SUM(LARM:RM!F8) -> 5609.2 | G8: =SUM(LARM:RM!G8) -> 0 | H8: =SUM(LARM:RM!H8) -> 0 | I8: =SUM(LARM:RM!I8) -> 13569.03 | J8: =SUM(LARM:RM!J8) -> 23958.84 | K8: =SUM(LARM:RM!K8) -> 6934.1 | L8: =SUM(LARM:RM!L8) -> 4030.18 | ... AI8: =SUM(LARM:RM!AI8) -> 0 | AJ8: =SUM(E8:AI8) -> 418361.73 | AK8: =SUM(LARM:RM!AK8) -> 0 | AL8: =SUM(LARM:RM!AL8) -> 9347.56 | AM8: =SUM(LARM:RM!AM8) -> 10292.91 | AN8: =SUM(LARM:RM!AN8) -> 8088.29 | AO8: =SUM(LARM:RM!AO8) -> 7695.04 | AP8: =SUM(LARM:RM!AP8) -> 33133.79 | AQ8: =SUM(LARM:RM!AQ8) -> 0 | AR8: =SUM(LARM:RM!AR8) -> 0 | ... BO8: =SUM(LARM:RM!BO8) -> 0 | BP8: =SUM(AK8:BO8) -> 398256.39 | BQ8: =SUM(LARM:RM!BQ8) -> 0 | BR8: =SUM(LARM:RM!BR8) -> 36807.75 | BS8: =SUM(LARM:RM!BS8) -> 27849.87 | BT8: =SUM(LARM:RM!BT8) -> 14642.8 | BU8: =SUM(LARM:RM!BU8) -> 4859.71 | BV8: =SUM(LARM:RM!BV8) -> 9360.65 | BW8: =SUM(LARM:RM!BW8) -> 0 | BX8: =SUM(LARM:RM!BX8) -> 0 | ... CU8: =SUM(LARM:RM!CU8) -> 19943.86 | CV8: =SUM(BQ8:CU8) -> 372283.26 | CW8: =SUM(LARM:RM!CW8) -> 9784.64 | CX8: =SUM(LARM:RM!CX8) -> 6922.99 | CY8: =SUM(LARM:RM!CY8) -> 0 | CZ8: =SUM(LARM:RM!CZ8) -> 0 | DA8: =SUM(LARM:RM!DA8) -> 0 | DB8: =SUM(LARM:RM!DB8) -> 12193.84 | DC8: =SUM(LARM:RM!DC8) -> 29361.82 | DD8: =SUM(LARM:RM!DD8) -> 3663.6 | ... EA8: =SUM(LARM:RM!EA8) -> 0 | EB8: =SUM(CW8:EA8) -> 448049.92 | EC8: =SUM(LARM:RM!EC8) -> 0 | ED8: =SUM(LARM:RM!ED8) -> 0 | EE8: =SUM(LARM:RM!EE8) -> 0 | EF8: =SUM(LARM:RM!EF8) -> 21700.89 | EG8: =SUM(LARM:RM!EG8) -> 20376.6 | EH8: =SUM(LARM:RM!EH8) -> 29823.73 | EI8: =SUM(LARM:RM!EI8) -> 0 | EJ8: =SUM(LARM:RM!EJ8) -> 0 | ... FG8: =SUM(LARM:RM!FG8) -> 0 | FH8: =SUM(EC8:FG8) -> 252021.25 | FI8: =SUM(LARM:RM!FI8) -> 0 | FJ8: =SUM(LARM:RM!FJ8) -> 4644.29 | FK8: =SUM(LARM:RM!FK8) -> 3253.76 | FL8: =SUM(LARM:RM!FL8) -> 1108.49 | FM8: =SUM(LARM:RM!FM8) -> 6790.75 | FN8: =SUM(LARM:RM!FN8) -> 5732.34 | FO8: =SUM(LARM:RM!FO8) -> 1248.33 | FP8: =SUM(LARM:RM!FP8) -> 2185.4 | ... GM8: =SUM(LARM:RM!GM8) -> 0 | GN8: =SUM(FI8:GM8) -> 208446.75 | GO8: =SUM(LARM:RM!GO8) -> 0 | GP8: =SUM(LARM:RM!GP8) -> 4644.29 | GQ8: =SUM(LARM:RM!GQ8) -> 3253.76 | GR8: =SUM(LARM:RM!GR8) -> 1108.49 | GS8: =SUM(LARM:RM!GS8) -> 6339.9 | GT8: =SUM(LARM:RM!GT8) -> 5732.34 | GU8: =SUM(LARM:RM!GU8) -> 3022.92 | GV8: =SUM(LARM:RM!GV8) -> 2185.4 | ... HS8: =SUM(LARM:RM!HS8) -> 0 | HT8: =SUM(GO8:HS8) -> 216447.7 | HU8: =SUM(LARM:RM!HU8) -> 0 | HV8: =SUM(LARM:RM!HV8) -> 4644.29 | HW8: =SUM(LARM:RM!HW8) -> 2735.83 | HX8: =SUM(LARM:RM!HX8) -> 0 | HY8: =SUM(LARM:RM!HY8) -> 6339.9 | HZ8: =SUM(LARM:RM!HZ8) -> 5732.34 | IA8: =SUM(LARM:RM!IA8) -> 1248.33 | IB8: =SUM(LARM:RM!IB8) -> 2185.4 | ... IY8: =SUM(LARM:RM!IY8) -> 0 | IZ8: =SUM(HU8:IY8) -> 227073.04 | JA8: =SUM(LARM:RM!JA8) -> 0 | JB8: =SUM(LARM:RM!JB8) -> 4644.29 | JC8: =SUM(LARM:RM!JC8) -> 2735.83 | JD8: =SUM(LARM:RM!JD8) -> 0 | JE8: =SUM(LARM:RM!JE8) -> 6339.9 | JF8: =SUM(LARM:RM!JF8) -> 7715.48 | JG8: =SUM(LARM:RM!JG8) -> 1248.33 | JH8: =SUM(LARM:RM!JH8) -> 2185.4 | ... KE8: =SUM(LARM:RM!KE8) -> 0 | KF8: =SUM(JA8:KE8) -> 216974.81 | KG8: =SUM(LARM:RM!KG8) -> 0 | KH8: =SUM(LARM:RM!KH8) -> 4644.29 | KI8: =SUM(LARM:RM!KI8) -> 2735.83 | KJ8: =SUM(LARM:RM!KJ8) -> 0 | KK8: =SUM(LARM:RM!KK8) -> 8373.93 | KL8: =SUM(LARM:RM!KL8) -> 5732.34 | KM8: =SUM(LARM:RM!KM8) -> 1248.33 | KN8: =SUM(LARM:RM!KN8) -> 2185.4 | ... LK8: =SUM(LARM:RM!LK8) -> 0 | LL8: =SUM(KG8:LK8) -> 219850.31 | LM8: =SUM(LARM:RM!LM8) -> 0 | LN8: =SUM(LARM:RM!LN8) -> 4644.29 | LO8: =SUM(LARM:RM!LO8) -> 5072.51 | LP8: =SUM(LARM:RM!LP8) -> 0 | LQ8: =SUM(LARM:RM!LQ8) -> 6339.9 | LR8: =SUM(LARM:RM!LR8) -> 5732.34 | LS8: =SUM(LARM:RM!LS8) -> 1248.33 | LT8: =SUM(LARM:RM!LT8) -> 2185.4 | ... MQ8: =SUM(LARM:RM!MQ8) -> 0 | MR8: =SUM(LM8:MQ8) -> 217996.5 | MS8: =SUM(LARM:RM!MS8) -> 0 | MT8: =SUM(LARM:RM!MT8) -> 7651.39 | MU8: =SUM(LARM:RM!MU8) -> 2735.83 | MV8: =SUM(LARM:RM!MV8) -> 0 | MW8: =SUM(LARM:RM!MW8) -> 6339.9 | MX8: =SUM(LARM:RM!MX8) -> 6640.24 | MY8: =SUM(LARM:RM!MY8) -> 1248.33 | MZ8: =SUM(LARM:RM!MZ8) -> 2185.4 | ... NW8: =SUM(LARM:RM!NW8) -> 0 | NX8: =SUM(MS8:NW8) -> 233050.24 | NZ8: =AJ8+BP8+CV8+EB8+FH8+GN8+HT8+IZ8+KF8+LL8+MR8+NX8 -> 3428811.9 | OA8: =SUM(OI8:OP8) -> 2206375.3 | OB8: =IF(OA8=0,"",(NZ8/OA8)-1) -> 0.55404744 | OG8: VENDA DE IMÓVEIS | OI8: =SUM(LARM:RM!OI8) -> 279600.35 | OJ8: =SUM(LARM:RM!OJ8) -> 263742.9 | OK8: =SUM(LARM:RM!OK8) -> 252200.17 | OL8: =SUM(LARM:RM!OL8) -> 273971.87 | OM8: =SUM(LARM:RM!OM8) -> 275114.79 | ON8: =SUM(LARM:RM!ON8) -> 269166.44 | OO8: =SUM(LARM:RM!OO8) -> 286804.45 | OP8: =SUM(LARM:RM!OP8) -> 305774.34 | ... OT8: =SUM(LARM:RM!OT8) -> 334653.85 | OV8: =SUM(OI8:OT8) -> 3483497.6
B9: 1.2 | C9: ALUGUÉIS | E9: =SUM(LARM:RM!E9) -> 0 | F9: =SUM(LARM:RM!F9) -> 0 | G9: =SUM(LARM:RM!G9) -> 0 | H9: =SUM(LARM:RM!H9) -> 0 | I9: =SUM(LARM:RM!I9) -> 0 | J9: =SUM(LARM:RM!J9) -> 9751.45 | K9: =SUM(LARM:RM!K9) -> 0 | L9: =SUM(LARM:RM!L9) -> 0 | ... AI9: =SUM(LARM:RM!AI9) -> 0 | AJ9: =SUM(E9:AI9) -> 9751.45 | AK9: =SUM(LARM:RM!AK9) -> 0 | AL9: =SUM(LARM:RM!AL9) -> 0 | AM9: =SUM(LARM:RM!AM9) -> 0 | AN9: =SUM(LARM:RM!AN9) -> 0 | AO9: =SUM(LARM:RM!AO9) -> 0 | AP9: =SUM(LARM:RM!AP9) -> 0 | AQ9: =SUM(LARM:RM!AQ9) -> 0 | AR9: =SUM(LARM:RM!AR9) -> 0 | ... BO9: =SUM(LARM:RM!BO9) -> 0 | BP9: =SUM(AK9:BO9) -> 0 | BQ9: =SUM(LARM:RM!BQ9) -> 0 | BR9: =SUM(LARM:RM!BR9) -> 0 | BS9: =SUM(LARM:RM!BS9) -> 0 | BT9: =SUM(LARM:RM!BT9) -> 0 | BU9: =SUM(LARM:RM!BU9) -> 0 | BV9: =SUM(LARM:RM!BV9) -> 9751.45 | BW9: =SUM(LARM:RM!BW9) -> 0 | BX9: =SUM(LARM:RM!BX9) -> 0 | ... CU9: =SUM(LARM:RM!CU9) -> 0 | CV9: =SUM(BQ9:CU9) -> 9751.45 | CW9: =SUM(LARM:RM!CW9) -> 0 | CX9: =SUM(LARM:RM!CX9) -> 0 | CY9: =SUM(LARM:RM!CY9) -> 0 | CZ9: =SUM(LARM:RM!CZ9) -> 0 | DA9: =SUM(LARM:RM!DA9) -> 0 | DB9: =SUM(LARM:RM!DB9) -> 0 | DC9: =SUM(LARM:RM!DC9) -> 0 | DD9: =SUM(LARM:RM!DD9) -> 0 | ... EA9: =SUM(LARM:RM!EA9) -> 0 | EB9: =SUM(CW9:EA9) -> 0 | EC9: =SUM(LARM:RM!EC9) -> 0 | ED9: =SUM(LARM:RM!ED9) -> 0 | EE9: =SUM(LARM:RM!EE9) -> 0 | EF9: =SUM(LARM:RM!EF9) -> 0 | EG9: =SUM(LARM:RM!EG9) -> 0 | EH9: =SUM(LARM:RM!EH9) -> 0 | EI9: =SUM(LARM:RM!EI9) -> 0 | EJ9: =SUM(LARM:RM!EJ9) -> 0 | ... FG9: =SUM(LARM:RM!FG9) -> 0 | FH9: =SUM(EC9:FG9) -> 0 | FI9: =SUM(LARM:RM!FI9) -> 0 | FJ9: =SUM(LARM:RM!FJ9) -> 0 | FK9: =SUM(LARM:RM!FK9) -> 0 | FL9: =SUM(LARM:RM!FL9) -> 0 | FM9: =SUM(LARM:RM!FM9) -> 0 | FN9: =SUM(LARM:RM!FN9) -> 9751.45 | FO9: =SUM(LARM:RM!FO9) -> 0 | FP9: =SUM(LARM:RM!FP9) -> 0 | ... GM9: =SUM(LARM:RM!GM9) -> 0 | GN9: =SUM(FI9:GM9) -> 9751.45 | GO9: =SUM(LARM:RM!GO9) -> 0 | GP9: =SUM(LARM:RM!GP9) -> 0 | GQ9: =SUM(LARM:RM!GQ9) -> 0 | GR9: =SUM(LARM:RM!GR9) -> 0 | GS9: =SUM(LARM:RM!GS9) -> 0 | GT9: =SUM(LARM:RM!GT9) -> 0 | GU9: =SUM(LARM:RM!GU9) -> 0 | GV9: =SUM(LARM:RM!GV9) -> 9751.45 | ... HS9: =SUM(LARM:RM!HS9) -> 0 | HT9: =SUM(GO9:HS9) -> 9751.45 | HU9: =SUM(LARM:RM!HU9) -> 0 | HV9: =SUM(LARM:RM!HV9) -> 0 | HW9: =SUM(LARM:RM!HW9) -> 0 | HX9: =SUM(LARM:RM!HX9) -> 0 | HY9: =SUM(LARM:RM!HY9) -> 0 | HZ9: =SUM(LARM:RM!HZ9) -> 9751.45 | IA9: =SUM(LARM:RM!IA9) -> 0 | IB9: =SUM(LARM:RM!IB9) -> 0 | ... IY9: =SUM(LARM:RM!IY9) -> 0 | IZ9: =SUM(HU9:IY9) -> 9751.45 | JA9: =SUM(LARM:RM!JA9) -> 0 | JB9: =SUM(LARM:RM!JB9) -> 0 | JC9: =SUM(LARM:RM!JC9) -> 0 | JD9: =SUM(LARM:RM!JD9) -> 0 | JE9: =SUM(LARM:RM!JE9) -> 0 | JF9: =SUM(LARM:RM!JF9) -> 9751.45 | JG9: =SUM(LARM:RM!JG9) -> 0 | JH9: =SUM(LARM:RM!JH9) -> 0 | ... KE9: =SUM(LARM:RM!KE9) -> 0 | KF9: =SUM(JA9:KE9) -> 9751.45 | KG9: =SUM(LARM:RM!KG9) -> 0 | KH9: =SUM(LARM:RM!KH9) -> 0 | KI9: =SUM(LARM:RM!KI9) -> 0 | KJ9: =SUM(LARM:RM!KJ9) -> 0 | KK9: =SUM(LARM:RM!KK9) -> 0 | KL9: =SUM(LARM:RM!KL9) -> 9751.45 | KM9: =SUM(LARM:RM!KM9) -> 0 | KN9: =SUM(LARM:RM!KN9) -> 0 | ... LK9: =SUM(LARM:RM!LK9) -> 0 | LL9: =SUM(KG9:LK9) -> 9751.45 | LM9: =SUM(LARM:RM!LM9) -> 0 | LN9: =SUM(LARM:RM!LN9) -> 0 | LO9: =SUM(LARM:RM!LO9) -> 0 | LP9: =SUM(LARM:RM!LP9) -> 0 | LQ9: =SUM(LARM:RM!LQ9) -> 0 | LR9: =SUM(LARM:RM!LR9) -> 9751.45 | LS9: =SUM(LARM:RM!LS9) -> 0 | LT9: =SUM(LARM:RM!LT9) -> 0 | ... MQ9: =SUM(LARM:RM!MQ9) -> 0 | MR9: =SUM(LM9:MQ9) -> 9751.45 | MS9: =SUM(LARM:RM!MS9) -> 0 | MT9: =SUM(LARM:RM!MT9) -> 0 | MU9: =SUM(LARM:RM!MU9) -> 0 | MV9: =SUM(LARM:RM!MV9) -> 0 | MW9: =SUM(LARM:RM!MW9) -> 0 | MX9: =SUM(LARM:RM!MX9) -> 9751.45 | MY9: =SUM(LARM:RM!MY9) -> 0 | MZ9: =SUM(LARM:RM!MZ9) -> 0 | ... NW9: =SUM(LARM:RM!NW9) -> 0 | NX9: =SUM(MS9:NW9) -> 9751.45 | NZ9: =AJ9+BP9+CV9+EB9+FH9+GN9+HT9+IZ9+KF9+LL9+MR9+NX9 -> 87763.05 | OA9: =SUM(OI9:OP9) -> 78011.6 | OB9: =IF(OA9=0,"",(NZ9/OA9)-1) -> 0.125 | OG9: ALUGUÉIS | OI9: =SUM(LARM:RM!OI9) -> 9751.45 | OJ9: =SUM(LARM:RM!OJ9) -> 9751.45 | OK9: =SUM(LARM:RM!OK9) -> 9751.45 | OL9: =SUM(LARM:RM!OL9) -> 9751.45 | OM9: =SUM(LARM:RM!OM9) -> 9751.45 | ON9: =SUM(LARM:RM!ON9) -> 9751.45 | OO9: =SUM(LARM:RM!OO9) -> 9751.45 | OP9: =SUM(LARM:RM!OP9) -> 9751.45 | ... OT9: =SUM(LARM:RM!OT9) -> 9751.45 | OV9: =SUM(OI9:OT9) -> 117017.4
B10: 1.3 | C10: VENDA DE MERCADORIAS/GADO | E10: =SUM(LARM:RM!E10) -> 0 | F10: =SUM(LARM:RM!F10) -> 0 | G10: =SUM(LARM:RM!G10) -> 0 | H10: =SUM(LARM:RM!H10) -> 0 | I10: =SUM(LARM:RM!I10) -> 0 | J10: =SUM(LARM:RM!J10) -> 0 | K10: =SUM(LARM:RM!K10) -> 0 | L10: =SUM(LARM:RM!L10) -> 0 | ... AI10: =SUM(LARM:RM!AI10) -> 0 | AJ10: =SUM(E10:AI10) -> 50000 | AK10: =SUM(LARM:RM!AK10) -> 0 | AL10: =SUM(LARM:RM!AL10) -> 0 | AM10: =SUM(LARM:RM!AM10) -> 77500 | AN10: =SUM(LARM:RM!AN10) -> 0 | AO10: =SUM(LARM:RM!AO10) -> 0 | AP10: =SUM(LARM:RM!AP10) -> 0 | AQ10: =SUM(LARM:RM!AQ10) -> 0 | AR10: =SUM(LARM:RM!AR10) -> 0 | ... BO10: =SUM(LARM:RM!BO10) -> 0 | BP10: =SUM(AK10:BO10) -> 77500 | BQ10: =SUM(LARM:RM!BQ10) -> 0 | BR10: =SUM(LARM:RM!BR10) -> 0 | BS10: =SUM(LARM:RM!BS10) -> 0 | BT10: =SUM(LARM:RM!BT10) -> 0 | BU10: =SUM(LARM:RM!BU10) -> 0 | BV10: =SUM(LARM:RM!BV10) -> 0 | BW10: =SUM(LARM:RM!BW10) -> 0 | BX10: =SUM(LARM:RM!BX10) -> 0 | ... CU10: =SUM(LARM:RM!CU10) -> 0 | CV10: =SUM(BQ10:CU10) -> 0 | CW10: =SUM(LARM:RM!CW10) -> 0 | CX10: =SUM(LARM:RM!CX10) -> 0 | CY10: =SUM(LARM:RM!CY10) -> 0 | CZ10: =SUM(LARM:RM!CZ10) -> 0 | DA10: =SUM(LARM:RM!DA10) -> 0 | DB10: =SUM(LARM:RM!DB10) -> 0 | DC10: =SUM(LARM:RM!DC10) -> 0 | DD10: =SUM(LARM:RM!DD10) -> 0 | ... EA10: =SUM(LARM:RM!EA10) -> 0 | EB10: =SUM(CW10:EA10) -> 12000 | EC10: =SUM(LARM:RM!EC10) -> 0 | ED10: =SUM(LARM:RM!ED10) -> 0 | EE10: =SUM(LARM:RM!EE10) -> 0 | EF10: =SUM(LARM:RM!EF10) -> 0 | EG10: =SUM(LARM:RM!EG10) -> 0 | EH10: =SUM(LARM:RM!EH10) -> 0 | EI10: =SUM(LARM:RM!EI10) -> 0 | EJ10: =SUM(LARM:RM!EJ10) -> 0 | ... FG10: =SUM(LARM:RM!FG10) -> 0 | FH10: =SUM(EC10:FG10) -> 0 | FI10: =SUM(LARM:RM!FI10) -> 0 | FJ10: =SUM(LARM:RM!FJ10) -> 0 | FK10: =SUM(LARM:RM!FK10) -> 0 | FL10: =SUM(LARM:RM!FL10) -> 0 | FM10: =SUM(LARM:RM!FM10) -> 0 | FN10: =SUM(LARM:RM!FN10) -> 0 | FO10: =SUM(LARM:RM!FO10) -> 0 | FP10: =SUM(LARM:RM!FP10) -> 0 | ... GM10: =SUM(LARM:RM!GM10) -> 0 | GN10: =SUM(FI10:GM10) -> 0 | GO10: =SUM(LARM:RM!GO10) -> 0 | GP10: =SUM(LARM:RM!GP10) -> 0 | GQ10: =SUM(LARM:RM!GQ10) -> 0 | GR10: =SUM(LARM:RM!GR10) -> 0 | GS10: =SUM(LARM:RM!GS10) -> 0 | GT10: =SUM(LARM:RM!GT10) -> 0 | GU10: =SUM(LARM:RM!GU10) -> 0 | GV10: =SUM(LARM:RM!GV10) -> 0 | ... HS10: =SUM(LARM:RM!HS10) -> 0 | HT10: =SUM(GO10:HS10) -> 0 | HU10: =SUM(LARM:RM!HU10) -> 0 | HV10: =SUM(LARM:RM!HV10) -> 0 | HW10: =SUM(LARM:RM!HW10) -> 0 | HX10: =SUM(LARM:RM!HX10) -> 0 | HY10: =SUM(LARM:RM!HY10) -> 0 | HZ10: =SUM(LARM:RM!HZ10) -> 0 | IA10: =SUM(LARM:RM!IA10) -> 0 | IB10: =SUM(LARM:RM!IB10) -> 0 | ... IY10: =SUM(LARM:RM!IY10) -> 0 | IZ10: =SUM(HU10:IY10) -> 125000 | JA10: =SUM(LARM:RM!JA10) -> 0 | JB10: =SUM(LARM:RM!JB10) -> 0 | JC10: =SUM(LARM:RM!JC10) -> 0 | JD10: =SUM(LARM:RM!JD10) -> 0 | JE10: =SUM(LARM:RM!JE10) -> 0 | JF10: =SUM(LARM:RM!JF10) -> 0 | JG10: =SUM(LARM:RM!JG10) -> 0 | JH10: =SUM(LARM:RM!JH10) -> 0 | ... KE10: =SUM(LARM:RM!KE10) -> 0 | KF10: =SUM(JA10:KE10) -> 0 | KG10: =SUM(LARM:RM!KG10) -> 0 | KH10: =SUM(LARM:RM!KH10) -> 0 | KI10: =SUM(LARM:RM!KI10) -> 0 | KJ10: =SUM(LARM:RM!KJ10) -> 0 | KK10: =SUM(LARM:RM!KK10) -> 0 | KL10: =SUM(LARM:RM!KL10) -> 0 | KM10: =SUM(LARM:RM!KM10) -> 0 | KN10: =SUM(LARM:RM!KN10) -> 0 | ... LK10: =SUM(LARM:RM!LK10) -> 0 | LL10: =SUM(KG10:LK10) -> 0 | LM10: =SUM(LARM:RM!LM10) -> 0 | LN10: =SUM(LARM:RM!LN10) -> 0 | LO10: =SUM(LARM:RM!LO10) -> 0 | LP10: =SUM(LARM:RM!LP10) -> 0 | LQ10: =SUM(LARM:RM!LQ10) -> 0 | LR10: =SUM(LARM:RM!LR10) -> 0 | LS10: =SUM(LARM:RM!LS10) -> 0 | LT10: =SUM(LARM:RM!LT10) -> 0 | ... MQ10: =SUM(LARM:RM!MQ10) -> 0 | MR10: =SUM(LM10:MQ10) -> 0 | MS10: =SUM(LARM:RM!MS10) -> 0 | MT10: =SUM(LARM:RM!MT10) -> 0 | MU10: =SUM(LARM:RM!MU10) -> 0 | MV10: =SUM(LARM:RM!MV10) -> 0 | MW10: =SUM(LARM:RM!MW10) -> 0 | MX10: =SUM(LARM:RM!MX10) -> 0 | MY10: =SUM(LARM:RM!MY10) -> 0 | MZ10: =SUM(LARM:RM!MZ10) -> 0 | ... NW10: =SUM(LARM:RM!NW10) -> 0 | NX10: =SUM(MS10:NW10) -> 0 | NZ10: =AJ10+BP10+CV10+EB10+FH10+GN10+HT10+IZ10+KF10+LL10+MR10+NX10 -> 264500 | OA10: =SUM(OI10:OP10) -> 287980 | OB10: =IF(OA10=0,"",(NZ10/OA10)-1) -> -0.08153344 | OG10: VENDA DE MERCADORIAS/GADO | OI10: =SUM(LARM:RM!OI10) -> 0 | OJ10: =SUM(LARM:RM!OJ10) -> 0 | OK10: =SUM(LARM:RM!OK10) -> 162980 | OL10: =SUM(LARM:RM!OL10) -> 0 | OM10: =SUM(LARM:RM!OM10) -> 0 | ON10: =SUM(LARM:RM!ON10) -> 0 | OO10: =SUM(LARM:RM!OO10) -> 0 | OP10: =SUM(LARM:RM!OP10) -> 125000 | ... OT10: =SUM(LARM:RM!OT10) -> 0 | OV10: =SUM(OI10:OT10) -> 287980
B11: 1.4 | C11: OUTRAS RECEITAS OPERACIONAIS | E11: =SUM(LARM:RM!E11) -> 0 | F11: =SUM(LARM:RM!F11) -> 0 | G11: =SUM(LARM:RM!G11) -> 0 | H11: =SUM(LARM:RM!H11) -> 0 | I11: =SUM(LARM:RM!I11) -> 0 | J11: =SUM(LARM:RM!J11) -> 8693.44 | K11: =SUM(LARM:RM!K11) -> 0 | L11: =SUM(LARM:RM!L11) -> 0 | ... AI11: =SUM(LARM:RM!AI11) -> 0 | AJ11: =SUM(E11:AI11) -> 10135.44 | AK11: =SUM(LARM:RM!AK11) -> 0 | AL11: =SUM(LARM:RM!AL11) -> 0 | AM11: =SUM(LARM:RM!AM11) -> 0 | AN11: =SUM(LARM:RM!AN11) -> 8965.86 | AO11: =SUM(LARM:RM!AO11) -> 0 | AP11: =SUM(LARM:RM!AP11) -> 0 | AQ11: =SUM(LARM:RM!AQ11) -> 0 | AR11: =SUM(LARM:RM!AR11) -> 0 | ... BO11: =SUM(LARM:RM!BO11) -> 0 | BP11: =SUM(AK11:BO11) -> 10408.86 | BQ11: =SUM(LARM:RM!BQ11) -> 0 | BR11: =SUM(LARM:RM!BR11) -> 0 | BS11: =SUM(LARM:RM!BS11) -> 0 | BT11: =SUM(LARM:RM!BT11) -> 8965.86 | BU11: =SUM(LARM:RM!BU11) -> 0 | BV11: =SUM(LARM:RM!BV11) -> 0 | BW11: =SUM(LARM:RM!BW11) -> 0 | BX11: =SUM(LARM:RM!BX11) -> 0 | ... CU11: =SUM(LARM:RM!CU11) -> 0 | CV11: =SUM(BQ11:CU11) -> 10408.86 | CW11: =SUM(LARM:RM!CW11) -> 0 | CX11: =SUM(LARM:RM!CX11) -> 0 | CY11: =SUM(LARM:RM!CY11) -> 0 | CZ11: =SUM(LARM:RM!CZ11) -> 0 | DA11: =SUM(LARM:RM!DA11) -> 0 | DB11: =SUM(LARM:RM!DB11) -> 8965.86 | DC11: =SUM(LARM:RM!DC11) -> 0 | DD11: =SUM(LARM:RM!DD11) -> 0 | ... EA11: =SUM(LARM:RM!EA11) -> 0 | EB11: =SUM(CW11:EA11) -> 10407.86 | EC11: =SUM(LARM:RM!EC11) -> 0 | ED11: =SUM(LARM:RM!ED11) -> 0 | EE11: =SUM(LARM:RM!EE11) -> 0 | EF11: =SUM(LARM:RM!EF11) -> 0 | EG11: =SUM(LARM:RM!EG11) -> 0 | EH11: =SUM(LARM:RM!EH11) -> 0 | EI11: =SUM(LARM:RM!EI11) -> 0 | EJ11: =SUM(LARM:RM!EJ11) -> 0 | ... FG11: =SUM(LARM:RM!FG11) -> 0 | FH11: =SUM(EC11:FG11) -> 1442 | FI11: =SUM(LARM:RM!FI11) -> 0 | FJ11: =SUM(LARM:RM!FJ11) -> 0 | FK11: =SUM(LARM:RM!FK11) -> 0 | FL11: =SUM(LARM:RM!FL11) -> 8438.56 | FM11: =SUM(LARM:RM!FM11) -> 0 | FN11: =SUM(LARM:RM!FN11) -> 0 | FO11: =SUM(LARM:RM!FO11) -> 0 | FP11: =SUM(LARM:RM!FP11) -> 0 | ... GM11: =SUM(LARM:RM!GM11) -> 0 | GN11: =SUM(FI11:GM11) -> 9880.56 | GO11: =SUM(LARM:RM!GO11) -> 0 | GP11: =SUM(LARM:RM!GP11) -> 0 | GQ11: =SUM(LARM:RM!GQ11) -> 8438.56 | GR11: =SUM(LARM:RM!GR11) -> 0 | GS11: =SUM(LARM:RM!GS11) -> 0 | GT11: =SUM(LARM:RM!GT11) -> 0 | GU11: =SUM(LARM:RM!GU11) -> 0 | GV11: =SUM(LARM:RM!GV11) -> 0 | ... HS11: =SUM(LARM:RM!HS11) -> 0 | HT11: =SUM(GO11:HS11) -> 9880.56 | HU11: =SUM(LARM:RM!HU11) -> 0 | HV11: =SUM(LARM:RM!HV11) -> 0 | HW11: =SUM(LARM:RM!HW11) -> 0 | HX11: =SUM(LARM:RM!HX11) -> 0 | HY11: =SUM(LARM:RM!HY11) -> 8438.56 | HZ11: =SUM(LARM:RM!HZ11) -> 0 | IA11: =SUM(LARM:RM!IA11) -> 0 | IB11: =SUM(LARM:RM!IB11) -> 0 | ... IY11: =SUM(LARM:RM!IY11) -> 0 | IZ11: =SUM(HU11:IY11) -> 9880.56 | JA11: =SUM(LARM:RM!JA11) -> 0 | JB11: =SUM(LARM:RM!JB11) -> 0 | JC11: =SUM(LARM:RM!JC11) -> 8438.56 | JD11: =SUM(LARM:RM!JD11) -> 0 | JE11: =SUM(LARM:RM!JE11) -> 0 | JF11: =SUM(LARM:RM!JF11) -> 0 | JG11: =SUM(LARM:RM!JG11) -> 0 | JH11: =SUM(LARM:RM!JH11) -> 0 | ... KE11: =SUM(LARM:RM!KE11) -> 0 | KF11: =SUM(JA11:KE11) -> 9880.56 | KG11: =SUM(LARM:RM!KG11) -> 0 | KH11: =SUM(LARM:RM!KH11) -> 0 | KI11: =SUM(LARM:RM!KI11) -> 8438.56 | KJ11: =SUM(LARM:RM!KJ11) -> 0 | KK11: =SUM(LARM:RM!KK11) -> 0 | KL11: =SUM(LARM:RM!KL11) -> 0 | KM11: =SUM(LARM:RM!KM11) -> 0 | KN11: =SUM(LARM:RM!KN11) -> 0 | ... LK11: =SUM(LARM:RM!LK11) -> 0 | LL11: =SUM(KG11:LK11) -> 9880.56 | LM11: =SUM(LARM:RM!LM11) -> 0 | LN11: =SUM(LARM:RM!LN11) -> 0 | LO11: =SUM(LARM:RM!LO11) -> 8438.56 | LP11: =SUM(LARM:RM!LP11) -> 0 | LQ11: =SUM(LARM:RM!LQ11) -> 0 | LR11: =SUM(LARM:RM!LR11) -> 0 | LS11: =SUM(LARM:RM!LS11) -> 0 | LT11: =SUM(LARM:RM!LT11) -> 0 | ... MQ11: =SUM(LARM:RM!MQ11) -> 0 | MR11: =SUM(LM11:MQ11) -> 9880.56 | MS11: =SUM(LARM:RM!MS11) -> 0 | MT11: =SUM(LARM:RM!MT11) -> 0 | MU11: =SUM(LARM:RM!MU11) -> 8438.56 | MV11: =SUM(LARM:RM!MV11) -> 0 | MW11: =SUM(LARM:RM!MW11) -> 0 | MX11: =SUM(LARM:RM!MX11) -> 0 | MY11: =SUM(LARM:RM!MY11) -> 0 | MZ11: =SUM(LARM:RM!MZ11) -> 0 | ... NW11: =SUM(LARM:RM!NW11) -> 0 | NX11: =SUM(MS11:NW11) -> 9880.56 | NZ11: =AJ11+BP11+CV11+EB11+FH11+GN11+HT11+IZ11+KF11+LL11+MR11+NX11 -> 111966.94 | OA11: =SUM(OI11:OP11) -> 87001.65 | OB11: =IF(OA11=0,"",(NZ11/OA11)-1) -> 0.28695191 | OG11: OUTRAS RECEITAS OPERACIONAIS | OI11: =SUM(LARM:RM!OI11) -> 9823.56 | OJ11: =SUM(LARM:RM!OJ11) -> 9823.56 | OK11: =SUM(LARM:RM!OK11) -> 9823.56 | OL11: =SUM(LARM:RM!OL11) -> 9823.56 | OM11: =SUM(LARM:RM!OM11) -> 14228 | ON11: =SUM(LARM:RM!ON11) -> 13832.29 | OO11: =SUM(LARM:RM!OO11) -> 9823.56 | OP11: =SUM(LARM:RM!OP11) -> 9823.56 | ... OT11: =SUM(LARM:RM!OT11) -> 9823.56 | OV11: =SUM(OI11:OT11) -> 126295.89
C12: Deduções das Receitas | E12: =SUM(E13:E14) -> 0 | F12: =SUM(F13:F14) -> 0 | G12: =SUM(G13:G14) -> 0 | H12: =SUM(H13:H14) -> 0 | I12: =SUM(I13:I14) -> 0 | J12: =SUM(J13:J14) -> 0 | K12: =SUM(K13:K14) -> 0 | L12: =SUM(L13:L14) -> 0 | ... NX12: =SUM(NX13:NX14) -> -7812.9 | NZ12: =SUM(NZ13:NZ14) -> -457666.46 | OA12: =SUM(OA13:OA14)+OA15 -> -250212.96 | OB12: =IF(OA12=0,"",((NZ12/OA12)-1)*-1) -> -0.82910773 | OG12: Deduções das Receitas | OI12: =SUM(OI13:OI14) -> -81795.37 | OJ12: =SUM(OJ13:OJ14) -> -31012.46 | OK12: =SUM(OK13:OK14) -> -14258.97 | OL12: =SUM(OL13:OL14) -> -47277.71 | OM12: =SUM(OM13:OM14) -> -10039.91 | ON12: =SUM(ON13:ON14) -> -11839.47 | OO12: =SUM(OO13:OO14) -> -34432.94 | OP12: =SUM(OP13:OP14) -> -19556.13 | ... OT12: =SUM(OT13:OT14) -> -7812.9 | OV12: =SUM(OV13:OV14) -> -306707.3
B13: 1.9 | C13: VENDAS CANCELADAS | E13: =SUM(LARM:RM!E13) -> 0 | F13: =SUM(LARM:RM!F13) -> 0 | G13: =SUM(LARM:RM!G13) -> 0 | H13: =SUM(LARM:RM!H13) -> 0 | I13: =SUM(LARM:RM!I13) -> 0 | J13: =SUM(LARM:RM!J13) -> 0 | K13: =SUM(LARM:RM!K13) -> 0 | L13: =SUM(LARM:RM!L13) -> 0 | ... AI13: =SUM(LARM:RM!AI13) -> 0 | AJ13: =SUM(E13:AI13) -> -74993.5 | AK13: =SUM(LARM:RM!AK13) -> 0 | AL13: =SUM(LARM:RM!AL13) -> 0 | AM13: =SUM(LARM:RM!AM13) -> 0 | AN13: =SUM(LARM:RM!AN13) -> 0 | AO13: =SUM(LARM:RM!AO13) -> 0 | AP13: =SUM(LARM:RM!AP13) -> 0 | AQ13: =SUM(LARM:RM!AQ13) -> 0 | AR13: =SUM(LARM:RM!AR13) -> 0 | ... BO13: =SUM(LARM:RM!BO13) -> 0 | BP13: =SUM(AK13:BO13) -> 0 | BQ13: =SUM(LARM:RM!BQ13) -> 0 | BR13: =SUM(LARM:RM!BR13) -> -20091.35 | BS13: =SUM(LARM:RM!BS13) -> 0 | BT13: =SUM(LARM:RM!BT13) -> 0 | BU13: =SUM(LARM:RM!BU13) -> 0 | BV13: =SUM(LARM:RM!BV13) -> 0 | BW13: =SUM(LARM:RM!BW13) -> 0 | BX13: =SUM(LARM:RM!BX13) -> 0 | ... CU13: =SUM(LARM:RM!CU13) -> 0 | CV13: =SUM(BQ13:CU13) -> -39188.38 | CW13: =SUM(LARM:RM!CW13) -> 0 | CX13: =SUM(LARM:RM!CX13) -> 0 | CY13: =SUM(LARM:RM!CY13) -> 0 | CZ13: =SUM(LARM:RM!CZ13) -> 0 | DA13: =SUM(LARM:RM!DA13) -> 0 | DB13: =SUM(LARM:RM!DB13) -> 0 | DC13: =SUM(LARM:RM!DC13) -> 0 | DD13: =SUM(LARM:RM!DD13) -> 0 | ... EA13: =SUM(LARM:RM!EA13) -> 0 | EB13: =SUM(CW13:EA13) -> -50391.62 | EC13: =SUM(LARM:RM!EC13) -> 0 | ED13: =SUM(LARM:RM!ED13) -> 0 | EE13: =SUM(LARM:RM!EE13) -> 0 | EF13: =SUM(LARM:RM!EF13) -> 0 | EG13: =SUM(LARM:RM!EG13) -> 0 | EH13: =SUM(LARM:RM!EH13) -> 0 | EI13: =SUM(LARM:RM!EI13) -> 0 | EJ13: =SUM(LARM:RM!EJ13) -> 0 | ... FG13: =SUM(LARM:RM!FG13) -> 0 | FH13: =SUM(EC13:FG13) -> -48578.94 | FI13: =SUM(LARM:RM!FI13) -> 0 | FJ13: =SUM(LARM:RM!FJ13) -> 0 | FK13: =SUM(LARM:RM!FK13) -> 0 | FL13: =SUM(LARM:RM!FL13) -> 0 | FM13: =SUM(LARM:RM!FM13) -> 0 | FN13: =SUM(LARM:RM!FN13) -> 0 | FO13: =SUM(LARM:RM!FO13) -> 0 | FP13: =SUM(LARM:RM!FP13) -> 0 | ... GM13: =SUM(LARM:RM!GM13) -> 0 | GN13: =SUM(FI13:GM13) -> 0 | GO13: =SUM(LARM:RM!GO13) -> 0 | GP13: =SUM(LARM:RM!GP13) -> 0 | GQ13: =SUM(LARM:RM!GQ13) -> 0 | GR13: =SUM(LARM:RM!GR13) -> 0 | GS13: =SUM(LARM:RM!GS13) -> 0 | GT13: =SUM(LARM:RM!GT13) -> 0 | GU13: =SUM(LARM:RM!GU13) -> 0 | GV13: =SUM(LARM:RM!GV13) -> 0 | ... HS13: =SUM(LARM:RM!HS13) -> 0 | HT13: =SUM(GO13:HS13) -> 0 | HU13: =SUM(LARM:RM!HU13) -> 0 | HV13: =SUM(LARM:RM!HV13) -> 0 | HW13: =SUM(LARM:RM!HW13) -> 0 | HX13: =SUM(LARM:RM!HX13) -> 0 | HY13: =SUM(LARM:RM!HY13) -> 0 | HZ13: =SUM(LARM:RM!HZ13) -> 0 | IA13: =SUM(LARM:RM!IA13) -> 0 | IB13: =SUM(LARM:RM!IB13) -> 0 | ... IY13: =SUM(LARM:RM!IY13) -> 0 | IZ13: =SUM(HU13:IY13) -> 0 | JA13: =SUM(LARM:RM!JA13) -> 0 | JB13: =SUM(LARM:RM!JB13) -> 0 | JC13: =SUM(LARM:RM!JC13) -> 0 | JD13: =SUM(LARM:RM!JD13) -> 0 | JE13: =SUM(LARM:RM!JE13) -> 0 | JF13: =SUM(LARM:RM!JF13) -> 0 | JG13: =SUM(LARM:RM!JG13) -> 0 | JH13: =SUM(LARM:RM!JH13) -> 0 | ... KE13: =SUM(LARM:RM!KE13) -> 0 | KF13: =SUM(JA13:KE13) -> 0 | KG13: =SUM(LARM:RM!KG13) -> 0 | KH13: =SUM(LARM:RM!KH13) -> 0 | KI13: =SUM(LARM:RM!KI13) -> 0 | KJ13: =SUM(LARM:RM!KJ13) -> 0 | KK13: =SUM(LARM:RM!KK13) -> 0 | KL13: =SUM(LARM:RM!KL13) -> 0 | KM13: =SUM(LARM:RM!KM13) -> 0 | KN13: =SUM(LARM:RM!KN13) -> 0 | ... LK13: =SUM(LARM:RM!LK13) -> 0 | LL13: =SUM(KG13:LK13) -> 0 | LM13: =SUM(LARM:RM!LM13) -> 0 | LN13: =SUM(LARM:RM!LN13) -> 0 | LO13: =SUM(LARM:RM!LO13) -> 0 | LP13: =SUM(LARM:RM!LP13) -> 0 | LQ13: =SUM(LARM:RM!LQ13) -> 0 | LR13: =SUM(LARM:RM!LR13) -> 0 | LS13: =SUM(LARM:RM!LS13) -> 0 | LT13: =SUM(LARM:RM!LT13) -> 0 | ... MQ13: =SUM(LARM:RM!MQ13) -> 0 | MR13: =SUM(LM13:MQ13) -> 0 | MS13: =SUM(LARM:RM!MS13) -> 0 | MT13: =SUM(LARM:RM!MT13) -> 0 | MU13: =SUM(LARM:RM!MU13) -> 0 | MV13: =SUM(LARM:RM!MV13) -> 0 | MW13: =SUM(LARM:RM!MW13) -> 0 | MX13: =SUM(LARM:RM!MX13) -> 0 | MY13: =SUM(LARM:RM!MY13) -> 0 | MZ13: =SUM(LARM:RM!MZ13) -> 0 | ... NW13: =SUM(LARM:RM!NW13) -> 0 | NX13: =SUM(MS13:NW13) -> 0 | NZ13: =AJ13+BP13+CV13+EB13+FH13+GN13+HT13+IZ13+KF13+LL13+MR13+NX13 -> -213152.44 | OA13: =SUM(OI13:OP13) -> -53251.59 | OB13: =IF(OA13=0,"",((NZ13/OA13)-1)*-1) -> -3.0027432 | OG13: VENDAS CANCELADAS | OI13: =SUM(LARM:RM!OI13) -> -53251.59 | OJ13: =SUM(LARM:RM!OJ13) -> 0 | OK13: =SUM(LARM:RM!OK13) -> 0 | OL13: =SUM(LARM:RM!OL13) -> 0 | OM13: =SUM(LARM:RM!OM13) -> 0 | ON13: =SUM(LARM:RM!ON13) -> 0 | OO13: =SUM(LARM:RM!OO13) -> 0 | OP13: =SUM(LARM:RM!OP13) -> 0 | ... OT13: =SUM(LARM:RM!OT13) -> 0 | OV13: =SUM(OI13:OT13) -> -53251.59
B14: 2.1 | C14: IMPOSTOS S/ VENDAS | E14: =SUM(LARM:RM!E14) -> 0 | F14: =SUM(LARM:RM!F14) -> 0 | G14: =SUM(LARM:RM!G14) -> 0 | H14: =SUM(LARM:RM!H14) -> 0 | I14: =SUM(LARM:RM!I14) -> 0 | J14: =SUM(LARM:RM!J14) -> 0 | K14: =SUM(LARM:RM!K14) -> 0 | L14: =SUM(LARM:RM!L14) -> 0 | ... AI14: =SUM(LARM:RM!AI14) -> 0 | AJ14: =SUM(E14:AI14) -> -52873.83 | AK14: =SUM(LARM:RM!AK14) -> 0 | AL14: =SUM(LARM:RM!AL14) -> 0 | AM14: =SUM(LARM:RM!AM14) -> 0 | AN14: =SUM(LARM:RM!AN14) -> 0 | AO14: =SUM(LARM:RM!AO14) -> 0 | AP14: =SUM(LARM:RM!AP14) -> 0 | AQ14: =SUM(LARM:RM!AQ14) -> 0 | AR14: =SUM(LARM:RM!AR14) -> 0 | ... BO14: =SUM(LARM:RM!BO14) -> 0 | BP14: =SUM(AK14:BO14) -> -12641.7 | BQ14: =SUM(LARM:RM!BQ14) -> 0 | BR14: =SUM(LARM:RM!BR14) -> 0 | BS14: =SUM(LARM:RM!BS14) -> 0 | BT14: =SUM(LARM:RM!BT14) -> 0 | BU14: =SUM(LARM:RM!BU14) -> 0 | BV14: =SUM(LARM:RM!BV14) -> 0 | BW14: =SUM(LARM:RM!BW14) -> 0 | BX14: =SUM(LARM:RM!BX14) -> 0 | ... CU14: =SUM(LARM:RM!CU14) -> 0 | CV14: =SUM(BQ14:CU14) -> -10165.49 | CW14: =SUM(LARM:RM!CW14) -> 0 | CX14: =SUM(LARM:RM!CX14) -> 0 | CY14: =SUM(LARM:RM!CY14) -> 0 | CZ14: =SUM(LARM:RM!CZ14) -> 0 | DA14: =SUM(LARM:RM!DA14) -> 0 | DB14: =SUM(LARM:RM!DB14) -> 0 | DC14: =SUM(LARM:RM!DC14) -> 0 | DD14: =SUM(LARM:RM!DD14) -> 0 | ... EA14: =SUM(LARM:RM!EA14) -> 0 | EB14: =SUM(CW14:EA14) -> -36470.21 | EC14: =SUM(LARM:RM!EC14) -> 0 | ED14: =SUM(LARM:RM!ED14) -> 0 | EE14: =SUM(LARM:RM!EE14) -> 0 | EF14: =SUM(LARM:RM!EF14) -> 0 | EG14: =SUM(LARM:RM!EG14) -> 0 | EH14: =SUM(LARM:RM!EH14) -> 0 | EI14: =SUM(LARM:RM!EI14) -> 0 | EJ14: =SUM(LARM:RM!EJ14) -> 0 | ... FG14: =SUM(LARM:RM!FG14) -> 0 | FH14: =SUM(EC14:FG14) -> -10039.91 | FI14: =SUM(LARM:RM!FI14) -> 0 | FJ14: =SUM(LARM:RM!FJ14) -> 0 | FK14: =SUM(LARM:RM!FK14) -> 0 | FL14: =SUM(LARM:RM!FL14) -> 0 | FM14: =SUM(LARM:RM!FM14) -> 0 | FN14: =SUM(LARM:RM!FN14) -> 0 | FO14: =SUM(LARM:RM!FO14) -> 0 | FP14: =SUM(LARM:RM!FP14) -> 0 | ... GM14: =SUM(LARM:RM!GM14) -> 0 | GN14: =SUM(FI14:GM14) -> -11839.47 | GO14: =SUM(LARM:RM!GO14) -> 0 | GP14: =SUM(LARM:RM!GP14) -> 0 | GQ14: =SUM(LARM:RM!GQ14) -> 0 | GR14: =SUM(LARM:RM!GR14) -> 0 | GS14: =SUM(LARM:RM!GS14) -> 0 | GT14: =SUM(LARM:RM!GT14) -> 0 | GU14: =SUM(LARM:RM!GU14) -> 0 | GV14: =SUM(LARM:RM!GV14) -> 0 | ... HS14: =SUM(LARM:RM!HS14) -> 0 | HT14: =SUM(GO14:HS14) -> -34432.94 | HU14: =SUM(LARM:RM!HU14) -> 0 | HV14: =SUM(LARM:RM!HV14) -> 0 | HW14: =SUM(LARM:RM!HW14) -> 0 | HX14: =SUM(LARM:RM!HX14) -> 0 | HY14: =SUM(LARM:RM!HY14) -> 0 | HZ14: =SUM(LARM:RM!HZ14) -> 0 | IA14: =SUM(LARM:RM!IA14) -> 0 | IB14: =SUM(LARM:RM!IB14) -> 0 | ... IY14: =SUM(LARM:RM!IY14) -> 0 | IZ14: =SUM(HU14:IY14) -> -19556.13 | JA14: =SUM(LARM:RM!JA14) -> 0 | JB14: =SUM(LARM:RM!JB14) -> 0 | JC14: =SUM(LARM:RM!JC14) -> 0 | JD14: =SUM(LARM:RM!JD14) -> 0 | JE14: =SUM(LARM:RM!JE14) -> 0 | JF14: =SUM(LARM:RM!JF14) -> 0 | JG14: =SUM(LARM:RM!JG14) -> 0 | JH14: =SUM(LARM:RM!JH14) -> 0 | ... KE14: =SUM(LARM:RM!KE14) -> 0 | KF14: =SUM(JA14:KE14) -> -11435.29 | KG14: =SUM(LARM:RM!KG14) -> 0 | KH14: =SUM(LARM:RM!KH14) -> 0 | KI14: =SUM(LARM:RM!KI14) -> 0 | KJ14: =SUM(LARM:RM!KJ14) -> 0 | KK14: =SUM(LARM:RM!KK14) -> 0 | KL14: =SUM(LARM:RM!KL14) -> 0 | KM14: =SUM(LARM:RM!KM14) -> 0 | KN14: =SUM(LARM:RM!KN14) -> 0 | ... LK14: =SUM(LARM:RM!LK14) -> 0 | LL14: =SUM(KG14:LK14) -> -29433.25 | LM14: =SUM(LARM:RM!LM14) -> 0 | LN14: =SUM(LARM:RM!LN14) -> 0 | LO14: =SUM(LARM:RM!LO14) -> 0 | LP14: =SUM(LARM:RM!LP14) -> 0 | LQ14: =SUM(LARM:RM!LQ14) -> 0 | LR14: =SUM(LARM:RM!LR14) -> 0 | LS14: =SUM(LARM:RM!LS14) -> 0 | LT14: =SUM(LARM:RM!LT14) -> 0 | ... MQ14: =SUM(LARM:RM!MQ14) -> 0 | MR14: =SUM(LM14:MQ14) -> -7812.9 | MS14: =SUM(LARM:RM!MS14) -> 0 | MT14: =SUM(LARM:RM!MT14) -> 0 | MU14: =SUM(LARM:RM!MU14) -> 0 | MV14: =SUM(LARM:RM!MV14) -> 0 | MW14: =SUM(LARM:RM!MW14) -> 0 | MX14: =SUM(LARM:RM!MX14) -> 0 | MY14: =SUM(LARM:RM!MY14) -> 0 | MZ14: =SUM(LARM:RM!MZ14) -> 0 | ... NW14: =SUM(LARM:RM!NW14) -> 0 | NX14: =SUM(MS14:NW14) -> -7812.9 | NZ14: =AJ14+BP14+CV14+EB14+FH14+GN14+HT14+IZ14+KF14+LL14+MR14+NX14 -> -244514.02 | OA14: =SUM(OI14:OP14) -> -196961.37 | OB14: =IF(OA14=0,"",((NZ14/OA14)-1)*-1) -> -0.24143135 | OG14: IMPOSTOS S/ VENDAS | OI14: =SUM(LARM:RM!OI14) -> -28543.78 | OJ14: =SUM(LARM:RM!OJ14) -> -31012.46 | OK14: =SUM(LARM:RM!OK14) -> -14258.97 | OL14: =SUM(LARM:RM!OL14) -> -47277.71 | OM14: =SUM(LARM:RM!OM14) -> -10039.91 | ON14: =SUM(LARM:RM!ON14) -> -11839.47 | OO14: =SUM(LARM:RM!OO14) -> -34432.94 | OP14: =SUM(LARM:RM!OP14) -> -19556.13 | ... OT14: =SUM(LARM:RM!OT14) -> -7812.9 | OV14: =SUM(OI14:OT14) -> -253455.71
OB15: =IF(OA15=0,"",((NZ15/OA15)-1)*-1)
C16: Receita Líquida | E16: =E7+E12 -> 0 | F16: =F7+F12 -> 5609.2 | G16: =G7+G12 -> 0 | H16: =H7+H12 -> 0 | I16: =I7+I12 -> 13569.03 | J16: =J7+J12 -> 42403.73 | K16: =K7+K12 -> 6934.1 | L16: =L7+L12 -> 4030.18 | ... NX16: =NX7+NX12 -> 244869.35 | NZ16: =NZ7+NZ12 -> 3435375.4 | OA16: =OA7+OA12 -> 2158942.6 | OB16: =IF(OA16=0,"",((NZ16/OA16)-1)*-1) -> -0.59123052 | OG16: Receita Líquida | OI16: =OI7+OI12 -> 217379.99 | OJ16: =OJ7+OJ12 -> 252305.45 | OK16: =OK7+OK12 -> 420496.21 | OL16: =OL7+OL12 -> 246269.17 | OM16: =OM7+OM12 -> 289054.34 | ON16: =ON7+ON12 -> 280910.71 | OO16: =OO7+OO12 -> 271946.52 | OP16: =OP7+OP12 -> 430793.22 | ... OT16: =OT7+OT12 -> 346415.96 | OV16: =OV7+OV12 -> 3708083.6
B18: 4. | C18: Despesas Gerais e Administrativas | E18: =SUM(E19:E31) -> 0 | F18: =SUM(F19:F31) -> -67226.89 | G18: =SUM(G19:G31) -> 0 | H18: =SUM(H19:H31) -> 0 | I18: =SUM(I19:I31) -> -1169.24 | J18: =SUM(J19:J31) -> -925.94 | K18: =SUM(K19:K31) -> -16863.94 | L18: =SUM(L19:L31) -> -29245.09 | ... NX18: =SUM(NX19:NX31) -> -513052.46 | NZ18: =SUM(NZ19:NZ31) -> -5451172.4 | OA18: =OA19+OA20+OA21+OA22+OA23+OA24+OA25+OA26+OA27+OA28+OA29 -> -3164894.4 | OB18: =IF(OA18=0,"",((NZ18/OA18)-1)*-1) -> -0.7223868 | OG18: Despesas Gerais e Administrativas | OI18: =SUM(OI19:OI31) -> -452359.82 | OJ18: =SUM(OJ19:OJ31) -> -463922.99 | OK18: =SUM(OK19:OK31) -> -496965.19 | OL18: =SUM(OL19:OL31) -> -385228.73 | OM18: =SUM(OM19:OM31) -> -662378.39 | ON18: =SUM(ON19:ON31) -> -386553.25 | OO18: =SUM(OO19:OO31) -> -347842.85 | OP18: =SUM(OP19:OP31) -> -423415.81 | ... OT18: =SUM(OT19:OT31) -> -517533.53 | OV18: =SUM(OV19:OV31) -> -5372977.7
B19: 4.1 | C19: DESPESAS COM PESSOAL (1) | E19: =SUM(LARM:RM!E19) -> 0 | F19: =SUM(LARM:RM!F19) -> 0 | G19: =SUM(LARM:RM!G19) -> 0 | H19: =SUM(LARM:RM!H19) -> 0 | I19: =SUM(LARM:RM!I19) -> 0 | J19: =SUM(LARM:RM!J19) -> 0 | K19: =SUM(LARM:RM!K19) -> 0 | L19: =SUM(LARM:RM!L19) -> 0 | ... AI19: =SUM(LARM:RM!AI19) -> 0 | AJ19: =SUM(E19:AI19) -> -110882.46 | AK19: =SUM(LARM:RM!AK19) -> 0 | AL19: =SUM(LARM:RM!AL19) -> 0 | AM19: =SUM(LARM:RM!AM19) -> 0 | AN19: =SUM(LARM:RM!AN19) -> 0 | AO19: =SUM(LARM:RM!AO19) -> 0 | AP19: =SUM(LARM:RM!AP19) -> 0 | AQ19: =SUM(LARM:RM!AQ19) -> 0 | AR19: =SUM(LARM:RM!AR19) -> 0 | ... BO19: =SUM(LARM:RM!BO19) -> 0 | BP19: =SUM(AK19:BO19) -> -103879.25 | BQ19: =SUM(LARM:RM!BQ19) -> 0 | BR19: =SUM(LARM:RM!BR19) -> 0 | BS19: =SUM(LARM:RM!BS19) -> 0 | BT19: =SUM(LARM:RM!BT19) -> 0 | BU19: =SUM(LARM:RM!BU19) -> 0 | BV19: =SUM(LARM:RM!BV19) -> 0 | BW19: =SUM(LARM:RM!BW19) -> 0 | BX19: =SUM(LARM:RM!BX19) -> 0 | ... CU19: =SUM(LARM:RM!CU19) -> 0 | CV19: =SUM(BQ19:CU19) -> -103543.4 | CW19: =SUM(LARM:RM!CW19) -> 0 | CX19: =SUM(LARM:RM!CX19) -> 0 | CY19: =SUM(LARM:RM!CY19) -> 0 | CZ19: =SUM(LARM:RM!CZ19) -> 0 | DA19: =SUM(LARM:RM!DA19) -> 0 | DB19: =SUM(LARM:RM!DB19) -> 0 | DC19: =SUM(LARM:RM!DC19) -> 0 | DD19: =SUM(LARM:RM!DD19) -> 0 | ... EA19: =SUM(LARM:RM!EA19) -> 0 | EB19: =SUM(CW19:EA19) -> -97907.42 | EC19: =SUM(LARM:RM!EC19) -> 0 | ED19: =SUM(LARM:RM!ED19) -> 0 | EE19: =SUM(LARM:RM!EE19) -> 0 | EF19: =SUM(LARM:RM!EF19) -> 0 | EG19: =SUM(LARM:RM!EG19) -> 0 | EH19: =SUM(LARM:RM!EH19) -> 0 | EI19: =SUM(LARM:RM!EI19) -> 0 | EJ19: =SUM(LARM:RM!EJ19) -> 0 | ... FG19: =SUM(LARM:RM!FG19) -> 0 | FH19: =SUM(EC19:FG19) -> -109473.56 | FI19: =SUM(LARM:RM!FI19) -> 0 | FJ19: =SUM(LARM:RM!FJ19) -> 0 | FK19: =SUM(LARM:RM!FK19) -> 0 | FL19: =SUM(LARM:RM!FL19) -> 0 | FM19: =SUM(LARM:RM!FM19) -> 0 | FN19: =SUM(LARM:RM!FN19) -> 0 | FO19: =SUM(LARM:RM!FO19) -> 0 | FP19: =SUM(LARM:RM!FP19) -> 0 | ... GM19: =SUM(LARM:RM!GM19) -> 0 | GN19: =SUM(FI19:GM19) -> -113995.28 | GO19: =SUM(LARM:RM!GO19) -> 0 | GP19: =SUM(LARM:RM!GP19) -> 0 | GQ19: =SUM(LARM:RM!GQ19) -> 0 | GR19: =SUM(LARM:RM!GR19) -> 0 | GS19: =SUM(LARM:RM!GS19) -> 0 | GT19: =SUM(LARM:RM!GT19) -> 0 | GU19: =SUM(LARM:RM!GU19) -> 0 | GV19: =SUM(LARM:RM!GV19) -> 0 | ... HS19: =SUM(LARM:RM!HS19) -> 0 | HT19: =SUM(GO19:HS19) -> -110883.44 | HU19: =SUM(LARM:RM!HU19) -> -1356.3 | HV19: =SUM(LARM:RM!HV19) -> 0 | HW19: =SUM(LARM:RM!HW19) -> 0 | HX19: =SUM(LARM:RM!HX19) -> 0 | HY19: =SUM(LARM:RM!HY19) -> 0 | HZ19: =SUM(LARM:RM!HZ19) -> 0 | IA19: =SUM(LARM:RM!IA19) -> -726.58 | IB19: =SUM(LARM:RM!IB19) -> 0 | ... IY19: =SUM(LARM:RM!IY19) -> 0 | IZ19: =SUM(HU19:IY19) -> -119898.27 | JA19: =SUM(LARM:RM!JA19) -> 0 | JB19: =SUM(LARM:RM!JB19) -> 0 | JC19: =SUM(LARM:RM!JC19) -> 0 | JD19: =SUM(LARM:RM!JD19) -> 0 | JE19: =SUM(LARM:RM!JE19) -> 0 | JF19: =SUM(LARM:RM!JF19) -> 0 | JG19: =SUM(LARM:RM!JG19) -> 0 | JH19: =SUM(LARM:RM!JH19) -> 0 | ... KE19: =SUM(LARM:RM!KE19) -> 0 | KF19: =SUM(JA19:KE19) -> -115799.65 | KG19: =SUM(LARM:RM!KG19) -> 0 | KH19: =SUM(LARM:RM!KH19) -> 0 | KI19: =SUM(LARM:RM!KI19) -> 0 | KJ19: =SUM(LARM:RM!KJ19) -> 0 | KK19: =SUM(LARM:RM!KK19) -> 0 | KL19: =SUM(LARM:RM!KL19) -> 0 | KM19: =SUM(LARM:RM!KM19) -> 0 | KN19: =SUM(LARM:RM!KN19) -> 0 | ... LK19: =SUM(LARM:RM!LK19) -> 0 | LL19: =SUM(KG19:LK19) -> -111574.14 | LM19: =SUM(LARM:RM!LM19) -> 0 | LN19: =SUM(LARM:RM!LN19) -> 0 | LO19: =SUM(LARM:RM!LO19) -> 0 | LP19: =SUM(LARM:RM!LP19) -> 0 | LQ19: =SUM(LARM:RM!LQ19) -> 0 | LR19: =SUM(LARM:RM!LR19) -> 0 | LS19: =SUM(LARM:RM!LS19) -> 0 | LT19: =SUM(LARM:RM!LT19) -> 0 | ... MQ19: =SUM(LARM:RM!MQ19) -> 0 | MR19: =SUM(LM19:MQ19) -> -150447.51 | MS19: =SUM(LARM:RM!MS19) -> 0 | MT19: =SUM(LARM:RM!MT19) -> -661.45 | MU19: =SUM(LARM:RM!MU19) -> 0 | MV19: =SUM(LARM:RM!MV19) -> 0 | MW19: =SUM(LARM:RM!MW19) -> 0 | MX19: =SUM(LARM:RM!MX19) -> 0 | MY19: =SUM(LARM:RM!MY19) -> -2493.99 | MZ19: =SUM(LARM:RM!MZ19) -> 0 | ... NW19: =SUM(LARM:RM!NW19) -> 0 | NX19: =SUM(MS19:NW19) -> -200850.35 | NZ19: =AJ19+BP19+CV19+EB19+FH19+GN19+HT19+IZ19+KF19+LL19+MR19+NX19 -> -1449134.7 | OA19: =SUM(OI19:OP19) -> -911269.45 | OB19: =IF(OA19=0,"",((NZ19/OA19)-1)*-1) -> -0.59023737 | OG19: DESPESAS COM PESSOAL (1) | OI19: =SUM(LARM:RM!OI19) -> -111635.3 | OJ19: =SUM(LARM:RM!OJ19) -> -112667.6 | OK19: =SUM(LARM:RM!OK19) -> -110044.48 | OL19: =SUM(LARM:RM!OL19) -> -112962 | OM19: =SUM(LARM:RM!OM19) -> -129511.36 | ON19: =SUM(LARM:RM!ON19) -> -107974.74 | OO19: =SUM(LARM:RM!OO19) -> -107164.06 | OP19: =SUM(LARM:RM!OP19) -> -119309.9 | ... OT19: =SUM(LARM:RM!OT19) -> -208561.27 | OV19: =SUM(OI19:OT19) -> -1498973.6
B20: 4.2 | C20: OCUPACÃO (2) | E20: =SUM(LARM:RM!E20) -> 0 | F20: =SUM(LARM:RM!F20) -> -23096.54 | G20: =SUM(LARM:RM!G20) -> 0 | H20: =SUM(LARM:RM!H20) -> 0 | I20: =SUM(LARM:RM!I20) -> 0 | J20: =SUM(LARM:RM!J20) -> 0 | K20: =SUM(LARM:RM!K20) -> -6591.13 | L20: =SUM(LARM:RM!L20) -> -3680 | ... AI20: =SUM(LARM:RM!AI20) -> 0 | AJ20: =SUM(E20:AI20) -> -46655.23 | AK20: =SUM(LARM:RM!AK20) -> 0 | AL20: =SUM(LARM:RM!AL20) -> -31307.19 | AM20: =SUM(LARM:RM!AM20) -> 0 | AN20: =SUM(LARM:RM!AN20) -> 0 | AO20: =SUM(LARM:RM!AO20) -> 0 | AP20: =SUM(LARM:RM!AP20) -> 0 | AQ20: =SUM(LARM:RM!AQ20) -> 0 | AR20: =SUM(LARM:RM!AR20) -> 0 | ... BO20: =SUM(LARM:RM!BO20) -> 0 | BP20: =SUM(AK20:BO20) -> -37989.34 | BQ20: =SUM(LARM:RM!BQ20) -> 0 | BR20: =SUM(LARM:RM!BR20) -> -23057.46 | BS20: =SUM(LARM:RM!BS20) -> 0 | BT20: =SUM(LARM:RM!BT20) -> 0 | BU20: =SUM(LARM:RM!BU20) -> 0 | BV20: =SUM(LARM:RM!BV20) -> 0 | BW20: =SUM(LARM:RM!BW20) -> 0 | BX20: =SUM(LARM:RM!BX20) -> 0 | ... CU20: =SUM(LARM:RM!CU20) -> 0 | CV20: =SUM(BQ20:CU20) -> -40314.91 | CW20: =SUM(LARM:RM!CW20) -> -25508.45 | CX20: =SUM(LARM:RM!CX20) -> 0 | CY20: =SUM(LARM:RM!CY20) -> 0 | CZ20: =SUM(LARM:RM!CZ20) -> 0 | DA20: =SUM(LARM:RM!DA20) -> 0 | DB20: =SUM(LARM:RM!DB20) -> -7434.76 | DC20: =SUM(LARM:RM!DC20) -> 0 | DD20: =SUM(LARM:RM!DD20) -> 0 | ... EA20: =SUM(LARM:RM!EA20) -> 0 | EB20: =SUM(CW20:EA20) -> -42669.81 | EC20: =SUM(LARM:RM!EC20) -> 0 | ED20: =SUM(LARM:RM!ED20) -> 0 | EE20: =SUM(LARM:RM!EE20) -> 0 | EF20: =SUM(LARM:RM!EF20) -> -25905.95 | EG20: =SUM(LARM:RM!EG20) -> 0 | EH20: =SUM(LARM:RM!EH20) -> -3300.3 | EI20: =SUM(LARM:RM!EI20) -> 0 | EJ20: =SUM(LARM:RM!EJ20) -> 0 | ... FG20: =SUM(LARM:RM!FG20) -> 0 | FH20: =SUM(EC20:FG20) -> -42379.91 | FI20: =SUM(LARM:RM!FI20) -> 0 | FJ20: =SUM(LARM:RM!FJ20) -> -29913.46 | FK20: =SUM(LARM:RM!FK20) -> 0 | FL20: =SUM(LARM:RM!FL20) -> 0 | FM20: =SUM(LARM:RM!FM20) -> 0 | FN20: =SUM(LARM:RM!FN20) -> 0 | FO20: =SUM(LARM:RM!FO20) -> 0 | FP20: =SUM(LARM:RM!FP20) -> 0 | ... GM20: =SUM(LARM:RM!GM20) -> 0 | GN20: =SUM(FI20:GM20) -> -36283.86 | GO20: =SUM(LARM:RM!GO20) -> -29387.02 | GP20: =SUM(LARM:RM!GP20) -> 0 | GQ20: =SUM(LARM:RM!GQ20) -> 0 | GR20: =SUM(LARM:RM!GR20) -> 0 | GS20: =SUM(LARM:RM!GS20) -> 0 | GT20: =SUM(LARM:RM!GT20) -> 0 | GU20: =SUM(LARM:RM!GU20) -> -6222 | GV20: =SUM(LARM:RM!GV20) -> 0 | ... HS20: =SUM(LARM:RM!HS20) -> 0 | HT20: =SUM(GO20:HS20) -> -42307.02 | HU20: =SUM(LARM:RM!HU20) -> -29667.91 | HV20: =SUM(LARM:RM!HV20) -> 0 | HW20: =SUM(LARM:RM!HW20) -> 0 | HX20: =SUM(LARM:RM!HX20) -> 0 | HY20: =SUM(LARM:RM!HY20) -> 0 | HZ20: =SUM(LARM:RM!HZ20) -> 0 | IA20: =SUM(LARM:RM!IA20) -> 0 | IB20: =SUM(LARM:RM!IB20) -> 0 | ... IY20: =SUM(LARM:RM!IY20) -> 0 | IZ20: =SUM(HU20:IY20) -> -40147.91 | JA20: =SUM(LARM:RM!JA20) -> -30006.03 | JB20: =SUM(LARM:RM!JB20) -> 0 | JC20: =SUM(LARM:RM!JC20) -> 0 | JD20: =SUM(LARM:RM!JD20) -> 0 | JE20: =SUM(LARM:RM!JE20) -> -1600 | JF20: =SUM(LARM:RM!JF20) -> 0 | JG20: =SUM(LARM:RM!JG20) -> 0 | JH20: =SUM(LARM:RM!JH20) -> 0 | ... KE20: =SUM(LARM:RM!KE20) -> 0 | KF20: =SUM(JA20:KE20) -> -58954.62 | KG20: =SUM(LARM:RM!KG20) -> -19096 | KH20: =SUM(LARM:RM!KH20) -> 0 | KI20: =SUM(LARM:RM!KI20) -> -8616.67 | KJ20: =SUM(LARM:RM!KJ20) -> 0 | KK20: =SUM(LARM:RM!KK20) -> 0 | KL20: =SUM(LARM:RM!KL20) -> -11016.58 | KM20: =SUM(LARM:RM!KM20) -> 0 | KN20: =SUM(LARM:RM!KN20) -> 0 | ... LK20: =SUM(LARM:RM!LK20) -> 0 | LL20: =SUM(KG20:LK20) -> -52455.25 | LM20: =SUM(LARM:RM!LM20) -> 0 | LN20: =SUM(LARM:RM!LN20) -> 0 | LO20: =SUM(LARM:RM!LO20) -> -18896 | LP20: =SUM(LARM:RM!LP20) -> 0 | LQ20: =SUM(LARM:RM!LQ20) -> -10779.81 | LR20: =SUM(LARM:RM!LR20) -> 0 | LS20: =SUM(LARM:RM!LS20) -> 0 | LT20: =SUM(LARM:RM!LT20) -> 0 | ... MQ20: =SUM(LARM:RM!MQ20) -> 0 | MR20: =SUM(LM20:MQ20) -> -41124.61 | MS20: =SUM(LARM:RM!MS20) -> -12889.37 | MT20: =SUM(LARM:RM!MT20) -> 0 | MU20: =SUM(LARM:RM!MU20) -> -10106 | MV20: =SUM(LARM:RM!MV20) -> 0 | MW20: =SUM(LARM:RM!MW20) -> 0 | MX20: =SUM(LARM:RM!MX20) -> -6126.27 | MY20: =SUM(LARM:RM!MY20) -> 0 | MZ20: =SUM(LARM:RM!MZ20) -> 0 | ... NW20: =SUM(LARM:RM!NW20) -> 0 | NX20: =SUM(MS20:NW20) -> -39869.64 | NZ20: =AJ20+BP20+CV20+EB20+FH20+GN20+HT20+IZ20+KF20+LL20+MR20+NX20 -> -521152.11 | OA20: =SUM(OI20:OP20) -> -353409.24 | OB20: =IF(OA20=0,"",((NZ20/OA20)-1)*-1) -> -0.474642 | OD20: =30963-26696 -> 4267 | OG20: OCUPACÃO (2) | OI20: =SUM(LARM:RM!OI20) -> -57061.97 | OJ20: =SUM(LARM:RM!OJ20) -> -40747.43 | OK20: =SUM(LARM:RM!OK20) -> -43027.53 | OL20: =SUM(LARM:RM!OL20) -> -52087.93 | OM20: =SUM(LARM:RM!OM20) -> -41745.59 | ON20: =SUM(LARM:RM!ON20) -> -36283.86 | OO20: =SUM(LARM:RM!OO20) -> -42307.02 | OP20: =SUM(LARM:RM!OP20) -> -40147.91 | ... OT20: =SUM(LARM:RM!OT20) -> -39869.64 | OV20: =SUM(OI20:OT20) -> -545813.36
B21: 4.3 | C21: UTILIDADES E SERVICOS (3) | E21: =SUM(LARM:RM!E21) -> 0 | F21: =SUM(LARM:RM!F21) -> -467.06 | G21: =SUM(LARM:RM!G21) -> 0 | H21: =SUM(LARM:RM!H21) -> 0 | I21: =SUM(LARM:RM!I21) -> 0 | J21: =SUM(LARM:RM!J21) -> -425.94 | K21: =SUM(LARM:RM!K21) -> 0 | L21: =SUM(LARM:RM!L21) -> -2141.17 | ... AI21: =SUM(LARM:RM!AI21) -> 0 | AJ21: =SUM(E21:AI21) -> -9008.6 | AK21: =SUM(LARM:RM!AK21) -> 0 | AL21: =SUM(LARM:RM!AL21) -> -1083.35 | AM21: =SUM(LARM:RM!AM21) -> 0 | AN21: =SUM(LARM:RM!AN21) -> 0 | AO21: =SUM(LARM:RM!AO21) -> 0 | AP21: =SUM(LARM:RM!AP21) -> -368.15 | AQ21: =SUM(LARM:RM!AQ21) -> 0 | AR21: =SUM(LARM:RM!AR21) -> 0 | ... BO21: =SUM(LARM:RM!BO21) -> 0 | BP21: =SUM(AK21:BO21) -> -9002.28 | BQ21: =SUM(LARM:RM!BQ21) -> 0 | BR21: =SUM(LARM:RM!BR21) -> -1078.46 | BS21: =SUM(LARM:RM!BS21) -> 0 | BT21: =SUM(LARM:RM!BT21) -> 0 | BU21: =SUM(LARM:RM!BU21) -> -518.11 | BV21: =SUM(LARM:RM!BV21) -> -640.46 | BW21: =SUM(LARM:RM!BW21) -> 0 | BX21: =SUM(LARM:RM!BX21) -> 0 | ... CU21: =SUM(LARM:RM!CU21) -> 0 | CV21: =SUM(BQ21:CU21) -> -10324.54 | CW21: =SUM(LARM:RM!CW21) -> -1047.29 | CX21: =SUM(LARM:RM!CX21) -> 0 | CY21: =SUM(LARM:RM!CY21) -> 0 | CZ21: =SUM(LARM:RM!CZ21) -> 0 | DA21: =SUM(LARM:RM!DA21) -> 0 | DB21: =SUM(LARM:RM!DB21) -> -1715.24 | DC21: =SUM(LARM:RM!DC21) -> 0 | DD21: =SUM(LARM:RM!DD21) -> -682.88 | ... EA21: =SUM(LARM:RM!EA21) -> 0 | EB21: =SUM(CW21:EA21) -> -7949.8 | EC21: =SUM(LARM:RM!EC21) -> 0 | ED21: =SUM(LARM:RM!ED21) -> 0 | EE21: =SUM(LARM:RM!EE21) -> 0 | EF21: =SUM(LARM:RM!EF21) -> -2005.31 | EG21: =SUM(LARM:RM!EG21) -> 0 | EH21: =SUM(LARM:RM!EH21) -> 0 | EI21: =SUM(LARM:RM!EI21) -> 0 | EJ21: =SUM(LARM:RM!EJ21) -> 0 | ... FG21: =SUM(LARM:RM!FG21) -> 0 | FH21: =SUM(EC21:FG21) -> -6502.56 | FI21: =SUM(LARM:RM!FI21) -> 0 | FJ21: =SUM(LARM:RM!FJ21) -> -518.98 | FK21: =SUM(LARM:RM!FK21) -> -536.4 | FL21: =SUM(LARM:RM!FL21) -> 0 | FM21: =SUM(LARM:RM!FM21) -> 0 | FN21: =SUM(LARM:RM!FN21) -> -386.3 | FO21: =SUM(LARM:RM!FO21) -> 0 | FP21: =SUM(LARM:RM!FP21) -> 0 | ... GM21: =SUM(LARM:RM!GM21) -> 0 | GN21: =SUM(FI21:GM21) -> -8110.67 | GO21: =SUM(LARM:RM!GO21) -> -398.57 | GP21: =SUM(LARM:RM!GP21) -> 0 | GQ21: =SUM(LARM:RM!GQ21) -> 0 | GR21: =SUM(LARM:RM!GR21) -> 0 | GS21: =SUM(LARM:RM!GS21) -> 0 | GT21: =SUM(LARM:RM!GT21) -> 0 | GU21: =SUM(LARM:RM!GU21) -> -1068.1 | GV21: =SUM(LARM:RM!GV21) -> -1306.92 | ... HS21: =SUM(LARM:RM!HS21) -> 0 | HT21: =SUM(GO21:HS21) -> -7661.79 | HU21: =SUM(LARM:RM!HU21) -> -417.32 | HV21: =SUM(LARM:RM!HV21) -> 0 | HW21: =SUM(LARM:RM!HW21) -> 0 | HX21: =SUM(LARM:RM!HX21) -> 0 | HY21: =SUM(LARM:RM!HY21) -> -768.02 | HZ21: =SUM(LARM:RM!HZ21) -> 0 | IA21: =SUM(LARM:RM!IA21) -> 0 | IB21: =SUM(LARM:RM!IB21) -> -1027.86 | ... IY21: =SUM(LARM:RM!IY21) -> 0 | IZ21: =SUM(HU21:IY21) -> -8653.22 | JA21: =SUM(LARM:RM!JA21) -> -896.91 | JB21: =SUM(LARM:RM!JB21) -> 0 | JC21: =SUM(LARM:RM!JC21) -> 0 | JD21: =SUM(LARM:RM!JD21) -> 0 | JE21: =SUM(LARM:RM!JE21) -> 0 | JF21: =SUM(LARM:RM!JF21) -> 0 | JG21: =SUM(LARM:RM!JG21) -> 0 | JH21: =SUM(LARM:RM!JH21) -> -387.39 | ... KE21: =SUM(LARM:RM!KE21) -> 0 | KF21: =SUM(JA21:KE21) -> -8872.97 | KG21: =SUM(LARM:RM!KG21) -> -100.06 | KH21: =SUM(LARM:RM!KH21) -> 0 | KI21: =SUM(LARM:RM!KI21) -> 0 | KJ21: =SUM(LARM:RM!KJ21) -> 0 | KK21: =SUM(LARM:RM!KK21) -> 0 | KL21: =SUM(LARM:RM!KL21) -> -810.54 | KM21: =SUM(LARM:RM!KM21) -> 0 | KN21: =SUM(LARM:RM!KN21) -> -2463.91 | ... LK21: =SUM(LARM:RM!LK21) -> 0 | LL21: =SUM(KG21:LK21) -> -8680.33 | LM21: =SUM(LARM:RM!LM21) -> 0 | LN21: =SUM(LARM:RM!LN21) -> 0 | LO21: =SUM(LARM:RM!LO21) -> -475.23 | LP21: =SUM(LARM:RM!LP21) -> 0 | LQ21: =SUM(LARM:RM!LQ21) -> -488.75 | LR21: =SUM(LARM:RM!LR21) -> 0 | LS21: =SUM(LARM:RM!LS21) -> 0 | LT21: =SUM(LARM:RM!LT21) -> 0 | ... MQ21: =SUM(LARM:RM!MQ21) -> 0 | MR21: =SUM(LM21:MQ21) -> -9424.26 | MS21: =SUM(LARM:RM!MS21) -> 0 | MT21: =SUM(LARM:RM!MT21) -> 0 | MU21: =SUM(LARM:RM!MU21) -> -910.42 | MV21: =SUM(LARM:RM!MV21) -> -150 | MW21: =SUM(LARM:RM!MW21) -> -621.57 | MX21: =SUM(LARM:RM!MX21) -> -310.05 | MY21: =SUM(LARM:RM!MY21) -> 0 | MZ21: =SUM(LARM:RM!MZ21) -> -410 | ... NW21: =SUM(LARM:RM!NW21) -> 0 | NX21: =SUM(MS21:NW21) -> -7829.66 | NZ21: =AJ21+BP21+CV21+EB21+FH21+GN21+HT21+IZ21+KF21+LL21+MR21+NX21 -> -102020.68 | OA21: =SUM(OI21:OP21) -> -56334.5 | OB21: =IF(OA21=0,"",((NZ21/OA21)-1)*-1) -> -0.81098048 | OG21: UTILIDADES E SERVICOS (3) | OI21: =SUM(LARM:RM!OI21) -> -4204.94 | OJ21: =SUM(LARM:RM!OJ21) -> -8275.42 | OK21: =SUM(LARM:RM!OK21) -> -9040.77 | OL21: =SUM(LARM:RM!OL21) -> -7889.33 | OM21: =SUM(LARM:RM!OM21) -> -5830.58 | ON21: =SUM(LARM:RM!ON21) -> -6999.93 | OO21: =SUM(LARM:RM!OO21) -> -6551.05 | OP21: =SUM(LARM:RM!OP21) -> -7542.48 | ... OT21: =SUM(LARM:RM!OT21) -> -6399.81 | OV21: =SUM(OI21:OT21) -> -86757.08
B22: 4.4 | C22: DESPESAS GERAIS/TERCEIROS (4) | E22: =SUM(LARM:RM!E22) -> 0 | F22: =SUM(LARM:RM!F22) -> -2880 | G22: =SUM(LARM:RM!G22) -> 0 | H22: =SUM(LARM:RM!H22) -> 0 | I22: =SUM(LARM:RM!I22) -> -958.74 | J22: =SUM(LARM:RM!J22) -> -500 | K22: =SUM(LARM:RM!K22) -> -2846 | L22: =SUM(LARM:RM!L22) -> -1001.87 | ... AI22: =SUM(LARM:RM!AI22) -> 0 | AJ22: =SUM(E22:AI22) -> -104190.97 | AK22: =SUM(LARM:RM!AK22) -> 0 | AL22: =SUM(LARM:RM!AL22) -> -8171.74 | AM22: =SUM(LARM:RM!AM22) -> -1022.64 | AN22: =SUM(LARM:RM!AN22) -> 0 | AO22: =SUM(LARM:RM!AO22) -> 0 | AP22: =SUM(LARM:RM!AP22) -> -5000 | AQ22: =SUM(LARM:RM!AQ22) -> 0 | AR22: =SUM(LARM:RM!AR22) -> 0 | ... BO22: =SUM(LARM:RM!BO22) -> 0 | BP22: =SUM(AK22:BO22) -> -66884.41 | BQ22: =SUM(LARM:RM!BQ22) -> 0 | BR22: =SUM(LARM:RM!BR22) -> -5859.08 | BS22: =SUM(LARM:RM!BS22) -> -3975.52 | BT22: =SUM(LARM:RM!BT22) -> 0 | BU22: =SUM(LARM:RM!BU22) -> 0 | BV22: =SUM(LARM:RM!BV22) -> -8001.8 | BW22: =SUM(LARM:RM!BW22) -> 0 | BX22: =SUM(LARM:RM!BX22) -> 0 | ... CU22: =SUM(LARM:RM!CU22) -> 0 | CV22: =SUM(BQ22:CU22) -> -84437.182 | CW22: =SUM(LARM:RM!CW22) -> -3019.78 | CX22: =SUM(LARM:RM!CX22) -> -771.7 | CY22: =SUM(LARM:RM!CY22) -> 0 | CZ22: =SUM(LARM:RM!CZ22) -> 0 | DA22: =SUM(LARM:RM!DA22) -> 0 | DB22: =SUM(LARM:RM!DB22) -> -5393.02 | DC22: =SUM(LARM:RM!DC22) -> 0 | DD22: =SUM(LARM:RM!DD22) -> -13994.03 | ... EA22: =SUM(LARM:RM!EA22) -> 0 | EB22: =SUM(CW22:EA22) -> -64251.31 | EC22: =SUM(LARM:RM!EC22) -> 0 | ED22: =SUM(LARM:RM!ED22) -> 0 | EE22: =SUM(LARM:RM!EE22) -> 0 | EF22: =SUM(LARM:RM!EF22) -> -1393.86 | EG22: =SUM(LARM:RM!EG22) -> 0 | EH22: =SUM(LARM:RM!EH22) -> -1018.24 | EI22: =SUM(LARM:RM!EI22) -> 0 | EJ22: =SUM(LARM:RM!EJ22) -> 0 | ... FG22: =SUM(LARM:RM!FG22) -> 0 | FH22: =SUM(EC22:FG22) -> -80509.79 | FI22: =SUM(LARM:RM!FI22) -> 0 | FJ22: =SUM(LARM:RM!FJ22) -> -4840.8 | FK22: =SUM(LARM:RM!FK22) -> 0 | FL22: =SUM(LARM:RM!FL22) -> 0 | FM22: =SUM(LARM:RM!FM22) -> 0 | FN22: =SUM(LARM:RM!FN22) -> -78.58 | FO22: =SUM(LARM:RM!FO22) -> 0 | FP22: =SUM(LARM:RM!FP22) -> 0 | ... GM22: =SUM(LARM:RM!GM22) -> 0 | GN22: =SUM(FI22:GM22) -> -75465.22 | GO22: =SUM(LARM:RM!GO22) -> -3340.5 | GP22: =SUM(LARM:RM!GP22) -> 0 | GQ22: =SUM(LARM:RM!GQ22) -> 0 | GR22: =SUM(LARM:RM!GR22) -> 0 | GS22: =SUM(LARM:RM!GS22) -> 0 | GT22: =SUM(LARM:RM!GT22) -> 0 | GU22: =SUM(LARM:RM!GU22) -> -1654.4 | GV22: =SUM(LARM:RM!GV22) -> -5000 | ... HS22: =SUM(LARM:RM!HS22) -> 0 | HT22: =SUM(GO22:HS22) -> -57221.49 | HU22: =SUM(LARM:RM!HU22) -> -24075.62 | HV22: =SUM(LARM:RM!HV22) -> 0 | HW22: =SUM(LARM:RM!HW22) -> 0 | HX22: =SUM(LARM:RM!HX22) -> -660.7 | HY22: =SUM(LARM:RM!HY22) -> -5950 | HZ22: =SUM(LARM:RM!HZ22) -> 0 | IA22: =SUM(LARM:RM!IA22) -> 0 | IB22: =SUM(LARM:RM!IB22) -> 0 | ... IY22: =SUM(LARM:RM!IY22) -> 0 | IZ22: =SUM(HU22:IY22) -> -113521.79 | JA22: =SUM(LARM:RM!JA22) -> -3830 | JB22: =SUM(LARM:RM!JB22) -> 0 | JC22: =SUM(LARM:RM!JC22) -> 0 | JD22: =SUM(LARM:RM!JD22) -> -5000 | JE22: =SUM(LARM:RM!JE22) -> -1310 | JF22: =SUM(LARM:RM!JF22) -> 0 | JG22: =SUM(LARM:RM!JG22) -> 0 | JH22: =SUM(LARM:RM!JH22) -> -32730.9 | ... KE22: =SUM(LARM:RM!KE22) -> 0 | KF22: =SUM(JA22:KE22) -> -77885.54 | KG22: =SUM(LARM:RM!KG22) -> -43127 | KH22: =SUM(LARM:RM!KH22) -> 0 | KI22: =SUM(LARM:RM!KI22) -> 0 | KJ22: =SUM(LARM:RM!KJ22) -> 0 | KK22: =SUM(LARM:RM!KK22) -> 0 | KL22: =SUM(LARM:RM!KL22) -> -5950 | KM22: =SUM(LARM:RM!KM22) -> 0 | KN22: =SUM(LARM:RM!KN22) -> -780 | ... LK22: =SUM(LARM:RM!LK22) -> 0 | LL22: =SUM(KG22:LK22) -> -99640.55 | LM22: =SUM(LARM:RM!LM22) -> 0 | LN22: =SUM(LARM:RM!LN22) -> 0 | LO22: =SUM(LARM:RM!LO22) -> -8233.6 | LP22: =SUM(LARM:RM!LP22) -> 0 | LQ22: =SUM(LARM:RM!LQ22) -> -1215 | LR22: =SUM(LARM:RM!LR22) -> -5000 | LS22: =SUM(LARM:RM!LS22) -> 0 | LT22: =SUM(LARM:RM!LT22) -> 0 | ... MQ22: =SUM(LARM:RM!MQ22) -> 0 | MR22: =SUM(LM22:MQ22) -> -51655.35 | MS22: =SUM(LARM:RM!MS22) -> -2550 | MT22: =SUM(LARM:RM!MT22) -> 0 | MU22: =SUM(LARM:RM!MU22) -> -1197.47 | MV22: =SUM(LARM:RM!MV22) -> 0 | MW22: =SUM(LARM:RM!MW22) -> -265 | MX22: =SUM(LARM:RM!MX22) -> 0 | MY22: =SUM(LARM:RM!MY22) -> 0 | MZ22: =SUM(LARM:RM!MZ22) -> 0 | ... NW22: =SUM(LARM:RM!NW22) -> 0 | NX22: =SUM(MS22:NW22) -> -96240.37 | NZ22: =AJ22+BP22+CV22+EB22+FH22+GN22+HT22+IZ22+KF22+LL22+MR22+NX22 -> -971903.97 | OA22: =SUM(OI22:OP22) -> -575353.81 | OB22: =IF(OA22=0,"",((NZ22/OA22)-1)*-1) -> -0.68922836 | OG22: DESPESAS GERAIS/TERCEIROS (4) | OI22: =SUM(LARM:RM!OI22) -> -69833.83 | OJ22: =SUM(LARM:RM!OJ22) -> -71248.07 | OK22: =SUM(LARM:RM!OK22) -> -60634.41 | OL22: =SUM(LARM:RM!OL22) -> -62994.01 | OM22: =SUM(LARM:RM!OM22) -> -83034.99 | ON22: =SUM(LARM:RM!ON22) -> -60465.22 | OO22: =SUM(LARM:RM!OO22) -> -55421.49 | OP22: =SUM(LARM:RM!OP22) -> -111721.79 | ... OT22: =SUM(LARM:RM!OT22) -> -94440.37 | OV22: =SUM(OI22:OT22) -> -893575.62
B23: 4.5 | C23: SERVICOS PROFISSIONAIS (5) | E23: =SUM(LARM:RM!E23) -> 0 | F23: =SUM(LARM:RM!F23) -> 0 | G23: =SUM(LARM:RM!G23) -> 0 | H23: =SUM(LARM:RM!H23) -> 0 | I23: =SUM(LARM:RM!I23) -> -210.5 | J23: =SUM(LARM:RM!J23) -> 0 | K23: =SUM(LARM:RM!K23) -> 0 | L23: =SUM(LARM:RM!L23) -> 0 | ... AI23: =SUM(LARM:RM!AI23) -> 0 | AJ23: =SUM(E23:AI23) -> -22781.98 | AK23: =SUM(LARM:RM!AK23) -> 0 | AL23: =SUM(LARM:RM!AL23) -> 0 | AM23: =SUM(LARM:RM!AM23) -> 0 | AN23: =SUM(LARM:RM!AN23) -> 0 | AO23: =SUM(LARM:RM!AO23) -> -210.5 | AP23: =SUM(LARM:RM!AP23) -> 0 | AQ23: =SUM(LARM:RM!AQ23) -> 0 | AR23: =SUM(LARM:RM!AR23) -> 0 | ... BO23: =SUM(LARM:RM!BO23) -> 0 | BP23: =SUM(AK23:BO23) -> -21287.14 | BQ23: =SUM(LARM:RM!BQ23) -> 0 | BR23: =SUM(LARM:RM!BR23) -> 0 | BS23: =SUM(LARM:RM!BS23) -> 0 | BT23: =SUM(LARM:RM!BT23) -> 0 | BU23: =SUM(LARM:RM!BU23) -> -210.5 | BV23: =SUM(LARM:RM!BV23) -> 0 | BW23: =SUM(LARM:RM!BW23) -> 0 | BX23: =SUM(LARM:RM!BX23) -> 0 | ... CU23: =SUM(LARM:RM!CU23) -> 0 | CV23: =SUM(BQ23:CU23) -> -59421.56 | CW23: =SUM(LARM:RM!CW23) -> -19452.8 | CX23: =SUM(LARM:RM!CX23) -> 0 | CY23: =SUM(LARM:RM!CY23) -> 0 | CZ23: =SUM(LARM:RM!CZ23) -> 0 | DA23: =SUM(LARM:RM!DA23) -> 0 | DB23: =SUM(LARM:RM!DB23) -> -4210.5 | DC23: =SUM(LARM:RM!DC23) -> 0 | DD23: =SUM(LARM:RM!DD23) -> 0 | ... EA23: =SUM(LARM:RM!EA23) -> 0 | EB23: =SUM(CW23:EA23) -> -55465.64 | EC23: =SUM(LARM:RM!EC23) -> 0 | ED23: =SUM(LARM:RM!ED23) -> 0 | EE23: =SUM(LARM:RM!EE23) -> 0 | EF23: =SUM(LARM:RM!EF23) -> 0 | EG23: =SUM(LARM:RM!EG23) -> -1157.17 | EH23: =SUM(LARM:RM!EH23) -> -2232.8 | EI23: =SUM(LARM:RM!EI23) -> 0 | EJ23: =SUM(LARM:RM!EJ23) -> 0 | ... FG23: =SUM(LARM:RM!FG23) -> 0 | FH23: =SUM(EC23:FG23) -> -31471.09 | FI23: =SUM(LARM:RM!FI23) -> 0 | FJ23: =SUM(LARM:RM!FJ23) -> 0 | FK23: =SUM(LARM:RM!FK23) -> 0 | FL23: =SUM(LARM:RM!FL23) -> 0 | FM23: =SUM(LARM:RM!FM23) -> -204.44 | FN23: =SUM(LARM:RM!FN23) -> 0 | FO23: =SUM(LARM:RM!FO23) -> 0 | FP23: =SUM(LARM:RM!FP23) -> 0 | ... GM23: =SUM(LARM:RM!GM23) -> 0 | GN23: =SUM(FI23:GM23) -> -60219.24 | GO23: =SUM(LARM:RM!GO23) -> 0 | GP23: =SUM(LARM:RM!GP23) -> 0 | GQ23: =SUM(LARM:RM!GQ23) -> 0 | GR23: =SUM(LARM:RM!GR23) -> 0 | GS23: =SUM(LARM:RM!GS23) -> 0 | GT23: =SUM(LARM:RM!GT23) -> 0 | GU23: =SUM(LARM:RM!GU23) -> -392.22 | GV23: =SUM(LARM:RM!GV23) -> 0 | ... HS23: =SUM(LARM:RM!HS23) -> 0 | HT23: =SUM(GO23:HS23) -> -20911.55 | HU23: =SUM(LARM:RM!HU23) -> 0 | HV23: =SUM(LARM:RM!HV23) -> 0 | HW23: =SUM(LARM:RM!HW23) -> 0 | HX23: =SUM(LARM:RM!HX23) -> 0 | HY23: =SUM(LARM:RM!HY23) -> -204.44 | HZ23: =SUM(LARM:RM!HZ23) -> 0 | IA23: =SUM(LARM:RM!IA23) -> 0 | IB23: =SUM(LARM:RM!IB23) -> 0 | ... IY23: =SUM(LARM:RM!IY23) -> 0 | IZ23: =SUM(HU23:IY23) -> -30741.87 | JA23: =SUM(LARM:RM!JA23) -> 0 | JB23: =SUM(LARM:RM!JB23) -> 0 | JC23: =SUM(LARM:RM!JC23) -> 0 | JD23: =SUM(LARM:RM!JD23) -> 0 | JE23: =SUM(LARM:RM!JE23) -> -210.5 | JF23: =SUM(LARM:RM!JF23) -> 0 | JG23: =SUM(LARM:RM!JG23) -> 0 | JH23: =SUM(LARM:RM!JH23) -> 0 | ... KE23: =SUM(LARM:RM!KE23) -> 0 | KF23: =SUM(JA23:KE23) -> -23309.48 | KG23: =SUM(LARM:RM!KG23) -> -31 | KH23: =SUM(LARM:RM!KH23) -> 0 | KI23: =SUM(LARM:RM!KI23) -> -109.9 | KJ23: =SUM(LARM:RM!KJ23) -> 0 | KK23: =SUM(LARM:RM!KK23) -> 0 | KL23: =SUM(LARM:RM!KL23) -> -375.2 | KM23: =SUM(LARM:RM!KM23) -> 0 | KN23: =SUM(LARM:RM!KN23) -> 0 | ... LK23: =SUM(LARM:RM!LK23) -> 0 | LL23: =SUM(KG23:LK23) -> -55549.25 | LM23: =SUM(LARM:RM!LM23) -> 0 | LN23: =SUM(LARM:RM!LN23) -> 0 | LO23: =SUM(LARM:RM!LO23) -> -2313.66 | LP23: =SUM(LARM:RM!LP23) -> 0 | LQ23: =SUM(LARM:RM!LQ23) -> -210.5 | LR23: =SUM(LARM:RM!LR23) -> 0 | LS23: =SUM(LARM:RM!LS23) -> 0 | LT23: =SUM(LARM:RM!LT23) -> 0 | ... MQ23: =SUM(LARM:RM!MQ23) -> 0 | MR23: =SUM(LM23:MQ23) -> -20915.715 | MS23: =SUM(LARM:RM!MS23) -> 0 | MT23: =SUM(LARM:RM!MT23) -> 0 | MU23: =SUM(LARM:RM!MU23) -> -67.87 | MV23: =SUM(LARM:RM!MV23) -> 0 | MW23: =SUM(LARM:RM!MW23) -> -204.44 | MX23: =SUM(LARM:RM!MX23) -> 0 | MY23: =SUM(LARM:RM!MY23) -> 0 | MZ23: =SUM(LARM:RM!MZ23) -> 0 | ... NW23: =SUM(LARM:RM!NW23) -> 0 | NX23: =SUM(MS23:NW23) -> -30550.175 | NZ23: =AJ23+BP23+CV23+EB23+FH23+GN23+HT23+IZ23+KF23+LL23+MR23+NX23 -> -432624.69 | OA23: =SUM(OI23:OP23) -> -309240.33 | OB23: =IF(OA23=0,"",((NZ23/OA23)-1)*-1) -> -0.39899181 | OG23: SERVICOS PROFISSIONAIS (5) | OI23: =SUM(LARM:RM!OI23) -> -28251.06 | OJ23: =SUM(LARM:RM!OJ23) -> -27745 | OK23: =SUM(LARM:RM!OK23) -> -80255.5 | OL23: =SUM(LARM:RM!OL23) -> -30597.75 | OM23: =SUM(LARM:RM!OM23) -> -30518.36 | ON23: =SUM(LARM:RM!ON23) -> -60219.24 | OO23: =SUM(LARM:RM!OO23) -> -20911.55 | OP23: =SUM(LARM:RM!OP23) -> -30741.87 | ... OT23: =SUM(LARM:RM!OT23) -> -30550.175 | OV23: =SUM(OI23:OT23) -> -439564.95
B24: 4.6 | C24: DESPESAS DE VIAGENS (6) | E24: =SUM(LARM:RM!E24) -> 0 | F24: =SUM(LARM:RM!F24) -> -2417.3 | G24: =SUM(LARM:RM!G24) -> 0 | H24: =SUM(LARM:RM!H24) -> 0 | I24: =SUM(LARM:RM!I24) -> 0 | J24: =SUM(LARM:RM!J24) -> 0 | K24: =SUM(LARM:RM!K24) -> 0 | L24: =SUM(LARM:RM!L24) -> -927.93 | ... AI24: =SUM(LARM:RM!AI24) -> 0 | AJ24: =SUM(E24:AI24) -> -4959.07 | AK24: =SUM(LARM:RM!AK24) -> 0 | AL24: =SUM(LARM:RM!AL24) -> 0 | AM24: =SUM(LARM:RM!AM24) -> 0 | AN24: =SUM(LARM:RM!AN24) -> 0 | AO24: =SUM(LARM:RM!AO24) -> 0 | AP24: =SUM(LARM:RM!AP24) -> 0 | AQ24: =SUM(LARM:RM!AQ24) -> 0 | AR24: =SUM(LARM:RM!AR24) -> 0 | ... BO24: =SUM(LARM:RM!BO24) -> 0 | BP24: =SUM(AK24:BO24) -> -1651.38 | BQ24: =SUM(LARM:RM!BQ24) -> 0 | BR24: =SUM(LARM:RM!BR24) -> 0 | BS24: =SUM(LARM:RM!BS24) -> 0 | BT24: =SUM(LARM:RM!BT24) -> 0 | BU24: =SUM(LARM:RM!BU24) -> 0 | BV24: =SUM(LARM:RM!BV24) -> 0 | BW24: =SUM(LARM:RM!BW24) -> 0 | BX24: =SUM(LARM:RM!BX24) -> 0 | ... CU24: =SUM(LARM:RM!CU24) -> 0 | CV24: =SUM(BQ24:CU24) -> -4009.65 | CW24: =SUM(LARM:RM!CW24) -> 0 | CX24: =SUM(LARM:RM!CX24) -> 0 | CY24: =SUM(LARM:RM!CY24) -> 0 | CZ24: =SUM(LARM:RM!CZ24) -> 0 | DA24: =SUM(LARM:RM!DA24) -> 0 | DB24: =SUM(LARM:RM!DB24) -> 0 | DC24: =SUM(LARM:RM!DC24) -> 0 | DD24: =SUM(LARM:RM!DD24) -> 0 | ... EA24: =SUM(LARM:RM!EA24) -> 0 | EB24: =SUM(CW24:EA24) -> -12958.69 | EC24: =SUM(LARM:RM!EC24) -> 0 | ED24: =SUM(LARM:RM!ED24) -> 0 | EE24: =SUM(LARM:RM!EE24) -> 0 | EF24: =SUM(LARM:RM!EF24) -> 0 | EG24: =SUM(LARM:RM!EG24) -> 0 | EH24: =SUM(LARM:RM!EH24) -> 0 | EI24: =SUM(LARM:RM!EI24) -> 0 | EJ24: =SUM(LARM:RM!EJ24) -> 0 | ... FG24: =SUM(LARM:RM!FG24) -> 0 | FH24: =SUM(EC24:FG24) -> -825.9 | FI24: =SUM(LARM:RM!FI24) -> 0 | FJ24: =SUM(LARM:RM!FJ24) -> 0 | FK24: =SUM(LARM:RM!FK24) -> 0 | FL24: =SUM(LARM:RM!FL24) -> 0 | FM24: =SUM(LARM:RM!FM24) -> 0 | FN24: =SUM(LARM:RM!FN24) -> 0 | FO24: =SUM(LARM:RM!FO24) -> 0 | FP24: =SUM(LARM:RM!FP24) -> 0 | ... GM24: =SUM(LARM:RM!GM24) -> 0 | GN24: =SUM(FI24:GM24) -> -5581.87 | GO24: =SUM(LARM:RM!GO24) -> 0 | GP24: =SUM(LARM:RM!GP24) -> 0 | GQ24: =SUM(LARM:RM!GQ24) -> 0 | GR24: =SUM(LARM:RM!GR24) -> 0 | GS24: =SUM(LARM:RM!GS24) -> 0 | GT24: =SUM(LARM:RM!GT24) -> 0 | GU24: =SUM(LARM:RM!GU24) -> -2907.89 | GV24: =SUM(LARM:RM!GV24) -> 0 | ... HS24: =SUM(LARM:RM!HS24) -> 0 | HT24: =SUM(GO24:HS24) -> -4070.52 | HU24: =SUM(LARM:RM!HU24) -> 0 | HV24: =SUM(LARM:RM!HV24) -> 0 | HW24: =SUM(LARM:RM!HW24) -> 0 | HX24: =SUM(LARM:RM!HX24) -> 0 | HY24: =SUM(LARM:RM!HY24) -> 0 | HZ24: =SUM(LARM:RM!HZ24) -> 0 | IA24: =SUM(LARM:RM!IA24) -> 0 | IB24: =SUM(LARM:RM!IB24) -> 0 | ... IY24: =SUM(LARM:RM!IY24) -> 0 | IZ24: =SUM(HU24:IY24) -> -7120.83 | JA24: =SUM(LARM:RM!JA24) -> 0 | JB24: =SUM(LARM:RM!JB24) -> 0 | JC24: =SUM(LARM:RM!JC24) -> 0 | JD24: =SUM(LARM:RM!JD24) -> 0 | JE24: =SUM(LARM:RM!JE24) -> 0 | JF24: =SUM(LARM:RM!JF24) -> 0 | JG24: =SUM(LARM:RM!JG24) -> 0 | JH24: =SUM(LARM:RM!JH24) -> 0 | ... KE24: =SUM(LARM:RM!KE24) -> 0 | KF24: =SUM(JA24:KE24) -> -1159.41 | KG24: =SUM(LARM:RM!KG24) -> -3225.71 | KH24: =SUM(LARM:RM!KH24) -> 0 | KI24: =SUM(LARM:RM!KI24) -> 0 | KJ24: =SUM(LARM:RM!KJ24) -> 0 | KK24: =SUM(LARM:RM!KK24) -> 0 | KL24: =SUM(LARM:RM!KL24) -> 0 | KM24: =SUM(LARM:RM!KM24) -> 0 | KN24: =SUM(LARM:RM!KN24) -> 0 | ... LK24: =SUM(LARM:RM!LK24) -> 0 | LL24: =SUM(KG24:LK24) -> -8697.18 | LM24: =SUM(LARM:RM!LM24) -> 0 | LN24: =SUM(LARM:RM!LN24) -> 0 | LO24: =SUM(LARM:RM!LO24) -> 0 | LP24: =SUM(LARM:RM!LP24) -> 0 | LQ24: =SUM(LARM:RM!LQ24) -> 0 | LR24: =SUM(LARM:RM!LR24) -> 0 | LS24: =SUM(LARM:RM!LS24) -> 0 | LT24: =SUM(LARM:RM!LT24) -> 0 | ... MQ24: =SUM(LARM:RM!MQ24) -> 0 | MR24: =SUM(LM24:MQ24) -> 0 | MS24: =SUM(LARM:RM!MS24) -> 0 | MT24: =SUM(LARM:RM!MT24) -> 0 | MU24: =SUM(LARM:RM!MU24) -> 0 | MV24: =SUM(LARM:RM!MV24) -> 0 | MW24: =SUM(LARM:RM!MW24) -> 0 | MX24: =SUM(LARM:RM!MX24) -> 0 | MY24: =SUM(LARM:RM!MY24) -> 0 | MZ24: =SUM(LARM:RM!MZ24) -> 0 | ... NW24: =SUM(LARM:RM!NW24) -> 0 | NX24: =SUM(MS24:NW24) -> -1095.55 | NZ24: =AJ24+BP24+CV24+EB24+FH24+GN24+HT24+IZ24+KF24+LL24+MR24+NX24 -> -52130.05 | OA24: =SUM(OI24:OP24) -> -25781.55 | OB24: =IF(OA24=0,"",((NZ24/OA24)-1)*-1) -> -1.0219905 | OG24: DESPESAS DE VIAGENS (6) | OI24: =SUM(LARM:RM!OI24) -> -4261.96 | OJ24: =SUM(LARM:RM!OJ24) -> -1152.79 | OK24: =SUM(LARM:RM!OK24) -> -1619.94 | OL24: =SUM(LARM:RM!OL24) -> -1147.74 | OM24: =SUM(LARM:RM!OM24) -> -825.9 | ON24: =SUM(LARM:RM!ON24) -> -5581.87 | OO24: =SUM(LARM:RM!OO24) -> -4070.52 | OP24: =SUM(LARM:RM!OP24) -> -7120.83 | ... OT24: =SUM(LARM:RM!OT24) -> -1095.55 | OV24: =SUM(OI24:OT24) -> -36733.69
B25: 4.7 | C25: DESPESAS COM VEÍCULOS (7) | E25: =SUM(LARM:RM!E25) -> 0 | F25: =SUM(LARM:RM!F25) -> -1527.75 | G25: =SUM(LARM:RM!G25) -> 0 | H25: =SUM(LARM:RM!H25) -> 0 | I25: =SUM(LARM:RM!I25) -> 0 | J25: =SUM(LARM:RM!J25) -> 0 | K25: =SUM(LARM:RM!K25) -> 0 | L25: =SUM(LARM:RM!L25) -> -2302.2 | ... AI25: =SUM(LARM:RM!AI25) -> 0 | AJ25: =SUM(E25:AI25) -> -13244.43 | AK25: =SUM(LARM:RM!AK25) -> 0 | AL25: =SUM(LARM:RM!AL25) -> 0 | AM25: =SUM(LARM:RM!AM25) -> 0 | AN25: =SUM(LARM:RM!AN25) -> 0 | AO25: =SUM(LARM:RM!AO25) -> 0 | AP25: =SUM(LARM:RM!AP25) -> 0 | AQ25: =SUM(LARM:RM!AQ25) -> 0 | AR25: =SUM(LARM:RM!AR25) -> 0 | ... BO25: =SUM(LARM:RM!BO25) -> 0 | BP25: =SUM(AK25:BO25) -> -9617.46 | BQ25: =SUM(LARM:RM!BQ25) -> 0 | BR25: =SUM(LARM:RM!BR25) -> -2334 | BS25: =SUM(LARM:RM!BS25) -> 0 | BT25: =SUM(LARM:RM!BT25) -> 0 | BU25: =SUM(LARM:RM!BU25) -> 0 | BV25: =SUM(LARM:RM!BV25) -> 0 | BW25: =SUM(LARM:RM!BW25) -> 0 | BX25: =SUM(LARM:RM!BX25) -> 0 | ... CU25: =SUM(LARM:RM!CU25) -> 0 | CV25: =SUM(BQ25:CU25) -> -5799.85 | CW25: =SUM(LARM:RM!CW25) -> 0 | CX25: =SUM(LARM:RM!CX25) -> 0 | CY25: =SUM(LARM:RM!CY25) -> 0 | CZ25: =SUM(LARM:RM!CZ25) -> 0 | DA25: =SUM(LARM:RM!DA25) -> 0 | DB25: =SUM(LARM:RM!DB25) -> 0 | DC25: =SUM(LARM:RM!DC25) -> 0 | DD25: =SUM(LARM:RM!DD25) -> 0 | ... EA25: =SUM(LARM:RM!EA25) -> 0 | EB25: =SUM(CW25:EA25) -> -5191.87 | EC25: =SUM(LARM:RM!EC25) -> 0 | ED25: =SUM(LARM:RM!ED25) -> 0 | EE25: =SUM(LARM:RM!EE25) -> 0 | EF25: =SUM(LARM:RM!EF25) -> 0 | EG25: =SUM(LARM:RM!EG25) -> 0 | EH25: =SUM(LARM:RM!EH25) -> 0 | EI25: =SUM(LARM:RM!EI25) -> 0 | EJ25: =SUM(LARM:RM!EJ25) -> 0 | ... FG25: =SUM(LARM:RM!FG25) -> 0 | FH25: =SUM(EC25:FG25) -> -1870.32 | FI25: =SUM(LARM:RM!FI25) -> 0 | FJ25: =SUM(LARM:RM!FJ25) -> -1717.42 | FK25: =SUM(LARM:RM!FK25) -> 0 | FL25: =SUM(LARM:RM!FL25) -> 0 | FM25: =SUM(LARM:RM!FM25) -> 0 | FN25: =SUM(LARM:RM!FN25) -> 0 | FO25: =SUM(LARM:RM!FO25) -> 0 | FP25: =SUM(LARM:RM!FP25) -> 0 | ... GM25: =SUM(LARM:RM!GM25) -> 0 | GN25: =SUM(FI25:GM25) -> -5948.61 | GO25: =SUM(LARM:RM!GO25) -> 0 | GP25: =SUM(LARM:RM!GP25) -> 0 | GQ25: =SUM(LARM:RM!GQ25) -> 0 | GR25: =SUM(LARM:RM!GR25) -> 0 | GS25: =SUM(LARM:RM!GS25) -> 0 | GT25: =SUM(LARM:RM!GT25) -> 0 | GU25: =SUM(LARM:RM!GU25) -> 0 | GV25: =SUM(LARM:RM!GV25) -> 0 | ... HS25: =SUM(LARM:RM!HS25) -> 0 | HT25: =SUM(GO25:HS25) -> -5255.61 | HU25: =SUM(LARM:RM!HU25) -> 0 | HV25: =SUM(LARM:RM!HV25) -> 0 | HW25: =SUM(LARM:RM!HW25) -> 0 | HX25: =SUM(LARM:RM!HX25) -> 0 | HY25: =SUM(LARM:RM!HY25) -> 0 | HZ25: =SUM(LARM:RM!HZ25) -> 0 | IA25: =SUM(LARM:RM!IA25) -> 0 | IB25: =SUM(LARM:RM!IB25) -> 0 | ... IY25: =SUM(LARM:RM!IY25) -> 0 | IZ25: =SUM(HU25:IY25) -> -1265.19 | JA25: =SUM(LARM:RM!JA25) -> 0 | JB25: =SUM(LARM:RM!JB25) -> -388.2 | JC25: =SUM(LARM:RM!JC25) -> 0 | JD25: =SUM(LARM:RM!JD25) -> 0 | JE25: =SUM(LARM:RM!JE25) -> 0 | JF25: =SUM(LARM:RM!JF25) -> 0 | JG25: =SUM(LARM:RM!JG25) -> 0 | JH25: =SUM(LARM:RM!JH25) -> 0 | ... KE25: =SUM(LARM:RM!KE25) -> 0 | KF25: =SUM(JA25:KE25) -> -1653.39 | KG25: =SUM(LARM:RM!KG25) -> 0 | KH25: =SUM(LARM:RM!KH25) -> 0 | KI25: =SUM(LARM:RM!KI25) -> 0 | KJ25: =SUM(LARM:RM!KJ25) -> 0 | KK25: =SUM(LARM:RM!KK25) -> 0 | KL25: =SUM(LARM:RM!KL25) -> -379.96 | KM25: =SUM(LARM:RM!KM25) -> 0 | KN25: =SUM(LARM:RM!KN25) -> 0 | ... LK25: =SUM(LARM:RM!LK25) -> 0 | LL25: =SUM(KG25:LK25) -> -1645.15 | LM25: =SUM(LARM:RM!LM25) -> 0 | LN25: =SUM(LARM:RM!LN25) -> 0 | LO25: =SUM(LARM:RM!LO25) -> 0 | LP25: =SUM(LARM:RM!LP25) -> 0 | LQ25: =SUM(LARM:RM!LQ25) -> 0 | LR25: =SUM(LARM:RM!LR25) -> 0 | LS25: =SUM(LARM:RM!LS25) -> 0 | LT25: =SUM(LARM:RM!LT25) -> 0 | ... MQ25: =SUM(LARM:RM!MQ25) -> 0 | MR25: =SUM(LM25:MQ25) -> -4616.3 | MS25: =SUM(LARM:RM!MS25) -> 0 | MT25: =SUM(LARM:RM!MT25) -> 0 | MU25: =SUM(LARM:RM!MU25) -> 0 | MV25: =SUM(LARM:RM!MV25) -> 0 | MW25: =SUM(LARM:RM!MW25) -> 0 | MX25: =SUM(LARM:RM!MX25) -> 0 | MY25: =SUM(LARM:RM!MY25) -> 0 | MZ25: =SUM(LARM:RM!MZ25) -> 0 | ... NW25: =SUM(LARM:RM!NW25) -> 0 | NX25: =SUM(MS25:NW25) -> -3300.55 | NZ25: =AJ25+BP25+CV25+EB25+FH25+GN25+HT25+IZ25+KF25+LL25+MR25+NX25 -> -59408.73 | OA25: =SUM(OI25:OP25) -> -53338.04 | OB25: =IF(OA25=0,"",((NZ25/OA25)-1)*-1) -> -0.11381539 | OG25: DESPESAS COM VEÍCULOS (7) | OI25: =SUM(LARM:RM!OI25) -> -9735.06 | OJ25: =SUM(LARM:RM!OJ25) -> -12833.61 | OK25: =SUM(LARM:RM!OK25) -> -4372.5 | OL25: =SUM(LARM:RM!OL25) -> -7838.29 | OM25: =SUM(LARM:RM!OM25) -> -6089.17 | ON25: =SUM(LARM:RM!ON25) -> -5948.61 | OO25: =SUM(LARM:RM!OO25) -> -5255.61 | OP25: =SUM(LARM:RM!OP25) -> -1265.19 | ... OT25: =SUM(LARM:RM!OT25) -> -3300.55 | OV25: =SUM(OI25:OT25) -> -64553.43
B26: 4.8 | C26: DESPESAS COMERCIAIS (8) | E26: =SUM(LARM:RM!E26) -> 0 | F26: =SUM(LARM:RM!F26) -> 0 | G26: =SUM(LARM:RM!G26) -> 0 | H26: =SUM(LARM:RM!H26) -> 0 | I26: =SUM(LARM:RM!I26) -> 0 | J26: =SUM(LARM:RM!J26) -> 0 | K26: =SUM(LARM:RM!K26) -> -7426.81 | L26: =SUM(LARM:RM!L26) -> -14191.92 | ... AI26: =SUM(LARM:RM!AI26) -> 0 | AJ26: =SUM(E26:AI26) -> -32955.32 | AK26: =SUM(LARM:RM!AK26) -> 0 | AL26: =SUM(LARM:RM!AL26) -> 0 | AM26: =SUM(LARM:RM!AM26) -> 0 | AN26: =SUM(LARM:RM!AN26) -> 0 | AO26: =SUM(LARM:RM!AO26) -> -9711.19 | AP26: =SUM(LARM:RM!AP26) -> 0 | AQ26: =SUM(LARM:RM!AQ26) -> 0 | AR26: =SUM(LARM:RM!AR26) -> 0 | ... BO26: =SUM(LARM:RM!BO26) -> 0 | BP26: =SUM(AK26:BO26) -> -25184.89 | BQ26: =SUM(LARM:RM!BQ26) -> 0 | BR26: =SUM(LARM:RM!BR26) -> -467.41 | BS26: =SUM(LARM:RM!BS26) -> 0 | BT26: =SUM(LARM:RM!BT26) -> 0 | BU26: =SUM(LARM:RM!BU26) -> -8698.48 | BV26: =SUM(LARM:RM!BV26) -> -9993.71 | BW26: =SUM(LARM:RM!BW26) -> 0 | BX26: =SUM(LARM:RM!BX26) -> 0 | ... CU26: =SUM(LARM:RM!CU26) -> 0 | CV26: =SUM(BQ26:CU26) -> -28409.16 | CW26: =SUM(LARM:RM!CW26) -> 0 | CX26: =SUM(LARM:RM!CX26) -> 0 | CY26: =SUM(LARM:RM!CY26) -> 0 | CZ26: =SUM(LARM:RM!CZ26) -> 0 | DA26: =SUM(LARM:RM!DA26) -> 0 | DB26: =SUM(LARM:RM!DB26) -> -3500 | DC26: =SUM(LARM:RM!DC26) -> 0 | DD26: =SUM(LARM:RM!DD26) -> 0 | ... EA26: =SUM(LARM:RM!EA26) -> 0 | EB26: =SUM(CW26:EA26) -> -30206.22 | EC26: =SUM(LARM:RM!EC26) -> 0 | ED26: =SUM(LARM:RM!ED26) -> 0 | EE26: =SUM(LARM:RM!EE26) -> 0 | EF26: =SUM(LARM:RM!EF26) -> 0 | EG26: =SUM(LARM:RM!EG26) -> 0 | EH26: =SUM(LARM:RM!EH26) -> -13234.26 | EI26: =SUM(LARM:RM!EI26) -> 0 | EJ26: =SUM(LARM:RM!EJ26) -> 0 | ... FG26: =SUM(LARM:RM!FG26) -> 0 | FH26: =SUM(EC26:FG26) -> -51771.22 | FI26: =SUM(LARM:RM!FI26) -> 0 | FJ26: =SUM(LARM:RM!FJ26) -> 0 | FK26: =SUM(LARM:RM!FK26) -> 0 | FL26: =SUM(LARM:RM!FL26) -> 0 | FM26: =SUM(LARM:RM!FM26) -> 0 | FN26: =SUM(LARM:RM!FN26) -> 0 | FO26: =SUM(LARM:RM!FO26) -> 0 | FP26: =SUM(LARM:RM!FP26) -> 0 | ... GM26: =SUM(LARM:RM!GM26) -> 0 | GN26: =SUM(FI26:GM26) -> -42065.89 | GO26: =SUM(LARM:RM!GO26) -> 0 | GP26: =SUM(LARM:RM!GP26) -> 0 | GQ26: =SUM(LARM:RM!GQ26) -> 0 | GR26: =SUM(LARM:RM!GR26) -> 0 | GS26: =SUM(LARM:RM!GS26) -> 0 | GT26: =SUM(LARM:RM!GT26) -> 0 | GU26: =SUM(LARM:RM!GU26) -> -3500 | GV26: =SUM(LARM:RM!GV26) -> 0 | ... HS26: =SUM(LARM:RM!HS26) -> 0 | HT26: =SUM(GO26:HS26) -> -42036.96 | HU26: =SUM(LARM:RM!HU26) -> 0 | HV26: =SUM(LARM:RM!HV26) -> 0 | HW26: =SUM(LARM:RM!HW26) -> 0 | HX26: =SUM(LARM:RM!HX26) -> 0 | HY26: =SUM(LARM:RM!HY26) -> 0 | HZ26: =SUM(LARM:RM!HZ26) -> 0 | IA26: =SUM(LARM:RM!IA26) -> 0 | IB26: =SUM(LARM:RM!IB26) -> 0 | ... IY26: =SUM(LARM:RM!IY26) -> 0 | IZ26: =SUM(HU26:IY26) -> -42143.25 | JA26: =SUM(LARM:RM!JA26) -> 0 | JB26: =SUM(LARM:RM!JB26) -> 0 | JC26: =SUM(LARM:RM!JC26) -> 0 | JD26: =SUM(LARM:RM!JD26) -> 0 | JE26: =SUM(LARM:RM!JE26) -> -3500 | JF26: =SUM(LARM:RM!JF26) -> 0 | JG26: =SUM(LARM:RM!JG26) -> 0 | JH26: =SUM(LARM:RM!JH26) -> 0 | ... KE26: =SUM(LARM:RM!KE26) -> 0 | KF26: =SUM(JA26:KE26) -> -42310.18 | KG26: =SUM(LARM:RM!KG26) -> 0 | KH26: =SUM(LARM:RM!KH26) -> 0 | KI26: =SUM(LARM:RM!KI26) -> 0 | KJ26: =SUM(LARM:RM!KJ26) -> 0 | KK26: =SUM(LARM:RM!KK26) -> 0 | KL26: =SUM(LARM:RM!KL26) -> -3500 | KM26: =SUM(LARM:RM!KM26) -> 0 | KN26: =SUM(LARM:RM!KN26) -> 0 | ... LK26: =SUM(LARM:RM!LK26) -> 0 | LL26: =SUM(KG26:LK26) -> -42067.12 | LM26: =SUM(LARM:RM!LM26) -> 0 | LN26: =SUM(LARM:RM!LN26) -> 0 | LO26: =SUM(LARM:RM!LO26) -> 0 | LP26: =SUM(LARM:RM!LP26) -> 0 | LQ26: =SUM(LARM:RM!LQ26) -> 0 | LR26: =SUM(LARM:RM!LR26) -> 0 | LS26: =SUM(LARM:RM!LS26) -> -3500 | LT26: =SUM(LARM:RM!LT26) -> 0 | ... MQ26: =SUM(LARM:RM!MQ26) -> 0 | MR26: =SUM(LM26:MQ26) -> -37181.35 | MS26: =SUM(LARM:RM!MS26) -> 0 | MT26: =SUM(LARM:RM!MT26) -> 0 | MU26: =SUM(LARM:RM!MU26) -> 0 | MV26: =SUM(LARM:RM!MV26) -> 0 | MW26: =SUM(LARM:RM!MW26) -> 0 | MX26: =SUM(LARM:RM!MX26) -> 0 | MY26: =SUM(LARM:RM!MY26) -> 0 | MZ26: =SUM(LARM:RM!MZ26) -> 0 | ... NW26: =SUM(LARM:RM!NW26) -> 0 | NX26: =SUM(MS26:NW26) -> -46901.97 | NZ26: =AJ26+BP26+CV26+EB26+FH26+GN26+HT26+IZ26+KF26+LL26+MR26+NX26 -> -463233.53 | OA26: =SUM(OI26:OP26) -> -336566.28 | OB26: =IF(OA26=0,"",((NZ26/OA26)-1)*-1) -> -0.37635158 | OG26: DESPESAS COMERCIAIS (8) | OI26: =SUM(LARM:RM!OI26) -> -42036.96 | OJ26: =SUM(LARM:RM!OJ26) -> -42125.43 | OK26: =SUM(LARM:RM!OK26) -> -42078.05 | OL26: =SUM(LARM:RM!OL26) -> -42042.78 | OM26: =SUM(LARM:RM!OM26) -> -42036.96 | ON26: =SUM(LARM:RM!ON26) -> -42065.89 | OO26: =SUM(LARM:RM!OO26) -> -42036.96 | OP26: =SUM(LARM:RM!OP26) -> -42143.25 | ... OT26: =SUM(LARM:RM!OT26) -> -46901.97 | OV26: =SUM(OI26:OT26) -> -505026.9
B27: 4.9 | C27: IMPOSTOS E TAXAS (9) | E27: =SUM(LARM:RM!E27) -> 0 | F27: =SUM(LARM:RM!F27) -> 0 | G27: =SUM(LARM:RM!G27) -> 0 | H27: =SUM(LARM:RM!H27) -> 0 | I27: =SUM(LARM:RM!I27) -> 0 | J27: =SUM(LARM:RM!J27) -> 0 | K27: =SUM(LARM:RM!K27) -> 0 | L27: =SUM(LARM:RM!L27) -> 0 | ... AI27: =SUM(LARM:RM!AI27) -> 0 | AJ27: =SUM(E27:AI27) -> -42953.14 | AK27: =SUM(LARM:RM!AK27) -> 0 | AL27: =SUM(LARM:RM!AL27) -> 0 | AM27: =SUM(LARM:RM!AM27) -> 0 | AN27: =SUM(LARM:RM!AN27) -> 0 | AO27: =SUM(LARM:RM!AO27) -> 0 | AP27: =SUM(LARM:RM!AP27) -> 0 | AQ27: =SUM(LARM:RM!AQ27) -> 0 | AR27: =SUM(LARM:RM!AR27) -> 0 | ... BO27: =SUM(LARM:RM!BO27) -> 0 | BP27: =SUM(AK27:BO27) -> -40820.78 | BQ27: =SUM(LARM:RM!BQ27) -> 0 | BR27: =SUM(LARM:RM!BR27) -> 0 | BS27: =SUM(LARM:RM!BS27) -> 0 | BT27: =SUM(LARM:RM!BT27) -> 0 | BU27: =SUM(LARM:RM!BU27) -> 0 | BV27: =SUM(LARM:RM!BV27) -> 0 | BW27: =SUM(LARM:RM!BW27) -> 0 | BX27: =SUM(LARM:RM!BX27) -> 0 | ... CU27: =SUM(LARM:RM!CU27) -> 0 | CV27: =SUM(BQ27:CU27) -> -76000.71 | CW27: =SUM(LARM:RM!CW27) -> 0 | CX27: =SUM(LARM:RM!CX27) -> 0 | CY27: =SUM(LARM:RM!CY27) -> 0 | CZ27: =SUM(LARM:RM!CZ27) -> 0 | DA27: =SUM(LARM:RM!DA27) -> 0 | DB27: =SUM(LARM:RM!DB27) -> -2077.71 | DC27: =SUM(LARM:RM!DC27) -> 0 | DD27: =SUM(LARM:RM!DD27) -> 0 | ... EA27: =SUM(LARM:RM!EA27) -> 0 | EB27: =SUM(CW27:EA27) -> -22806.95 | EC27: =SUM(LARM:RM!EC27) -> 0 | ED27: =SUM(LARM:RM!ED27) -> 0 | EE27: =SUM(LARM:RM!EE27) -> 0 | EF27: =SUM(LARM:RM!EF27) -> 0 | EG27: =SUM(LARM:RM!EG27) -> 0 | EH27: =SUM(LARM:RM!EH27) -> 0 | EI27: =SUM(LARM:RM!EI27) -> 0 | EJ27: =SUM(LARM:RM!EJ27) -> 0 | ... FG27: =SUM(LARM:RM!FG27) -> 0 | FH27: =SUM(EC27:FG27) -> -267076.28 | FI27: =SUM(LARM:RM!FI27) -> 0 | FJ27: =SUM(LARM:RM!FJ27) -> 0 | FK27: =SUM(LARM:RM!FK27) -> 0 | FL27: =SUM(LARM:RM!FL27) -> 0 | FM27: =SUM(LARM:RM!FM27) -> 0 | FN27: =SUM(LARM:RM!FN27) -> 0 | FO27: =SUM(LARM:RM!FO27) -> 0 | FP27: =SUM(LARM:RM!FP27) -> 0 | ... GM27: =SUM(LARM:RM!GM27) -> 0 | GN27: =SUM(FI27:GM27) -> -7030.51 | GO27: =SUM(LARM:RM!GO27) -> 0 | GP27: =SUM(LARM:RM!GP27) -> 0 | GQ27: =SUM(LARM:RM!GQ27) -> 0 | GR27: =SUM(LARM:RM!GR27) -> 0 | GS27: =SUM(LARM:RM!GS27) -> 0 | GT27: =SUM(LARM:RM!GT27) -> 0 | GU27: =SUM(LARM:RM!GU27) -> -924.24 | GV27: =SUM(LARM:RM!GV27) -> 0 | ... HS27: =SUM(LARM:RM!HS27) -> 0 | HT27: =SUM(GO27:HS27) -> -7387.08 | HU27: =SUM(LARM:RM!HU27) -> 0 | HV27: =SUM(LARM:RM!HV27) -> 0 | HW27: =SUM(LARM:RM!HW27) -> 0 | HX27: =SUM(LARM:RM!HX27) -> 0 | HY27: =SUM(LARM:RM!HY27) -> 0 | HZ27: =SUM(LARM:RM!HZ27) -> 0 | IA27: =SUM(LARM:RM!IA27) -> 0 | IB27: =SUM(LARM:RM!IB27) -> 0 | ... IY27: =SUM(LARM:RM!IY27) -> 0 | IZ27: =SUM(HU27:IY27) -> -8541.93 | JA27: =SUM(LARM:RM!JA27) -> 0 | JB27: =SUM(LARM:RM!JB27) -> 0 | JC27: =SUM(LARM:RM!JC27) -> 0 | JD27: =SUM(LARM:RM!JD27) -> 0 | JE27: =SUM(LARM:RM!JE27) -> 0 | JF27: =SUM(LARM:RM!JF27) -> 0 | JG27: =SUM(LARM:RM!JG27) -> 0 | JH27: =SUM(LARM:RM!JH27) -> 0 | ... KE27: =SUM(LARM:RM!KE27) -> 0 | KF27: =SUM(JA27:KE27) -> -20870.72 | KG27: =SUM(LARM:RM!KG27) -> 0 | KH27: =SUM(LARM:RM!KH27) -> 0 | KI27: =SUM(LARM:RM!KI27) -> 0 | KJ27: =SUM(LARM:RM!KJ27) -> 0 | KK27: =SUM(LARM:RM!KK27) -> 0 | KL27: =SUM(LARM:RM!KL27) -> 0 | KM27: =SUM(LARM:RM!KM27) -> 0 | KN27: =SUM(LARM:RM!KN27) -> 0 | ... LK27: =SUM(LARM:RM!LK27) -> 0 | LL27: =SUM(KG27:LK27) -> -12143.16 | LM27: =SUM(LARM:RM!LM27) -> 0 | LN27: =SUM(LARM:RM!LN27) -> 0 | LO27: =SUM(LARM:RM!LO27) -> 0 | LP27: =SUM(LARM:RM!LP27) -> 0 | LQ27: =SUM(LARM:RM!LQ27) -> 0 | LR27: =SUM(LARM:RM!LR27) -> 0 | LS27: =SUM(LARM:RM!LS27) -> 0 | LT27: =SUM(LARM:RM!LT27) -> 0 | ... MQ27: =SUM(LARM:RM!MQ27) -> 0 | MR27: =SUM(LM27:MQ27) -> -7247.9 | MS27: =SUM(LARM:RM!MS27) -> 0 | MT27: =SUM(LARM:RM!MT27) -> 0 | MU27: =SUM(LARM:RM!MU27) -> 0 | MV27: =SUM(LARM:RM!MV27) -> 0 | MW27: =SUM(LARM:RM!MW27) -> 0 | MX27: =SUM(LARM:RM!MX27) -> 0 | MY27: =SUM(LARM:RM!MY27) -> 0 | MZ27: =SUM(LARM:RM!MZ27) -> 0 | ... NW27: =SUM(LARM:RM!NW27) -> 0 | NX27: =SUM(MS27:NW27) -> -1000 | NZ27: =AJ27+BP27+CV27+EB27+FH27+GN27+HT27+IZ27+KF27+LL27+MR27+NX27 -> -513879.16 | OA27: =SUM(OI27:OP27) -> -506965.46 | OB27: =IF(OA27=0,"",((NZ27/OA27)-1)*-1) -> -0.013637418 | OG27: IMPOSTOS E TAXAS (9) | OI27: =SUM(LARM:RM!OI27) -> -51104.36 | OJ27: =SUM(LARM:RM!OJ27) -> -79760.56 | OK27: =SUM(LARM:RM!OK27) -> -80016.63 | OL27: =SUM(LARM:RM!OL27) -> -7056.42 | OM27: =SUM(LARM:RM!OM27) -> -272184.52 | ON27: =SUM(LARM:RM!ON27) -> -6462.93 | OO27: =SUM(LARM:RM!OO27) -> -6819.5 | OP27: =SUM(LARM:RM!OP27) -> -3560.54 | ... OT27: =SUM(LARM:RM!OT27) -> -1000 | OV27: =SUM(OI27:OT27) -> -540426.34
B28: 4.10 | C28: DESPESAS INDEDUTIVEIS (10) | E28: =SUM(LARM:RM!E28) -> 0 | F28: =SUM(LARM:RM!F28) -> 0 | G28: =SUM(LARM:RM!G28) -> 0 | H28: =SUM(LARM:RM!H28) -> 0 | I28: =SUM(LARM:RM!I28) -> 0 | J28: =SUM(LARM:RM!J28) -> 0 | K28: =SUM(LARM:RM!K28) -> 0 | L28: =SUM(LARM:RM!L28) -> 0 | ... AI28: =SUM(LARM:RM!AI28) -> 0 | AJ28: =SUM(E28:AI28) -> -532.18 | AK28: =SUM(LARM:RM!AK28) -> 0 | AL28: =SUM(LARM:RM!AL28) -> 0 | AM28: =SUM(LARM:RM!AM28) -> 0 | AN28: =SUM(LARM:RM!AN28) -> 0 | AO28: =SUM(LARM:RM!AO28) -> 0 | AP28: =SUM(LARM:RM!AP28) -> 0 | AQ28: =SUM(LARM:RM!AQ28) -> 0 | AR28: =SUM(LARM:RM!AR28) -> 0 | ... BO28: =SUM(LARM:RM!BO28) -> 0 | BP28: =SUM(AK28:BO28) -> -208.24 | BQ28: =SUM(LARM:RM!BQ28) -> 0 | BR28: =SUM(LARM:RM!BR28) -> 0 | BS28: =SUM(LARM:RM!BS28) -> 0 | BT28: =SUM(LARM:RM!BT28) -> 0 | BU28: =SUM(LARM:RM!BU28) -> 0 | BV28: =SUM(LARM:RM!BV28) -> 0 | BW28: =SUM(LARM:RM!BW28) -> 0 | BX28: =SUM(LARM:RM!BX28) -> 0 | ... CU28: =SUM(LARM:RM!CU28) -> 0 | CV28: =SUM(BQ28:CU28) -> 0 | CW28: =SUM(LARM:RM!CW28) -> 0 | CX28: =SUM(LARM:RM!CX28) -> 0 | CY28: =SUM(LARM:RM!CY28) -> 0 | CZ28: =SUM(LARM:RM!CZ28) -> 0 | DA28: =SUM(LARM:RM!DA28) -> 0 | DB28: =SUM(LARM:RM!DB28) -> 0 | DC28: =SUM(LARM:RM!DC28) -> 0 | DD28: =SUM(LARM:RM!DD28) -> 0 | ... EA28: =SUM(LARM:RM!EA28) -> 0 | EB28: =SUM(CW28:EA28) -> 0 | EC28: =SUM(LARM:RM!EC28) -> 0 | ED28: =SUM(LARM:RM!ED28) -> 0 | EE28: =SUM(LARM:RM!EE28) -> 0 | EF28: =SUM(LARM:RM!EF28) -> 0 | EG28: =SUM(LARM:RM!EG28) -> 0 | EH28: =SUM(LARM:RM!EH28) -> 0 | EI28: =SUM(LARM:RM!EI28) -> 0 | EJ28: =SUM(LARM:RM!EJ28) -> 0 | ... FG28: =SUM(LARM:RM!FG28) -> 0 | FH28: =SUM(EC28:FG28) -> 0 | FI28: =SUM(LARM:RM!FI28) -> 0 | FJ28: =SUM(LARM:RM!FJ28) -> 0 | FK28: =SUM(LARM:RM!FK28) -> 0 | FL28: =SUM(LARM:RM!FL28) -> 0 | FM28: =SUM(LARM:RM!FM28) -> 0 | FN28: =SUM(LARM:RM!FN28) -> 0 | FO28: =SUM(LARM:RM!FO28) -> 0 | FP28: =SUM(LARM:RM!FP28) -> 0 | ... GM28: =SUM(LARM:RM!GM28) -> 0 | GN28: =SUM(FI28:GM28) -> 0 | GO28: =SUM(LARM:RM!GO28) -> 0 | GP28: =SUM(LARM:RM!GP28) -> 0 | GQ28: =SUM(LARM:RM!GQ28) -> 0 | GR28: =SUM(LARM:RM!GR28) -> 0 | GS28: =SUM(LARM:RM!GS28) -> 0 | GT28: =SUM(LARM:RM!GT28) -> 0 | GU28: =SUM(LARM:RM!GU28) -> -104.13 | GV28: =SUM(LARM:RM!GV28) -> 0 | ... HS28: =SUM(LARM:RM!HS28) -> 0 | HT28: =SUM(GO28:HS28) -> -104.13 | HU28: =SUM(LARM:RM!HU28) -> 0 | HV28: =SUM(LARM:RM!HV28) -> 0 | HW28: =SUM(LARM:RM!HW28) -> 0 | HX28: =SUM(LARM:RM!HX28) -> 0 | HY28: =SUM(LARM:RM!HY28) -> 0 | HZ28: =SUM(LARM:RM!HZ28) -> 0 | IA28: =SUM(LARM:RM!IA28) -> 0 | IB28: =SUM(LARM:RM!IB28) -> 0 | ... IY28: =SUM(LARM:RM!IY28) -> 0 | IZ28: =SUM(HU28:IY28) -> -2011.09 | JA28: =SUM(LARM:RM!JA28) -> 0 | JB28: =SUM(LARM:RM!JB28) -> 0 | JC28: =SUM(LARM:RM!JC28) -> 0 | JD28: =SUM(LARM:RM!JD28) -> 0 | JE28: =SUM(LARM:RM!JE28) -> 0 | JF28: =SUM(LARM:RM!JF28) -> 0 | JG28: =SUM(LARM:RM!JG28) -> 0 | JH28: =SUM(LARM:RM!JH28) -> 0 | ... KE28: =SUM(LARM:RM!KE28) -> 0 | KF28: =SUM(JA28:KE28) -> 0 | KG28: =SUM(LARM:RM!KG28) -> 0 | KH28: =SUM(LARM:RM!KH28) -> 0 | KI28: =SUM(LARM:RM!KI28) -> 0 | KJ28: =SUM(LARM:RM!KJ28) -> 0 | KK28: =SUM(LARM:RM!KK28) -> 0 | KL28: =SUM(LARM:RM!KL28) -> 0 | KM28: =SUM(LARM:RM!KM28) -> 0 | KN28: =SUM(LARM:RM!KN28) -> 0 | ... LK28: =SUM(LARM:RM!LK28) -> 0 | LL28: =SUM(KG28:LK28) -> -208.26 | LM28: =SUM(LARM:RM!LM28) -> 0 | LN28: =SUM(LARM:RM!LN28) -> 0 | LO28: =SUM(LARM:RM!LO28) -> 0 | LP28: =SUM(LARM:RM!LP28) -> 0 | LQ28: =SUM(LARM:RM!LQ28) -> 0 | LR28: =SUM(LARM:RM!LR28) -> 0 | LS28: =SUM(LARM:RM!LS28) -> 0 | LT28: =SUM(LARM:RM!LT28) -> 0 | ... MQ28: =SUM(LARM:RM!MQ28) -> 0 | MR28: =SUM(LM28:MQ28) -> 0 | MS28: =SUM(LARM:RM!MS28) -> 0 | MT28: =SUM(LARM:RM!MT28) -> 0 | MU28: =SUM(LARM:RM!MU28) -> 0 | MV28: =SUM(LARM:RM!MV28) -> 0 | MW28: =SUM(LARM:RM!MW28) -> 0 | MX28: =SUM(LARM:RM!MX28) -> 0 | MY28: =SUM(LARM:RM!MY28) -> 0 | MZ28: =SUM(LARM:RM!MZ28) -> 0 | ... NW28: =SUM(LARM:RM!NW28) -> 0 | NX28: =SUM(MS28:NW28) -> 0 | NZ28: =AJ28+BP28+CV28+EB28+FH28+GN28+HT28+IZ28+KF28+LL28+MR28+NX28 -> -3063.9 | OA28: =SUM(OI28:OP28) -> -4235.78 | OB28: =IF(OA28=0,"",((NZ28/OA28)-1)*-1) -> 0.27666215 | OG28: DESPESAS INDEDUTIVEIS (10) | OI28: =SUM(LARM:RM!OI28) -> -683.42 | OJ28: =SUM(LARM:RM!OJ28) -> 0 | OK28: =SUM(LARM:RM!OK28) -> -1437.14 | OL28: =SUM(LARM:RM!OL28) -> 0 | OM28: =SUM(LARM:RM!OM28) -> 0 | ON28: =SUM(LARM:RM!ON28) -> 0 | OO28: =SUM(LARM:RM!OO28) -> -104.13 | OP28: =SUM(LARM:RM!OP28) -> -2011.09 | ... OT28: =SUM(LARM:RM!OT28) -> 0 | OV28: =SUM(OI28:OT28) -> -4444.04
B29: 4.11 | C29: CUSTO DO GADO (11) | E29: =SUM(LARM:RM!E29) -> 0 | F29: =SUM(LARM:RM!F29) -> 0 | G29: =SUM(LARM:RM!G29) -> 0 | H29: =SUM(LARM:RM!H29) -> 0 | I29: =SUM(LARM:RM!I29) -> 0 | J29: =SUM(LARM:RM!J29) -> 0 | K29: =SUM(LARM:RM!K29) -> 0 | L29: =SUM(LARM:RM!L29) -> 0 | ... AI29: =SUM(LARM:RM!AI29) -> 0 | AJ29: =SUM(E29:AI29) -> 0 | AK29: =SUM(LARM:RM!AK29) -> 0 | AL29: =SUM(LARM:RM!AL29) -> 0 | AM29: =SUM(LARM:RM!AM29) -> 0 | AN29: =SUM(LARM:RM!AN29) -> 0 | AO29: =SUM(LARM:RM!AO29) -> 0 | AP29: =SUM(LARM:RM!AP29) -> 0 | AQ29: =SUM(LARM:RM!AQ29) -> 0 | AR29: =SUM(LARM:RM!AR29) -> 0 | ... BO29: =SUM(LARM:RM!BO29) -> 0 | BP29: =SUM(AK29:BO29) -> 0 | BQ29: =SUM(LARM:RM!BQ29) -> 0 | BR29: =SUM(LARM:RM!BR29) -> 0 | BS29: =SUM(LARM:RM!BS29) -> 0 | BT29: =SUM(LARM:RM!BT29) -> 0 | BU29: =SUM(LARM:RM!BU29) -> 0 | BV29: =SUM(LARM:RM!BV29) -> 0 | BW29: =SUM(LARM:RM!BW29) -> 0 | BX29: =SUM(LARM:RM!BX29) -> 0 | ... CU29: =SUM(LARM:RM!CU29) -> 0 | CV29: =SUM(BQ29:CU29) -> 0 | CW29: =SUM(LARM:RM!CW29) -> 0 | CX29: =SUM(LARM:RM!CX29) -> 0 | CY29: =SUM(LARM:RM!CY29) -> 0 | CZ29: =SUM(LARM:RM!CZ29) -> 0 | DA29: =SUM(LARM:RM!DA29) -> 0 | DB29: =SUM(LARM:RM!DB29) -> 0 | DC29: =SUM(LARM:RM!DC29) -> 0 | DD29: =SUM(LARM:RM!DD29) -> 0 | ... EA29: =SUM(LARM:RM!EA29) -> 0 | EB29: =SUM(CW29:EA29) -> 0 | EC29: =SUM(LARM:RM!EC29) -> 0 | ED29: =SUM(LARM:RM!ED29) -> 0 | EE29: =SUM(LARM:RM!EE29) -> 0 | EF29: =SUM(LARM:RM!EF29) -> 0 | EG29: =SUM(LARM:RM!EG29) -> 0 | EH29: =SUM(LARM:RM!EH29) -> 0 | EI29: =SUM(LARM:RM!EI29) -> 0 | EJ29: =SUM(LARM:RM!EJ29) -> 0 | ... FG29: =SUM(LARM:RM!FG29) -> 0 | FH29: =SUM(EC29:FG29) -> -4050 | FI29: =SUM(LARM:RM!FI29) -> 0 | FJ29: =SUM(LARM:RM!FJ29) -> 0 | FK29: =SUM(LARM:RM!FK29) -> 0 | FL29: =SUM(LARM:RM!FL29) -> 0 | FM29: =SUM(LARM:RM!FM29) -> 0 | FN29: =SUM(LARM:RM!FN29) -> 0 | FO29: =SUM(LARM:RM!FO29) -> 0 | FP29: =SUM(LARM:RM!FP29) -> 0 | ... GM29: =SUM(LARM:RM!GM29) -> 0 | GN29: =SUM(FI29:GM29) -> -4050 | GO29: =SUM(LARM:RM!GO29) -> 0 | GP29: =SUM(LARM:RM!GP29) -> 0 | GQ29: =SUM(LARM:RM!GQ29) -> 0 | GR29: =SUM(LARM:RM!GR29) -> 0 | GS29: =SUM(LARM:RM!GS29) -> 0 | GT29: =SUM(LARM:RM!GT29) -> 0 | GU29: =SUM(LARM:RM!GU29) -> 0 | GV29: =SUM(LARM:RM!GV29) -> 0 | ... HS29: =SUM(LARM:RM!HS29) -> 0 | HT29: =SUM(GO29:HS29) -> -4050 | HU29: =SUM(LARM:RM!HU29) -> 0 | HV29: =SUM(LARM:RM!HV29) -> 0 | HW29: =SUM(LARM:RM!HW29) -> 0 | HX29: =SUM(LARM:RM!HX29) -> 0 | HY29: =SUM(LARM:RM!HY29) -> 0 | HZ29: =SUM(LARM:RM!HZ29) -> 0 | IA29: =SUM(LARM:RM!IA29) -> 0 | IB29: =SUM(LARM:RM!IB29) -> 0 | ... IY29: =SUM(LARM:RM!IY29) -> 0 | IZ29: =SUM(HU29:IY29) -> -4050 | JA29: =SUM(LARM:RM!JA29) -> 0 | JB29: =SUM(LARM:RM!JB29) -> 0 | JC29: =SUM(LARM:RM!JC29) -> 0 | JD29: =SUM(LARM:RM!JD29) -> 0 | JE29: =SUM(LARM:RM!JE29) -> 0 | JF29: =SUM(LARM:RM!JF29) -> 0 | JG29: =SUM(LARM:RM!JG29) -> 0 | JH29: =SUM(LARM:RM!JH29) -> 0 | ... KE29: =SUM(LARM:RM!KE29) -> 0 | KF29: =SUM(JA29:KE29) -> -4050 | KG29: =SUM(LARM:RM!KG29) -> 0 | KH29: =SUM(LARM:RM!KH29) -> 0 | KI29: =SUM(LARM:RM!KI29) -> 0 | KJ29: =SUM(LARM:RM!KJ29) -> 0 | KK29: =SUM(LARM:RM!KK29) -> 0 | KL29: =SUM(LARM:RM!KL29) -> 0 | KM29: =SUM(LARM:RM!KM29) -> 0 | KN29: =SUM(LARM:RM!KN29) -> 0 | ... LK29: =SUM(LARM:RM!LK29) -> 0 | LL29: =SUM(KG29:LK29) -> -4050 | LM29: =SUM(LARM:RM!LM29) -> 0 | LN29: =SUM(LARM:RM!LN29) -> 0 | LO29: =SUM(LARM:RM!LO29) -> 0 | LP29: =SUM(LARM:RM!LP29) -> 0 | LQ29: =SUM(LARM:RM!LQ29) -> 0 | LR29: =SUM(LARM:RM!LR29) -> 0 | LS29: =SUM(LARM:RM!LS29) -> 0 | LT29: =SUM(LARM:RM!LT29) -> 0 | ... MQ29: =SUM(LARM:RM!MQ29) -> 0 | MR29: =SUM(LM29:MQ29) -> -4050 | MS29: =SUM(LARM:RM!MS29) -> 0 | MT29: =SUM(LARM:RM!MT29) -> 0 | MU29: =SUM(LARM:RM!MU29) -> 0 | MV29: =SUM(LARM:RM!MV29) -> 0 | MW29: =SUM(LARM:RM!MW29) -> 0 | MX29: =SUM(LARM:RM!MX29) -> 0 | MY29: =SUM(LARM:RM!MY29) -> 0 | MZ29: =SUM(LARM:RM!MZ29) -> 0 | ... NW29: =SUM(LARM:RM!NW29) -> 0 | NX29: =SUM(MS29:NW29) -> -4050 | NZ29: =AJ29+BP29+CV29+EB29+FH29+GN29+HT29+IZ29+KF29+LL29+MR29+NX29 -> -32400 | OA29: =SUM(OI29:OP29) -> -32400 | OB29: =IF(OA29=0,"",((NZ29/OA29)-1)*-1) -> 0 | OG29: CUSTO DO GADO (11) | OI29: =SUM(LARM:RM!OI29) -> -4050 | OJ29: =SUM(LARM:RM!OJ29) -> -4050 | OK29: =SUM(LARM:RM!OK29) -> -4050 | OL29: =SUM(LARM:RM!OL29) -> -4050 | OM29: =SUM(LARM:RM!OM29) -> -4050 | ON29: =SUM(LARM:RM!ON29) -> -4050 | OO29: =SUM(LARM:RM!OO29) -> -4050 | OP29: =SUM(LARM:RM!OP29) -> -4050 | ... OT29: =SUM(LARM:RM!OT29) -> -4050 | OV29: =SUM(OI29:OT29) -> -48600
B30: 4.12 | C30: DESPESAS MÉDICAS (12) | E30: =SUM(LARM:RM!E30) -> 0 | F30: =SUM(LARM:RM!F30) -> -35838.24 | G30: =SUM(LARM:RM!G30) -> 0 | H30: =SUM(LARM:RM!H30) -> 0 | I30: =SUM(LARM:RM!I30) -> 0 | J30: =SUM(LARM:RM!J30) -> 0 | K30: =SUM(LARM:RM!K30) -> 0 | L30: =SUM(LARM:RM!L30) -> 0 | ... AI30: =SUM(LARM:RM!AI30) -> 0 | AJ30: =SUM(E30:AI30) -> -65922.94 | AK30: =SUM(LARM:RM!AK30) -> 0 | AL30: =SUM(LARM:RM!AL30) -> -35838.24 | AM30: =SUM(LARM:RM!AM30) -> 0 | AN30: =SUM(LARM:RM!AN30) -> 0 | AO30: =SUM(LARM:RM!AO30) -> 0 | AP30: =SUM(LARM:RM!AP30) -> 0 | AQ30: =SUM(LARM:RM!AQ30) -> 0 | AR30: =SUM(LARM:RM!AR30) -> 0 | ... BO30: =SUM(LARM:RM!BO30) -> 0 | BP30: =SUM(AK30:BO30) -> -50352.94 | BQ30: =SUM(LARM:RM!BQ30) -> 0 | BR30: =SUM(LARM:RM!BR30) -> -35962.37 | BS30: =SUM(LARM:RM!BS30) -> 0 | BT30: =SUM(LARM:RM!BT30) -> 0 | BU30: =SUM(LARM:RM!BU30) -> 0 | BV30: =SUM(LARM:RM!BV30) -> 0 | BW30: =SUM(LARM:RM!BW30) -> 0 | BX30: =SUM(LARM:RM!BX30) -> 0 | ... CU30: =SUM(LARM:RM!CU30) -> -15800 | CV30: =SUM(BQ30:CU30) -> -56575.31 | CW30: =SUM(LARM:RM!CW30) -> 0 | CX30: =SUM(LARM:RM!CX30) -> -35838.24 | CY30: =SUM(LARM:RM!CY30) -> 0 | CZ30: =SUM(LARM:RM!CZ30) -> 0 | DA30: =SUM(LARM:RM!DA30) -> 0 | DB30: =SUM(LARM:RM!DB30) -> 0 | DC30: =SUM(LARM:RM!DC30) -> 0 | DD30: =SUM(LARM:RM!DD30) -> -1020 | ... EA30: =SUM(LARM:RM!EA30) -> 0 | EB30: =SUM(CW30:EA30) -> -54148.74 | EC30: =SUM(LARM:RM!EC30) -> 0 | ED30: =SUM(LARM:RM!ED30) -> 0 | EE30: =SUM(LARM:RM!EE30) -> 0 | EF30: =SUM(LARM:RM!EF30) -> -40131.65 | EG30: =SUM(LARM:RM!EG30) -> 0 | EH30: =SUM(LARM:RM!EH30) -> 0 | EI30: =SUM(LARM:RM!EI30) -> -16000 | EJ30: =SUM(LARM:RM!EJ30) -> 0 | ... FG30: =SUM(LARM:RM!FG30) -> 0 | FH30: =SUM(EC30:FG30) -> -71394.37 | FI30: =SUM(LARM:RM!FI30) -> 0 | FJ30: =SUM(LARM:RM!FJ30) -> -37338.24 | FK30: =SUM(LARM:RM!FK30) -> 0 | FL30: =SUM(LARM:RM!FL30) -> 0 | FM30: =SUM(LARM:RM!FM30) -> 0 | FN30: =SUM(LARM:RM!FN30) -> -300 | FO30: =SUM(LARM:RM!FO30) -> 0 | FP30: =SUM(LARM:RM!FP30) -> 0 | ... GM30: =SUM(LARM:RM!GM30) -> 0 | GN30: =SUM(FI30:GM30) -> -52300.96 | GO30: =SUM(LARM:RM!GO30) -> -35838.24 | GP30: =SUM(LARM:RM!GP30) -> 0 | GQ30: =SUM(LARM:RM!GQ30) -> 0 | GR30: =SUM(LARM:RM!GR30) -> 0 | GS30: =SUM(LARM:RM!GS30) -> 0 | GT30: =SUM(LARM:RM!GT30) -> 0 | GU30: =SUM(LARM:RM!GU30) -> 0 | GV30: =SUM(LARM:RM!GV30) -> 0 | ... HS30: =SUM(LARM:RM!HS30) -> 0 | HT30: =SUM(GO30:HS30) -> -66150.96 | HU30: =SUM(LARM:RM!HU30) -> -37338.24 | HV30: =SUM(LARM:RM!HV30) -> 0 | HW30: =SUM(LARM:RM!HW30) -> 0 | HX30: =SUM(LARM:RM!HX30) -> 0 | HY30: =SUM(LARM:RM!HY30) -> 0 | HZ30: =SUM(LARM:RM!HZ30) -> 0 | IA30: =SUM(LARM:RM!IA30) -> 0 | IB30: =SUM(LARM:RM!IB30) -> 0 | ... IY30: =SUM(LARM:RM!IY30) -> 0 | IZ30: =SUM(HU30:IY30) -> -66800.96 | JA30: =SUM(LARM:RM!JA30) -> -35838.24 | JB30: =SUM(LARM:RM!JB30) -> 0 | JC30: =SUM(LARM:RM!JC30) -> 0 | JD30: =SUM(LARM:RM!JD30) -> 0 | JE30: =SUM(LARM:RM!JE30) -> 0 | JF30: =SUM(LARM:RM!JF30) -> 0 | JG30: =SUM(LARM:RM!JG30) -> -8500 | JH30: =SUM(LARM:RM!JH30) -> 0 | ... KE30: =SUM(LARM:RM!KE30) -> 0 | KF30: =SUM(JA30:KE30) -> -55072.94 | KG30: =SUM(LARM:RM!KG30) -> -44338.24 | KH30: =SUM(LARM:RM!KH30) -> 0 | KI30: =SUM(LARM:RM!KI30) -> 0 | KJ30: =SUM(LARM:RM!KJ30) -> 0 | KK30: =SUM(LARM:RM!KK30) -> 0 | KL30: =SUM(LARM:RM!KL30) -> 0 | KM30: =SUM(LARM:RM!KM30) -> 0 | KN30: =SUM(LARM:RM!KN30) -> 0 | ... LK30: =SUM(LARM:RM!LK30) -> 0 | LL30: =SUM(KG30:LK30) -> -45072.94 | LM30: =SUM(LARM:RM!LM30) -> 0 | LN30: =SUM(LARM:RM!LN30) -> 0 | LO30: =SUM(LARM:RM!LO30) -> -35838.24 | LP30: =SUM(LARM:RM!LP30) -> -10000 | LQ30: =SUM(LARM:RM!LQ30) -> 0 | LR30: =SUM(LARM:RM!LR30) -> 0 | LS30: =SUM(LARM:RM!LS30) -> 0 | LT30: =SUM(LARM:RM!LT30) -> 0 | ... MQ30: =SUM(LARM:RM!MQ30) -> 0 | MR30: =SUM(LM30:MQ30) -> -64725.96 | MS30: =SUM(LARM:RM!MS30) -> 0 | MT30: =SUM(LARM:RM!MT30) -> -35838.24 | MU30: =SUM(LARM:RM!MU30) -> -35838.24 | MV30: =SUM(LARM:RM!MV30) -> 0 | MW30: =SUM(LARM:RM!MW30) -> -3300 | MX30: =SUM(LARM:RM!MX30) -> 0 | MY30: =SUM(LARM:RM!MY30) -> 0 | MZ30: =SUM(LARM:RM!MZ30) -> 0 | ... NW30: =SUM(LARM:RM!NW30) -> 0 | NX30: =SUM(MS30:NW30) -> -75364.2 | NZ30: =AJ30+BP30+CV30+EB30+FH30+GN30+HT30+IZ30+KF30+LL30+MR30+NX30 -> -723883.22 | OA30: =SUM(OI30:OP30) -> -407772.6 | OB30: =IF(OA30=0,"",((NZ30/OA30)-1)*-1) -> -0.775213 | OG30: CUSTO DO GADO (11) | OI30: =SUM(LARM:RM!OI30) -> -63500.96 | OJ30: =SUM(LARM:RM!OJ30) -> -57317.08 | OK30: =SUM(LARM:RM!OK30) -> -54388.24 | OL30: =SUM(LARM:RM!OL30) -> -50562.48 | OM30: =SUM(LARM:RM!OM30) -> -40550.96 | ON30: =SUM(LARM:RM!ON30) -> -46500.96 | OO30: =SUM(LARM:RM!OO30) -> -47150.96 | OP30: =SUM(LARM:RM!OP30) -> -47800.96 | ... OT30: =SUM(LARM:RM!OT30) -> -75364.2 | OV30: =SUM(OI30:OT30) -> -638508.64
B31: 6.1 | C31: RECEITAS/DESPESAS NÃO OPERACIONAIS | E31: =SUM(LARM:RM!E31) -> 0 | F31: =SUM(LARM:RM!F31) -> -1000 | G31: =SUM(LARM:RM!G31) -> 0 | H31: =SUM(LARM:RM!H31) -> 0 | I31: =SUM(LARM:RM!I31) -> 0 | J31: =SUM(LARM:RM!J31) -> 0 | K31: =SUM(LARM:RM!K31) -> 0 | L31: =SUM(LARM:RM!L31) -> -5000 | ... AI31: =SUM(LARM:RM!AI31) -> 0 | AJ31: =SUM(E31:AI31) -> -20825.02 | AK31: =SUM(LARM:RM!AK31) -> 0 | AL31: =SUM(LARM:RM!AL31) -> -2122.5 | AM31: =SUM(LARM:RM!AM31) -> 0 | AN31: =SUM(LARM:RM!AN31) -> 0 | AO31: =SUM(LARM:RM!AO31) -> 0 | AP31: =SUM(LARM:RM!AP31) -> 0 | AQ31: =SUM(LARM:RM!AQ31) -> 0 | AR31: =SUM(LARM:RM!AR31) -> 0 | ... BO31: =SUM(LARM:RM!BO31) -> 0 | BP31: =SUM(AK31:BO31) -> -6522.5 | BQ31: =SUM(LARM:RM!BQ31) -> 0 | BR31: =SUM(LARM:RM!BR31) -> -1000 | BS31: =SUM(LARM:RM!BS31) -> 0 | BT31: =SUM(LARM:RM!BT31) -> 0 | BU31: =SUM(LARM:RM!BU31) -> 0 | BV31: =SUM(LARM:RM!BV31) -> 0 | BW31: =SUM(LARM:RM!BW31) -> 0 | BX31: =SUM(LARM:RM!BX31) -> 0 | ... CU31: =SUM(LARM:RM!CU31) -> 0 | CV31: =SUM(BQ31:CU31) -> -5000 | CW31: =SUM(LARM:RM!CW31) -> -1000 | CX31: =SUM(LARM:RM!CX31) -> 0 | CY31: =SUM(LARM:RM!CY31) -> 0 | CZ31: =SUM(LARM:RM!CZ31) -> 0 | DA31: =SUM(LARM:RM!DA31) -> 0 | DB31: =SUM(LARM:RM!DB31) -> -520.12 | DC31: =SUM(LARM:RM!DC31) -> 0 | DD31: =SUM(LARM:RM!DD31) -> 0 | ... EA31: =SUM(LARM:RM!EA31) -> 0 | EB31: =SUM(CW31:EA31) -> -31990.12 | EC31: =SUM(LARM:RM!EC31) -> 0 | ED31: =SUM(LARM:RM!ED31) -> 0 | EE31: =SUM(LARM:RM!EE31) -> 0 | EF31: =SUM(LARM:RM!EF31) -> -1000 | EG31: =SUM(LARM:RM!EG31) -> 0 | EH31: =SUM(LARM:RM!EH31) -> -16000 | EI31: =SUM(LARM:RM!EI31) -> 0 | EJ31: =SUM(LARM:RM!EJ31) -> 0 | ... FG31: =SUM(LARM:RM!FG31) -> 0 | FH31: =SUM(EC31:FG31) -> -22000 | FI31: =SUM(LARM:RM!FI31) -> 0 | FJ31: =SUM(LARM:RM!FJ31) -> -1000 | FK31: =SUM(LARM:RM!FK31) -> 0 | FL31: =SUM(LARM:RM!FL31) -> 0 | FM31: =SUM(LARM:RM!FM31) -> 0 | FN31: =SUM(LARM:RM!FN31) -> 0 | FO31: =SUM(LARM:RM!FO31) -> 0 | FP31: =SUM(LARM:RM!FP31) -> 0 | ... GM31: =SUM(LARM:RM!GM31) -> 0 | GN31: =SUM(FI31:GM31) -> -4000 | GO31: =SUM(LARM:RM!GO31) -> -1000 | GP31: =SUM(LARM:RM!GP31) -> 0 | GQ31: =SUM(LARM:RM!GQ31) -> 0 | GR31: =SUM(LARM:RM!GR31) -> 0 | GS31: =SUM(LARM:RM!GS31) -> 0 | GT31: =SUM(LARM:RM!GT31) -> 0 | GU31: =SUM(LARM:RM!GU31) -> 0 | GV31: =SUM(LARM:RM!GV31) -> 0 | ... HS31: =SUM(LARM:RM!HS31) -> 0 | HT31: =SUM(GO31:HS31) -> -6000 | HU31: =SUM(LARM:RM!HU31) -> -1000 | HV31: =SUM(LARM:RM!HV31) -> 0 | HW31: =SUM(LARM:RM!HW31) -> 0 | HX31: =SUM(LARM:RM!HX31) -> 0 | HY31: =SUM(LARM:RM!HY31) -> 0 | HZ31: =SUM(LARM:RM!HZ31) -> 0 | IA31: =SUM(LARM:RM!IA31) -> 0 | IB31: =SUM(LARM:RM!IB31) -> 0 | ... IY31: =SUM(LARM:RM!IY31) -> 0 | IZ31: =SUM(HU31:IY31) -> -6000 | JA31: =SUM(LARM:RM!JA31) -> -1000 | JB31: =SUM(LARM:RM!JB31) -> 0 | JC31: =SUM(LARM:RM!JC31) -> 0 | JD31: =SUM(LARM:RM!JD31) -> 0 | JE31: =SUM(LARM:RM!JE31) -> 0 | JF31: =SUM(LARM:RM!JF31) -> 0 | JG31: =SUM(LARM:RM!JG31) -> 0 | JH31: =SUM(LARM:RM!JH31) -> 0 | ... KE31: =SUM(LARM:RM!KE31) -> 0 | KF31: =SUM(JA31:KE31) -> -6000 | KG31: =SUM(LARM:RM!KG31) -> -1000 | KH31: =SUM(LARM:RM!KH31) -> 0 | KI31: =SUM(LARM:RM!KI31) -> 0 | KJ31: =SUM(LARM:RM!KJ31) -> 0 | KK31: =SUM(LARM:RM!KK31) -> 0 | KL31: =SUM(LARM:RM!KL31) -> 0 | KM31: =SUM(LARM:RM!KM31) -> 0 | KN31: =SUM(LARM:RM!KN31) -> 0 | ... LK31: =SUM(LARM:RM!LK31) -> 0 | LL31: =SUM(KG31:LK31) -> -6000 | LM31: =SUM(LARM:RM!LM31) -> 0 | LN31: =SUM(LARM:RM!LN31) -> 0 | LO31: =SUM(LARM:RM!LO31) -> -1000 | LP31: =SUM(LARM:RM!LP31) -> 0 | LQ31: =SUM(LARM:RM!LQ31) -> 0 | LR31: =SUM(LARM:RM!LR31) -> 0 | LS31: =SUM(LARM:RM!LS31) -> 0 | LT31: =SUM(LARM:RM!LT31) -> 0 | ... MQ31: =SUM(LARM:RM!MQ31) -> 0 | MR31: =SUM(LM31:MQ31) -> -6000 | MS31: =SUM(LARM:RM!MS31) -> 0 | MT31: =SUM(LARM:RM!MT31) -> 0 | MU31: =SUM(LARM:RM!MU31) -> -1000 | MV31: =SUM(LARM:RM!MV31) -> 0 | MW31: =SUM(LARM:RM!MW31) -> 0 | MX31: =SUM(LARM:RM!MX31) -> 0 | MY31: =SUM(LARM:RM!MY31) -> 0 | MZ31: =SUM(LARM:RM!MZ31) -> 0 | ... NW31: =SUM(LARM:RM!NW31) -> 0 | NX31: =SUM(MS31:NW31) -> -6000 | NZ31: =AJ31+BP31+CV31+EB31+FH31+GN31+HT31+IZ31+KF31+LL31+MR31+NX31 -> -126337.64 | OA31: =SUM(OI31:OP31) -> -46000 | OB31: =IF(OA31=0,"",((NZ31/OA31)-1)*-1) -> -1.7464704 | OG31: RECEITAS/DESPESAS NÃO OPERACIONAIS | OI31: =SUM(LARM:RM!OI31) -> -6000 | OJ31: =SUM(LARM:RM!OJ31) -> -6000 | OK31: =SUM(LARM:RM!OK31) -> -6000 | OL31: =SUM(LARM:RM!OL31) -> -6000 | OM31: =SUM(LARM:RM!OM31) -> -6000 | ON31: =SUM(LARM:RM!ON31) -> -4000 | OO31: =SUM(LARM:RM!OO31) -> -6000 | OP31: =SUM(LARM:RM!OP31) -> -6000 | ... OT31: =SUM(LARM:RM!OT31) -> -6000 | OV31: =SUM(OI31:OT31) -> -70000
C33: Resultado Financeiro | E33: =E34+E36+E38 -> 0 | F33: =F34+F36+F38 -> 40.46 | G33: =G34+G36+G38 -> 0 | H33: =H34+H36+H38 -> 0 | I33: =I34+I36+I38 -> -422.47 | J33: =J34+J36+J38 -> -39.12 | K33: =K34+K36+K38 -> -21.57 | L33: =L34+L36+L38 -> 65.02 | ... NX33: =NX34+NX36+NX38 -> 20116.9 | NZ33: =NZ34+NZ36+NZ38 -> 251705.95 | OA33: =OA34+OA36+OA38 -> 513886.95 | OB33: =IF(OA33=0,"",((NZ33/OA33)-1)*-1) -> 0.51019198 | OG33: Resultado Financeiro | OI33: =OI34+OI36+OI38 -> 21611.64 | OJ33: =OJ34+OJ36+OJ38 -> 21488.97 | OK33: =OK34+OK36+OK38 -> 21356.51 | OL33: =OL34+OL36+OL38 -> 26260.4 | OM33: =OM34+OM36+OM38 -> 352597.58 | ON33: =ON34+ON36+ON38 -> 23649.985 | OO33: =OO34+OO36+OO38 -> 23649.985 | OP33: =OP34+OP36+OP38 -> 23271.88 | ... OT33: =OT34+OT36+OT38 -> 23271.88 | OV33: =OV34+OV36+OV38 -> 607892.31
C34: Receitas Financeiras | E34: =SUM(E35:E35) -> 0 | F34: =SUM(F35:F35) -> 52.52 | G34: =SUM(G35:G35) -> 0 | H34: =SUM(H35:H35) -> 0 | I34: =SUM(I35:I35) -> 0.08 | J34: =SUM(J35:J35) -> 0 | K34: =SUM(K35:K35) -> 2.61 | L34: =SUM(L35:L35) -> 86.58 | ... NX34: =SUM(NX35:NX35) -> 23073.73 | NZ34: =SUM(NZ35:NZ35) -> 288878.21 | OA34: =SUM(OA35:OA35) -> 537541.59 | OB34: =IF(OA34=0,"",((NZ34/OA34)-1)*-1) -> 0.46259375 | OG34: Receitas Financeiras | OI34: =SUM(OI35:OI35) -> 24568.47 | OJ34: =SUM(OJ35:OJ35) -> 24445.8 | OK34: =SUM(OK35:OK35) -> 24313.34 | OL34: =SUM(OL35:OL35) -> 29217.23 | OM34: =SUM(OM35:OM35) -> 355554.41 | ON34: =SUM(ON35:ON35) -> 26606.815 | OO34: =SUM(OO35:OO35) -> 26606.815 | OP34: =SUM(OP35:OP35) -> 26228.71 | ... OT34: =SUM(OT35:OT35) -> 26228.71 | OV34: =SUM(OV35:OV35) -> 643374.27
B35: 5.1 | C35: RECEITAS FINANCEIRAS | E35: =SUM(LARM:RM!E35) -> 0 | F35: =SUM(LARM:RM!F35) -> 52.52 | G35: =SUM(LARM:RM!G35) -> 0 | H35: =SUM(LARM:RM!H35) -> 0 | I35: =SUM(LARM:RM!I35) -> 0.08 | J35: =SUM(LARM:RM!J35) -> 0 | K35: =SUM(LARM:RM!K35) -> 2.61 | L35: =SUM(LARM:RM!L35) -> 86.58 | ... AI35: =SUM(LARM:RM!AI35) -> 14337.99 | AJ35: =SUM(E35:AI35) -> 14552.66 | AK35: =SUM(LARM:RM!AK35) -> 0 | AL35: =SUM(LARM:RM!AL35) -> 4.46 | AM35: =SUM(LARM:RM!AM35) -> 0 | AN35: =SUM(LARM:RM!AN35) -> 0 | AO35: =SUM(LARM:RM!AO35) -> 0.67 | AP35: =SUM(LARM:RM!AP35) -> 0.06 | AQ35: =SUM(LARM:RM!AQ35) -> 0 | AR35: =SUM(LARM:RM!AR35) -> 0 | ... BO35: =SUM(LARM:RM!BO35) -> 0 | BP35: =SUM(AK35:BO35) -> 60127.74 | BQ35: =SUM(LARM:RM!BQ35) -> 0 | BR35: =SUM(LARM:RM!BR35) -> 0 | BS35: =SUM(LARM:RM!BS35) -> 0 | BT35: =SUM(LARM:RM!BT35) -> 0.14 | BU35: =SUM(LARM:RM!BU35) -> 0.54 | BV35: =SUM(LARM:RM!BV35) -> 0.83 | BW35: =SUM(LARM:RM!BW35) -> 0 | BX35: =SUM(LARM:RM!BX35) -> 0 | ... CU35: =SUM(LARM:RM!CU35) -> 13014.28 | CV35: =SUM(BQ35:CU35) -> 18096.082 | CW35: =SUM(LARM:RM!CW35) -> 12.11 | CX35: =SUM(LARM:RM!CX35) -> 0.01 | CY35: =SUM(LARM:RM!CY35) -> 0 | CZ35: =SUM(LARM:RM!CZ35) -> 0 | DA35: =SUM(LARM:RM!DA35) -> 0 | DB35: =SUM(LARM:RM!DB35) -> 1.31 | DC35: =SUM(LARM:RM!DC35) -> 0 | DD35: =SUM(LARM:RM!DD35) -> 0.01 | ... EA35: =SUM(LARM:RM!EA35) -> 0 | EB35: =SUM(CW35:EA35) -> 8056.4 | EC35: =SUM(LARM:RM!EC35) -> 0 | ED35: =SUM(LARM:RM!ED35) -> 0 | EE35: =SUM(LARM:RM!EE35) -> 0 | EF35: =SUM(LARM:RM!EF35) -> 1.95 | EG35: =SUM(LARM:RM!EG35) -> 0 | EH35: =SUM(LARM:RM!EH35) -> 0 | EI35: =SUM(LARM:RM!EI35) -> 0 | EJ35: =SUM(LARM:RM!EJ35) -> 0 | ... FG35: =SUM(LARM:RM!FG35) -> 25609.43 | FH35: =SUM(EC35:FG35) -> 25611.38 | FI35: =SUM(LARM:RM!FI35) -> 0 | FJ35: =SUM(LARM:RM!FJ35) -> 0 | FK35: =SUM(LARM:RM!FK35) -> 0 | FL35: =SUM(LARM:RM!FL35) -> 0 | FM35: =SUM(LARM:RM!FM35) -> 0 | FN35: =SUM(LARM:RM!FN35) -> 0 | FO35: =SUM(LARM:RM!FO35) -> 0 | FP35: =SUM(LARM:RM!FP35) -> 0 | ... GM35: =SUM(LARM:RM!GM35) -> 0 | GN35: =SUM(FI35:GM35) -> 23073.73 | GO35: =SUM(LARM:RM!GO35) -> 0 | GP35: =SUM(LARM:RM!GP35) -> 0 | GQ35: =SUM(LARM:RM!GQ35) -> 0 | GR35: =SUM(LARM:RM!GR35) -> 0 | GS35: =SUM(LARM:RM!GS35) -> 0 | GT35: =SUM(LARM:RM!GT35) -> 0 | GU35: =SUM(LARM:RM!GU35) -> 0 | GV35: =SUM(LARM:RM!GV35) -> 0 | ... HS35: =SUM(LARM:RM!HS35) -> 23073.73 | HT35: =SUM(GO35:HS35) -> 23073.73 | HU35: =SUM(LARM:RM!HU35) -> 0 | HV35: =SUM(LARM:RM!HV35) -> 0 | HW35: =SUM(LARM:RM!HW35) -> 0 | HX35: =SUM(LARM:RM!HX35) -> 0 | HY35: =SUM(LARM:RM!HY35) -> 0 | HZ35: =SUM(LARM:RM!HZ35) -> 0 | IA35: =SUM(LARM:RM!IA35) -> 0 | IB35: =SUM(LARM:RM!IB35) -> 0 | ... IY35: =SUM(LARM:RM!IY35) -> 7181.36 | IZ35: =SUM(HU35:IY35) -> 23073.73 | JA35: =SUM(LARM:RM!JA35) -> 0 | JB35: =SUM(LARM:RM!JB35) -> 0 | JC35: =SUM(LARM:RM!JC35) -> 0 | JD35: =SUM(LARM:RM!JD35) -> 0 | JE35: =SUM(LARM:RM!JE35) -> 0 | JF35: =SUM(LARM:RM!JF35) -> 0 | JG35: =SUM(LARM:RM!JG35) -> 0 | JH35: =SUM(LARM:RM!JH35) -> 0 | ... KE35: =SUM(LARM:RM!KE35) -> 0 | KF35: =SUM(JA35:KE35) -> 25703.23 | KG35: =SUM(LARM:RM!KG35) -> 0 | KH35: =SUM(LARM:RM!KH35) -> 0 | KI35: =SUM(LARM:RM!KI35) -> 0 | KJ35: =SUM(LARM:RM!KJ35) -> 0 | KK35: =SUM(LARM:RM!KK35) -> 0 | KL35: =SUM(LARM:RM!KL35) -> 0 | KM35: =SUM(LARM:RM!KM35) -> 0 | KN35: =SUM(LARM:RM!KN35) -> 7181.36 | ... LK35: =SUM(LARM:RM!LK35) -> 14180.71 | LL35: =SUM(KG35:LK35) -> 21362.07 | LM35: =SUM(LARM:RM!LM35) -> 0 | LN35: =SUM(LARM:RM!LN35) -> 0 | LO35: =SUM(LARM:RM!LO35) -> 0 | LP35: =SUM(LARM:RM!LP35) -> 0 | LQ35: =SUM(LARM:RM!LQ35) -> 0 | LR35: =SUM(LARM:RM!LR35) -> 0 | LS35: =SUM(LARM:RM!LS35) -> 0 | LT35: =SUM(LARM:RM!LT35) -> 0 | ... MQ35: =SUM(LARM:RM!MQ35) -> 0 | MR35: =SUM(LM35:MQ35) -> 23073.73 | MS35: =SUM(LARM:RM!MS35) -> 0 | MT35: =SUM(LARM:RM!MT35) -> 0 | MU35: =SUM(LARM:RM!MU35) -> 0 | MV35: =SUM(LARM:RM!MV35) -> 0 | MW35: =SUM(LARM:RM!MW35) -> 0 | MX35: =SUM(LARM:RM!MX35) -> 0 | MY35: =SUM(LARM:RM!MY35) -> 0 | MZ35: =SUM(LARM:RM!MZ35) -> 0 | ... NW35: =SUM(LARM:RM!NW35) -> 7181.36 | NX35: =SUM(MS35:NW35) -> 23073.73 | NZ35: =AJ35+BP35+CV35+EB35+FH35+GN35+HT35+IZ35+KF35+LL35+MR35+NX35 -> 288878.21 | OA35: =SUM(OI35:OP35) -> 537541.59 | OB35: =IF(NZ35=0,"",(OA35/NZ35)-1) -> 0.86078966 | OG35: RECEITAS FINANCEIRAS | OI35: =SUM(LARM:RM!OI35) -> 24568.47 | OJ35: =SUM(LARM:RM!OJ35) -> 24445.8 | OK35: =SUM(LARM:RM!OK35) -> 24313.34 | OL35: =SUM(LARM:RM!OL35) -> 29217.23 | OM35: =SUM(LARM:RM!OM35) -> 355554.41 | ON35: =SUM(LARM:RM!ON35) -> 26606.815 | OO35: =SUM(LARM:RM!OO35) -> 26606.815 | OP35: =SUM(LARM:RM!OP35) -> 26228.71 | ... OT35: =SUM(LARM:RM!OT35) -> 26228.71 | OV35: =SUM(OI35:OT35) -> 643374.27
C36: Despesas Financeiras | E36: =SUM(E37) -> 0 | F36: =SUM(F37) -> -12.06 | G36: =SUM(G37) -> 0 | H36: =SUM(H37) -> 0 | I36: =SUM(I37) -> -422.55 | J36: =SUM(J37) -> -39.12 | K36: =SUM(K37) -> -24.18 | L36: =SUM(L37) -> -21.56 | ... NX36: =SUM(NX37) -> -2956.83 | NZ36: =SUM(NZ37) -> -23172.26 | OA36: =SUM(OA37:OA38) -> -23654.64 | OB36: =IF(OA36=0,"",((NZ36/OA36)-1)*-1) -> 0.020392616 | OG36: Despesas Financeiras | OI36: =SUM(OI37) -> -2956.83 | OJ36: =SUM(OJ37) -> -2956.83 | OK36: =SUM(OK37) -> -2956.83 | OL36: =SUM(OL37) -> -2956.83 | OM36: =SUM(OM37) -> -2956.83 | ON36: =SUM(ON37) -> -2956.83 | OO36: =SUM(OO37) -> -2956.83 | OP36: =SUM(OP37) -> -2956.83 | ... OT36: =SUM(OT37) -> -2956.83 | OV36: =SUM(OV37) -> -35481.96
B37: 5.2 | C37: DESPESAS FINANCEIRAS | E37: =SUM(LARM:RM!E37) -> 0 | F37: =SUM(LARM:RM!F37) -> -12.06 | G37: =SUM(LARM:RM!G37) -> 0 | H37: =SUM(LARM:RM!H37) -> 0 | I37: =SUM(LARM:RM!I37) -> -422.55 | J37: =SUM(LARM:RM!J37) -> -39.12 | K37: =SUM(LARM:RM!K37) -> -24.18 | L37: =SUM(LARM:RM!L37) -> -21.56 | ... AI37: =SUM(LARM:RM!AI37) -> 0 | AJ37: =SUM(E37:AI37) -> -3123.2 | AK37: =SUM(LARM:RM!AK37) -> 0 | AL37: =SUM(LARM:RM!AL37) -> -27.77 | AM37: =SUM(LARM:RM!AM37) -> -406.99 | AN37: =SUM(LARM:RM!AN37) -> -21.12 | AO37: =SUM(LARM:RM!AO37) -> -15 | AP37: =SUM(LARM:RM!AP37) -> -39.12 | AQ37: =SUM(LARM:RM!AQ37) -> 0 | AR37: =SUM(LARM:RM!AR37) -> 0 | ... BO37: =SUM(LARM:RM!BO37) -> 0 | BP37: =SUM(AK37:BO37) -> -2387.89 | BQ37: =SUM(LARM:RM!BQ37) -> 0 | BR37: =SUM(LARM:RM!BR37) -> -49.58 | BS37: =SUM(LARM:RM!BS37) -> -140.92 | BT37: =SUM(LARM:RM!BT37) -> -33.46 | BU37: =SUM(LARM:RM!BU37) -> -317.31 | BV37: =SUM(LARM:RM!BV37) -> -9 | BW37: =SUM(LARM:RM!BW37) -> 0 | BX37: =SUM(LARM:RM!BX37) -> 0 | ... CU37: =SUM(LARM:RM!CU37) -> -944.58 | CV37: =SUM(BQ37:CU37) -> 7475.84 | CW37: =SUM(LARM:RM!CW37) -> -24.12 | CX37: =SUM(LARM:RM!CX37) -> -128.04 | CY37: =SUM(LARM:RM!CY37) -> 0 | CZ37: =SUM(LARM:RM!CZ37) -> 0 | DA37: =SUM(LARM:RM!DA37) -> 0 | DB37: =SUM(LARM:RM!DB37) -> -323.19 | DC37: =SUM(LARM:RM!DC37) -> -27 | DD37: =SUM(LARM:RM!DD37) -> -18.18 | ... EA37: =SUM(LARM:RM!EA37) -> 0 | EB37: =SUM(CW37:EA37) -> -1481.05 | EC37: =SUM(LARM:RM!EC37) -> 0 | ED37: =SUM(LARM:RM!ED37) -> 0 | EE37: =SUM(LARM:RM!EE37) -> 0 | EF37: =SUM(LARM:RM!EF37) -> -48.94 | EG37: =SUM(LARM:RM!EG37) -> -39.18 | EH37: =SUM(LARM:RM!EH37) -> 0 | EI37: =SUM(LARM:RM!EI37) -> 0 | EJ37: =SUM(LARM:RM!EJ37) -> 0 | ... FG37: =SUM(LARM:RM!FG37) -> -998.57 | FH37: =SUM(EC37:FG37) -> -2958.15 | FI37: =SUM(LARM:RM!FI37) -> 0 | FJ37: =SUM(LARM:RM!FJ37) -> 0 | FK37: =SUM(LARM:RM!FK37) -> -86.8 | FL37: =SUM(LARM:RM!FL37) -> 0 | FM37: =SUM(LARM:RM!FM37) -> 0 | FN37: =SUM(LARM:RM!FN37) -> 0 | FO37: =SUM(LARM:RM!FO37) -> 0 | FP37: =SUM(LARM:RM!FP37) -> 0 | ... GM37: =SUM(LARM:RM!GM37) -> 0 | GN37: =SUM(FI37:GM37) -> -2956.83 | GO37: =SUM(LARM:RM!GO37) -> 0 | GP37: =SUM(LARM:RM!GP37) -> -86.8 | GQ37: =SUM(LARM:RM!GQ37) -> 0 | GR37: =SUM(LARM:RM!GR37) -> 0 | GS37: =SUM(LARM:RM!GS37) -> 0 | GT37: =SUM(LARM:RM!GT37) -> 0 | GU37: =SUM(LARM:RM!GU37) -> 0 | GV37: =SUM(LARM:RM!GV37) -> 0 | ... HS37: =SUM(LARM:RM!HS37) -> -998.57 | HT37: =SUM(GO37:HS37) -> -2956.83 | HU37: =SUM(LARM:RM!HU37) -> 0 | HV37: =SUM(LARM:RM!HV37) -> 0 | HW37: =SUM(LARM:RM!HW37) -> 0 | HX37: =SUM(LARM:RM!HX37) -> -86.8 | HY37: =SUM(LARM:RM!HY37) -> 0 | HZ37: =SUM(LARM:RM!HZ37) -> 0 | IA37: =SUM(LARM:RM!IA37) -> 0 | IB37: =SUM(LARM:RM!IB37) -> 0 | ... IY37: =SUM(LARM:RM!IY37) -> -998.57 | IZ37: =SUM(HU37:IY37) -> -2956.83 | JA37: =SUM(LARM:RM!JA37) -> 0 | JB37: =SUM(LARM:RM!JB37) -> -86.8 | JC37: =SUM(LARM:RM!JC37) -> 0 | JD37: =SUM(LARM:RM!JD37) -> 0 | JE37: =SUM(LARM:RM!JE37) -> 0 | JF37: =SUM(LARM:RM!JF37) -> 0 | JG37: =SUM(LARM:RM!JG37) -> 0 | JH37: =SUM(LARM:RM!JH37) -> 0 | ... KE37: =SUM(LARM:RM!KE37) -> 0 | KF37: =SUM(JA37:KE37) -> -2956.83 | KG37: =SUM(LARM:RM!KG37) -> 0 | KH37: =SUM(LARM:RM!KH37) -> -86.8 | KI37: =SUM(LARM:RM!KI37) -> 0 | KJ37: =SUM(LARM:RM!KJ37) -> 0 | KK37: =SUM(LARM:RM!KK37) -> 0 | KL37: =SUM(LARM:RM!KL37) -> 0 | KM37: =SUM(LARM:RM!KM37) -> 0 | KN37: =SUM(LARM:RM!KN37) -> 0 | ... LK37: =SUM(LARM:RM!LK37) -> -998.57 | LL37: =SUM(KG37:LK37) -> -2956.83 | LM37: =SUM(LARM:RM!LM37) -> 0 | LN37: =SUM(LARM:RM!LN37) -> 0 | LO37: =SUM(LARM:RM!LO37) -> -86.8 | LP37: =SUM(LARM:RM!LP37) -> 0 | LQ37: =SUM(LARM:RM!LQ37) -> 0 | LR37: =SUM(LARM:RM!LR37) -> 0 | LS37: =SUM(LARM:RM!LS37) -> 0 | LT37: =SUM(LARM:RM!LT37) -> 0 | ... MQ37: =SUM(LARM:RM!MQ37) -> 0 | MR37: =SUM(LM37:MQ37) -> -2956.83 | MS37: =SUM(LARM:RM!MS37) -> 0 | MT37: =SUM(LARM:RM!MT37) -> 0 | MU37: =SUM(LARM:RM!MU37) -> -86.8 | MV37: =SUM(LARM:RM!MV37) -> 0 | MW37: =SUM(LARM:RM!MW37) -> 0 | MX37: =SUM(LARM:RM!MX37) -> 0 | MY37: =SUM(LARM:RM!MY37) -> 0 | MZ37: =SUM(LARM:RM!MZ37) -> 0 | ... NW37: =SUM(LARM:RM!NW37) -> -998.57 | NX37: =SUM(MS37:NW37) -> -2956.83 | NZ37: =AJ37+BP37+CV37+EB37+FH37+GN37+HT37+IZ37+KF37+LL37+MR37+NX37 -> -23172.26 | OA37: =SUM(OI37:OP37) -> -23654.64 | OB37: =IF(OA37=0,"",((NZ37/OA37)-1)*-1) -> 0.020392616 | OG37: DESPESAS FINANCEIRAS | OI37: =SUM(LARM:RM!OI37) -> -2956.83 | OJ37: =SUM(LARM:RM!OJ37) -> -2956.83 | OK37: =SUM(LARM:RM!OK37) -> -2956.83 | OL37: =SUM(LARM:RM!OL37) -> -2956.83 | OM37: =SUM(LARM:RM!OM37) -> -2956.83 | ON37: =SUM(LARM:RM!ON37) -> -2956.83 | OO37: =SUM(LARM:RM!OO37) -> -2956.83 | OP37: =SUM(LARM:RM!OP37) -> -2956.83 | ... OT37: =SUM(LARM:RM!OT37) -> -2956.83 | OV37: =SUM(OI37:OT37) -> -35481.96
C38: Emprestimos e Financiamentos | E38: =SUM(E39) -> 0 | F38: =SUM(F39) -> 0 | G38: =SUM(G39) -> 0 | H38: =SUM(H39) -> 0 | I38: =SUM(I39) -> 0 | J38: =SUM(J39) -> 0 | K38: =SUM(K39) -> 0 | L38: =SUM(L39) -> 0 | ... NX38: =SUM(NX39) -> 0 | NZ38: =SUM(NZ39:NZ40) -> -14000 | OA38: =SUM(OA39:OA40) -> 0 | OB38: =IF(OA38=0,"",((NZ38/OA38)-1)*-1) | OG38: Emprestimos e Financiamentos | OI38: =SUM(OI39) -> 0 | OJ38: =SUM(OJ39) -> 0 | OK38: =SUM(OK39) -> 0 | OL38: =SUM(OL39) -> 0 | OM38: =SUM(OM39) -> 0 | ON38: =SUM(ON39) -> 0 | OO38: =SUM(OO39) -> 0 | OP38: =SUM(OP39) -> 0 | ... OT38: =SUM(OT39) -> 0 | OV38: =SUM(OV39) -> 0
B39: 7.4 | C39: Emprestimos e Financiamentos | E39: =SUM(LARM:RM!E39) -> 0 | F39: =SUM(LARM:RM!F39) -> 0 | G39: =SUM(LARM:RM!G39) -> 0 | H39: =SUM(LARM:RM!H39) -> 0 | I39: =SUM(LARM:RM!I39) -> 0 | J39: =SUM(LARM:RM!J39) -> 0 | K39: =SUM(LARM:RM!K39) -> 0 | L39: =SUM(LARM:RM!L39) -> 0 | ... AI39: =SUM(LARM:RM!AI39) -> 0 | AJ39: =SUM(E39:AI39) -> -14000 | AK39: =SUM(LARM:RM!AK39) -> 0 | AL39: =SUM(LARM:RM!AL39) -> 0 | AM39: =SUM(LARM:RM!AM39) -> 0 | AN39: =SUM(LARM:RM!AN39) -> 0 | AO39: =SUM(LARM:RM!AO39) -> 0 | AP39: =SUM(LARM:RM!AP39) -> 0 | AQ39: =SUM(LARM:RM!AQ39) -> 0 | AR39: =SUM(LARM:RM!AR39) -> 0 | ... BO39: =SUM(LARM:RM!BO39) -> 0 | BP39: =SUM(AK39:BO39) -> 0 | BQ39: =SUM(LARM:RM!BQ39) -> 0 | BR39: =SUM(LARM:RM!BR39) -> 0 | BS39: =SUM(LARM:RM!BS39) -> 0 | BT39: =SUM(LARM:RM!BT39) -> 0 | BU39: =SUM(LARM:RM!BU39) -> 0 | BV39: =SUM(LARM:RM!BV39) -> 0 | BW39: =SUM(LARM:RM!BW39) -> 0 | BX39: =SUM(LARM:RM!BX39) -> 0 | ... CU39: =SUM(LARM:RM!CU39) -> 0 | CV39: =SUM(BQ39:CU39) -> 0 | CW39: =SUM(LARM:RM!CW39) -> 0 | CX39: =SUM(LARM:RM!CX39) -> 0 | CY39: =SUM(LARM:RM!CY39) -> 0 | CZ39: =SUM(LARM:RM!CZ39) -> 0 | DA39: =SUM(LARM:RM!DA39) -> 0 | DB39: =SUM(LARM:RM!DB39) -> 0 | DC39: =SUM(LARM:RM!DC39) -> 0 | DD39: =SUM(LARM:RM!DD39) -> 0 | ... EA39: =SUM(LARM:RM!EA39) -> 0 | EB39: =SUM(CW39:EA39) -> 0 | EC39: =SUM(LARM:RM!EC39) -> 0 | ED39: =SUM(LARM:RM!ED39) -> 0 | EE39: =SUM(LARM:RM!EE39) -> 0 | EF39: =SUM(LARM:RM!EF39) -> 0 | EG39: =SUM(LARM:RM!EG39) -> 0 | EH39: =SUM(LARM:RM!EH39) -> 0 | EI39: =SUM(LARM:RM!EI39) -> 0 | EJ39: =SUM(LARM:RM!EJ39) -> 0 | ... FG39: =SUM(LARM:RM!FG39) -> 0 | FH39: =SUM(EC39:FG39) -> 0 | FI39: =SUM(LARM:RM!FI39) -> 0 | FJ39: =SUM(LARM:RM!FJ39) -> 0 | FK39: =SUM(LARM:RM!FK39) -> 0 | FL39: =SUM(LARM:RM!FL39) -> 0 | FM39: =SUM(LARM:RM!FM39) -> 0 | FN39: =SUM(LARM:RM!FN39) -> 0 | FO39: =SUM(LARM:RM!FO39) -> 0 | FP39: =SUM(LARM:RM!FP39) -> 0 | ... GM39: =SUM(LARM:RM!GM39) -> 0 | GN39: =SUM(FI39:GM39) -> 0 | GO39: =SUM(LARM:RM!GO39) -> 0 | GP39: =SUM(LARM:RM!GP39) -> 0 | GQ39: =SUM(LARM:RM!GQ39) -> 0 | GR39: =SUM(LARM:RM!GR39) -> 0 | GS39: =SUM(LARM:RM!GS39) -> 0 | GT39: =SUM(LARM:RM!GT39) -> 0 | GU39: =SUM(LARM:RM!GU39) -> 0 | GV39: =SUM(LARM:RM!GV39) -> 0 | ... HS39: =SUM(LARM:RM!HS39) -> 0 | HT39: =SUM(GO39:HS39) -> 0 | HU39: =SUM(LARM:RM!HU39) -> 0 | HV39: =SUM(LARM:RM!HV39) -> 0 | HW39: =SUM(LARM:RM!HW39) -> 0 | HX39: =SUM(LARM:RM!HX39) -> 0 | HY39: =SUM(LARM:RM!HY39) -> 0 | HZ39: =SUM(LARM:RM!HZ39) -> 0 | IA39: =SUM(LARM:RM!IA39) -> 0 | IB39: =SUM(LARM:RM!IB39) -> 0 | ... IY39: =SUM(LARM:RM!IY39) -> 0 | IZ39: =SUM(HU39:IY39) -> 0 | JA39: =SUM(LARM:RM!JA39) -> 0 | JB39: =SUM(LARM:RM!JB39) -> 0 | JC39: =SUM(LARM:RM!JC39) -> 0 | JD39: =SUM(LARM:RM!JD39) -> 0 | JE39: =SUM(LARM:RM!JE39) -> 0 | JF39: =SUM(LARM:RM!JF39) -> 0 | JG39: =SUM(LARM:RM!JG39) -> 0 | JH39: =SUM(LARM:RM!JH39) -> 0 | ... KE39: =SUM(LARM:RM!KE39) -> 0 | KF39: =SUM(JA39:KE39) -> 0 | KG39: =SUM(LARM:RM!KG39) -> 0 | KH39: =SUM(LARM:RM!KH39) -> 0 | KI39: =SUM(LARM:RM!KI39) -> 0 | KJ39: =SUM(LARM:RM!KJ39) -> 0 | KK39: =SUM(LARM:RM!KK39) -> 0 | KL39: =SUM(LARM:RM!KL39) -> 0 | KM39: =SUM(LARM:RM!KM39) -> 0 | KN39: =SUM(LARM:RM!KN39) -> 0 | ... LK39: =SUM(LARM:RM!LK39) -> 0 | LL39: =SUM(KG39:LK39) -> 0 | LM39: =SUM(LARM:RM!LM39) -> 0 | LN39: =SUM(LARM:RM!LN39) -> 0 | LO39: =SUM(LARM:RM!LO39) -> 0 | LP39: =SUM(LARM:RM!LP39) -> 0 | LQ39: =SUM(LARM:RM!LQ39) -> 0 | LR39: =SUM(LARM:RM!LR39) -> 0 | LS39: =SUM(LARM:RM!LS39) -> 0 | LT39: =SUM(LARM:RM!LT39) -> 0 | ... MQ39: =SUM(LARM:RM!MQ39) -> 0 | MR39: =SUM(LM39:MQ39) -> 0 | MS39: =SUM(LARM:RM!MS39) -> 0 | MT39: =SUM(LARM:RM!MT39) -> 0 | MU39: =SUM(LARM:RM!MU39) -> 0 | MV39: =SUM(LARM:RM!MV39) -> 0 | MW39: =SUM(LARM:RM!MW39) -> 0 | MX39: =SUM(LARM:RM!MX39) -> 0 | MY39: =SUM(LARM:RM!MY39) -> 0 | MZ39: =SUM(LARM:RM!MZ39) -> 0 | ... NW39: =SUM(LARM:RM!NW39) -> 0 | NX39: =SUM(MS39:NW39) -> 0 | NZ39: =AJ39+BP39+CV39+EB39+FH39+GN39+HT39+IZ39+KF39+LL39+MR39+NX39 -> -14000 | OA39: =SUM(OI39:OP39) -> 0 | OB39: =IF(OA39=0,"",((NZ39/OA39)-1)*-1) | OG39: Emprestimos e Financiamentos | OI39: =SUM(LARM:RM!OI39) -> 0 | OJ39: =SUM(LARM:RM!OJ39) -> 0 | OK39: =SUM(LARM:RM!OK39) -> 0 | OL39: =SUM(LARM:RM!OL39) -> 0 | OM39: =SUM(LARM:RM!OM39) -> 0 | ON39: =SUM(LARM:RM!ON39) -> 0 | OO39: =SUM(LARM:RM!OO39) -> 0 | OP39: =SUM(LARM:RM!OP39) -> 0 | ... OT39: =SUM(LARM:RM!OT39) -> 0 | OV39: =SUM(OI39:OT39) -> 0
C42: Geração de Caixa | E42: =E16+E18+E33 -> 0 | F42: =F16+F18+F33 -> -61577.23 | G42: =G16+G18+G33 -> 0 | H42: =H16+H18+H33 -> 0 | I42: =I16+I18+I33 -> 11977.32 | J42: =J16+J18+J33 -> 41438.67 | K42: =K16+K18+K33 -> -9951.41 | L42: =L16+L18+L33 -> -25149.89 | ... NX42: =NX16+NX18+NX33 -> -248066.21 | NZ42: =NZ16+NZ18+NZ33 -> -1764091 | OA42: =OA16+OA18+OA33 -> -492064.84 | OB42: =IF(OA42=0,"",((NZ42/OA42)-1)*-1) -> -2.5850784 | OG42: Geração de Caixa | OI42: =OI16+OI18+OI33 -> -213368.2 | OJ42: =OJ16+OJ18+OJ33 -> -190128.57 | OK42: =OK16+OK18+OK33 -> -55112.465 | OL42: =OL16+OL18+OL33 -> -112699.16 | OM42: =OM16+OM18+OM33 -> -20726.475 | ON42: =ON16+ON18+ON33 -> -81992.56 | OO42: =OO16+OO18+OO33 -> -52246.345 | OP42: =OP16+OP18+OP33 -> 30649.295 | ... OT42: =OT16+OT18+OT33 -> -147845.69 | OV42: =OV16+OV18+OV33 -> -1057001.8
B44: 7. | C44: Investimentos | E44: =SUM(E45:E57) -> 0 | F44: =SUM(F45:F57) -> -17362.73 | G44: =SUM(G45:G57) -> 0 | H44: =SUM(H45:H57) -> 0 | I44: =SUM(I45:I57) -> -946.67 | J44: =SUM(J45:J57) -> 0 | K44: =SUM(K45:K57) -> 0 | L44: =SUM(L45:L57) -> 0 | ... NX44: =SUM(NX45:NX57) -> -55373.33 | NZ44: =SUM(NZ45:NZ57) -> -210447.09 | OA44: =SUM(OA45:OA57) -> -639469.42 | OB44: =IF(OA44=0,"",((NZ44/OA44)-1)*-1) -> 0.67090359 | OG44: Investimentos | OI44: =SUM(OI45:OI57) -> -34362.73 | OJ44: =SUM(OJ45:OJ57) -> -158066.67 | OK44: =SUM(OK45:OK57) -> -158066.67 | OL44: =SUM(OL45:OL57) -> -143066.67 | OM44: =SUM(OM45:OM57) -> -36476.67 | ON44: =SUM(ON45:ON57) -> -36476.67 | OO44: =SUM(OO45:OO57) -> -36476.67 | OP44: =SUM(OP45:OP57) -> -36476.67 | ... OT44: =SUM(OT45:OT57) -> -35530 | OV44: =SUM(OV45:OV57) -> -784429.43
B45: 7.3 | C45: ATIVO IMOBILIZADO | E45: =SUM(LARM:RM!E45) -> 0 | F45: =SUM(LARM:RM!F45) -> -17362.73 | G45: =SUM(LARM:RM!G45) -> 0 | H45: =SUM(LARM:RM!H45) -> 0 | I45: =SUM(LARM:RM!I45) -> -946.67 | J45: =SUM(LARM:RM!J45) -> 0 | K45: =SUM(LARM:RM!K45) -> 0 | L45: =SUM(LARM:RM!L45) -> 0 | ... AI45: =SUM(LARM:RM!AI45) -> 0 | AJ45: =SUM(E45:AI45) -> -18309.4 | AK45: =SUM(LARM:RM!AK45) -> 0 | AL45: =SUM(LARM:RM!AL45) -> 0 | AM45: =SUM(LARM:RM!AM45) -> 0 | AN45: =SUM(LARM:RM!AN45) -> 0 | AO45: =SUM(LARM:RM!AO45) -> -946.67 | AP45: =SUM(LARM:RM!AP45) -> 0 | AQ45: =SUM(LARM:RM!AQ45) -> 0 | AR45: =SUM(LARM:RM!AR45) -> 0 | ... BO45: =SUM(LARM:RM!BO45) -> 0 | BP45: =SUM(AK45:BO45) -> -946.67 | BQ45: =SUM(LARM:RM!BQ45) -> 0 | BR45: =SUM(LARM:RM!BR45) -> 0 | BS45: =SUM(LARM:RM!BS45) -> 0 | BT45: =SUM(LARM:RM!BT45) -> 0 | BU45: =SUM(LARM:RM!BU45) -> -946.67 | BV45: =SUM(LARM:RM!BV45) -> 0 | BW45: =SUM(LARM:RM!BW45) -> 0 | BX45: =SUM(LARM:RM!BX45) -> 0 | ... CU45: =SUM(LARM:RM!CU45) -> 0 | CV45: =SUM(BQ45:CU45) -> -946.67 | CW45: =SUM(LARM:RM!CW45) -> 0 | CX45: =SUM(LARM:RM!CX45) -> 0 | CY45: =SUM(LARM:RM!CY45) -> 0 | CZ45: =SUM(LARM:RM!CZ45) -> 0 | DA45: =SUM(LARM:RM!DA45) -> 0 | DB45: =SUM(LARM:RM!DB45) -> -946.67 | DC45: =SUM(LARM:RM!DC45) -> 0 | DD45: =SUM(LARM:RM!DD45) -> 0 | ... EA45: =SUM(LARM:RM!EA45) -> 0 | EB45: =SUM(CW45:EA45) -> -7871.66 | EC45: =SUM(LARM:RM!EC45) -> 0 | ED45: =SUM(LARM:RM!ED45) -> 0 | EE45: =SUM(LARM:RM!EE45) -> 0 | EF45: =SUM(LARM:RM!EF45) -> 0 | EG45: =SUM(LARM:RM!EG45) -> 0 | EH45: =SUM(LARM:RM!EH45) -> 0 | EI45: =SUM(LARM:RM!EI45) -> 0 | EJ45: =SUM(LARM:RM!EJ45) -> 0 | ... FG45: =SUM(LARM:RM!FG45) -> 0 | FH45: =SUM(EC45:FG45) -> -13666.667 | FI45: =SUM(LARM:RM!FI45) -> 0 | FJ45: =SUM(LARM:RM!FJ45) -> 0 | FK45: =SUM(LARM:RM!FK45) -> 0 | FL45: =SUM(LARM:RM!FL45) -> 0 | FM45: =SUM(LARM:RM!FM45) -> -946.67 | FN45: =SUM(LARM:RM!FN45) -> 0 | FO45: =SUM(LARM:RM!FO45) -> 0 | FP45: =SUM(LARM:RM!FP45) -> 0 | ... GM45: =SUM(LARM:RM!GM45) -> 0 | GN45: =SUM(FI45:GM45) -> -12613.337 | GO45: =SUM(LARM:RM!GO45) -> 0 | GP45: =SUM(LARM:RM!GP45) -> 0 | GQ45: =SUM(LARM:RM!GQ45) -> 0 | GR45: =SUM(LARM:RM!GR45) -> 0 | GS45: =SUM(LARM:RM!GS45) -> -946.67 | GT45: =SUM(LARM:RM!GT45) -> 0 | GU45: =SUM(LARM:RM!GU45) -> 0 | GV45: =SUM(LARM:RM!GV45) -> 0 | ... HS45: =SUM(LARM:RM!HS45) -> 0 | HT45: =SUM(GO45:HS45) -> -12613.337 | HU45: =SUM(LARM:RM!HU45) -> 0 | HV45: =SUM(LARM:RM!HV45) -> 0 | HW45: =SUM(LARM:RM!HW45) -> 0 | HX45: =SUM(LARM:RM!HX45) -> 0 | HY45: =SUM(LARM:RM!HY45) -> -946.67 | HZ45: =SUM(LARM:RM!HZ45) -> 0 | IA45: =SUM(LARM:RM!IA45) -> 0 | IB45: =SUM(LARM:RM!IB45) -> 0 | ... IY45: =SUM(LARM:RM!IY45) -> 0 | IZ45: =SUM(HU45:IY45) -> -12613.337 | JA45: =SUM(LARM:RM!JA45) -> 0 | JB45: =SUM(LARM:RM!JB45) -> 0 | JC45: =SUM(LARM:RM!JC45) -> 0 | JD45: =SUM(LARM:RM!JD45) -> 0 | JE45: =SUM(LARM:RM!JE45) -> -946.67 | JF45: =SUM(LARM:RM!JF45) -> 0 | JG45: =SUM(LARM:RM!JG45) -> 0 | JH45: =SUM(LARM:RM!JH45) -> 0 | ... KE45: =SUM(LARM:RM!KE45) -> 0 | KF45: =SUM(JA45:KE45) -> -12613.337 | KG45: =SUM(LARM:RM!KG45) -> 0 | KH45: =SUM(LARM:RM!KH45) -> 0 | KI45: =SUM(LARM:RM!KI45) -> 0 | KJ45: =SUM(LARM:RM!KJ45) -> 0 | KK45: =SUM(LARM:RM!KK45) -> -946.67 | KL45: =SUM(LARM:RM!KL45) -> 0 | KM45: =SUM(LARM:RM!KM45) -> 0 | KN45: =SUM(LARM:RM!KN45) -> 0 | ... LK45: =SUM(LARM:RM!LK45) -> 0 | LL45: =SUM(KG45:LK45) -> -12613.337 | LM45: =SUM(LARM:RM!LM45) -> 0 | LN45: =SUM(LARM:RM!LN45) -> 0 | LO45: =SUM(LARM:RM!LO45) -> 0 | LP45: =SUM(LARM:RM!LP45) -> 0 | LQ45: =SUM(LARM:RM!LQ45) -> -946.67 | LR45: =SUM(LARM:RM!LR45) -> 0 | LS45: =SUM(LARM:RM!LS45) -> 0 | LT45: =SUM(LARM:RM!LT45) -> 0 | ... MQ45: =SUM(LARM:RM!MQ45) -> 0 | MR45: =SUM(LM45:MQ45) -> -8946.67 | MS45: =SUM(LARM:RM!MS45) -> 0 | MT45: =SUM(LARM:RM!MT45) -> 0 | MU45: =SUM(LARM:RM!MU45) -> 0 | MV45: =SUM(LARM:RM!MV45) -> 0 | MW45: =SUM(LARM:RM!MW45) -> 0 | MX45: =SUM(LARM:RM!MX45) -> 0 | MY45: =SUM(LARM:RM!MY45) -> 0 | MZ45: =SUM(LARM:RM!MZ45) -> 0 | ... NW45: =SUM(LARM:RM!NW45) -> 0 | NX45: =SUM(MS45:NW45) -> -8000 | NZ45: =AJ45+BP45+CV45+EB45+FH45+GN45+HT45+IZ45+KF45+LL45+MR45+NX45 -> -121754.42 | OA45: =SUM(OI45:OP45) -> -53989.42 | OB45: =IF(NZ45=0,"",(OA45/NZ45)-1) -> -0.55657117 | OG45: ATIVO IMOBILIZADO | OI45: =SUM(LARM:RM!OI45) -> -17362.73 | OJ45: =SUM(LARM:RM!OJ45) -> -15946.67 | OK45: =SUM(LARM:RM!OK45) -> -15946.67 | OL45: =SUM(LARM:RM!OL45) -> -946.67 | OM45: =SUM(LARM:RM!OM45) -> -946.67 | ON45: =SUM(LARM:RM!ON45) -> -946.67 | OO45: =SUM(LARM:RM!OO45) -> -946.67 | OP45: =SUM(LARM:RM!OP45) -> -946.67 | ... OT45: =SUM(LARM:RM!OT45) -> 0 | OV45: =SUM(OI45:OT45) -> -56829.43
B46: 7.2 | C46: OUTROS INVESTIMENTOS | E46: =SUM(LARM:RM!E46) -> 0 | F46: =SUM(LARM:RM!F46) -> 0 | G46: =SUM(LARM:RM!G46) -> 0 | H46: =SUM(LARM:RM!H46) -> 0 | I46: =SUM(LARM:RM!I46) -> 0 | J46: =SUM(LARM:RM!J46) -> 0 | K46: =SUM(LARM:RM!K46) -> 0 | L46: =SUM(LARM:RM!L46) -> 0 | ... AI46: =SUM(LARM:RM!AI46) -> 0 | AJ46: =SUM(E46:AI46) -> 0 | AK46: =SUM(LARM:RM!AK46) -> 0 | AL46: =SUM(LARM:RM!AL46) -> 0 | AM46: =SUM(LARM:RM!AM46) -> 0 | AN46: =SUM(LARM:RM!AN46) -> 0 | AO46: =SUM(LARM:RM!AO46) -> 0 | AP46: =SUM(LARM:RM!AP46) -> 0 | AQ46: =SUM(LARM:RM!AQ46) -> 0 | AR46: =SUM(LARM:RM!AR46) -> 0 | ... BO46: =SUM(LARM:RM!BO46) -> 0 | BP46: =SUM(AK46:BO46) -> 0 | BQ46: =SUM(LARM:RM!BQ46) -> 0 | BR46: =SUM(LARM:RM!BR46) -> 0 | BS46: =SUM(LARM:RM!BS46) -> 0 | BT46: =SUM(LARM:RM!BT46) -> 0 | BU46: =SUM(LARM:RM!BU46) -> 0 | BV46: =SUM(LARM:RM!BV46) -> 0 | BW46: =SUM(LARM:RM!BW46) -> 0 | BX46: =SUM(LARM:RM!BX46) -> 0 | ... CU46: =SUM(LARM:RM!CU46) -> 0 | CV46: =SUM(BQ46:CU46) -> 0 | CW46: =SUM(LARM:RM!CW46) -> 0 | CX46: =SUM(LARM:RM!CX46) -> 0 | CY46: =SUM(LARM:RM!CY46) -> 0 | CZ46: =SUM(LARM:RM!CZ46) -> 0 | DA46: =SUM(LARM:RM!DA46) -> 0 | DB46: =SUM(LARM:RM!DB46) -> 0 | DC46: =SUM(LARM:RM!DC46) -> 0 | DD46: =SUM(LARM:RM!DD46) -> 0 | ... EA46: =SUM(LARM:RM!EA46) -> 0 | EB46: =SUM(CW46:EA46) -> 0 | EC46: =SUM(LARM:RM!EC46) -> 0 | ED46: =SUM(LARM:RM!ED46) -> 0 | EE46: =SUM(LARM:RM!EE46) -> 0 | EF46: =SUM(LARM:RM!EF46) -> 0 | EG46: =SUM(LARM:RM!EG46) -> 0 | EH46: =SUM(LARM:RM!EH46) -> 0 | EI46: =SUM(LARM:RM!EI46) -> 0 | EJ46: =SUM(LARM:RM!EJ46) -> 0 | ... FG46: =SUM(LARM:RM!FG46) -> 0 | FH46: =SUM(EC46:FG46) -> 0 | FI46: =SUM(LARM:RM!FI46) -> 0 | FJ46: =SUM(LARM:RM!FJ46) -> 0 | FK46: =SUM(LARM:RM!FK46) -> 0 | FL46: =SUM(LARM:RM!FL46) -> 0 | FM46: =SUM(LARM:RM!FM46) -> 0 | FN46: =SUM(LARM:RM!FN46) -> 0 | FO46: =SUM(LARM:RM!FO46) -> 0 | FP46: =SUM(LARM:RM!FP46) -> 0 | ... GM46: =SUM(LARM:RM!GM46) -> 0 | GN46: =SUM(FI46:GM46) -> 0 | GO46: =SUM(LARM:RM!GO46) -> 0 | GP46: =SUM(LARM:RM!GP46) -> 0 | GQ46: =SUM(LARM:RM!GQ46) -> 0 | GR46: =SUM(LARM:RM!GR46) -> 0 | GS46: =SUM(LARM:RM!GS46) -> 0 | GT46: =SUM(LARM:RM!GT46) -> 0 | GU46: =SUM(LARM:RM!GU46) -> 0 | GV46: =SUM(LARM:RM!GV46) -> 0 | ... HS46: =SUM(LARM:RM!HS46) -> 0 | HT46: =SUM(GO46:HS46) -> 0 | HU46: =SUM(LARM:RM!HU46) -> 0 | HV46: =SUM(LARM:RM!HV46) -> 0 | HW46: =SUM(LARM:RM!HW46) -> 0 | HX46: =SUM(LARM:RM!HX46) -> 0 | HY46: =SUM(LARM:RM!HY46) -> 0 | HZ46: =SUM(LARM:RM!HZ46) -> 0 | IA46: =SUM(LARM:RM!IA46) -> 0 | IB46: =SUM(LARM:RM!IB46) -> 0 | ... IY46: =SUM(LARM:RM!IY46) -> 0 | IZ46: =SUM(HU46:IY46) -> 0 | JA46: =SUM(LARM:RM!JA46) -> 0 | JB46: =SUM(LARM:RM!JB46) -> 0 | JC46: =SUM(LARM:RM!JC46) -> 0 | JD46: =SUM(LARM:RM!JD46) -> 0 | JE46: =SUM(LARM:RM!JE46) -> 0 | JF46: =SUM(LARM:RM!JF46) -> 0 | JG46: =SUM(LARM:RM!JG46) -> 0 | JH46: =SUM(LARM:RM!JH46) -> 0 | ... KE46: =SUM(LARM:RM!KE46) -> 0 | KF46: =SUM(JA46:KE46) -> 0 | KG46: =SUM(LARM:RM!KG46) -> 0 | KH46: =SUM(LARM:RM!KH46) -> 0 | KI46: =SUM(LARM:RM!KI46) -> 0 | KJ46: =SUM(LARM:RM!KJ46) -> 0 | KK46: =SUM(LARM:RM!KK46) -> 0 | KL46: =SUM(LARM:RM!KL46) -> 0 | KM46: =SUM(LARM:RM!KM46) -> 0 | KN46: =SUM(LARM:RM!KN46) -> 0 | ... LK46: =SUM(LARM:RM!LK46) -> 0 | LL46: =SUM(KG46:LK46) -> 0 | LM46: =SUM(LARM:RM!LM46) -> 0 | LN46: =SUM(LARM:RM!LN46) -> 0 | LO46: =SUM(LARM:RM!LO46) -> 0 | LP46: =SUM(LARM:RM!LP46) -> 0 | LQ46: =SUM(LARM:RM!LQ46) -> 0 | LR46: =SUM(LARM:RM!LR46) -> 0 | LS46: =SUM(LARM:RM!LS46) -> 0 | LT46: =SUM(LARM:RM!LT46) -> 0 | ... MQ46: =SUM(LARM:RM!MQ46) -> 0 | MR46: =SUM(LM46:MQ46) -> 0 | MS46: =SUM(LARM:RM!MS46) -> 0 | MT46: =SUM(LARM:RM!MT46) -> 0 | MU46: =SUM(LARM:RM!MU46) -> 0 | MV46: =SUM(LARM:RM!MV46) -> 0 | MW46: =SUM(LARM:RM!MW46) -> 0 | MX46: =SUM(LARM:RM!MX46) -> 0 | MY46: =SUM(LARM:RM!MY46) -> 0 | MZ46: =SUM(LARM:RM!MZ46) -> 0 | ... NW46: =SUM(LARM:RM!NW46) -> 0 | NX46: =SUM(MS46:NW46) -> 0 | NZ46: =AJ46+BP46+CV46+EB46+FH46+GN46+HT46+IZ46+KF46+LL46+MR46+NX46 -> 0 | OA46: =SUM(OI46:OP46) -> 0 | OB46: =IF(NZ46=0,"",(OA46/NZ46)-1) | OG46: OUTROS INVESTIMENTOS | OI46: =SUM(LARM:RM!OI46) -> 0 | OJ46: =SUM(LARM:RM!OJ46) -> 0 | OK46: =SUM(LARM:RM!OK46) -> 0 | OL46: =SUM(LARM:RM!OL46) -> 0 | OM46: =SUM(LARM:RM!OM46) -> 0 | ON46: =SUM(LARM:RM!ON46) -> 0 | OO46: =SUM(LARM:RM!OO46) -> 0 | OP46: =SUM(LARM:RM!OP46) -> 0 | ... OT46: =SUM(LARM:RM!OT46) -> 0 | OV46: =SUM(OI46:OT46) -> 0
B47: 8.1 | C47: ED. FCO. MELAO-CJ 23 | E47: =SUM(LARM:RM!E47) -> 0 | F47: =SUM(LARM:RM!F47) -> 0 | G47: =SUM(LARM:RM!G47) -> 0 | H47: =SUM(LARM:RM!H47) -> 0 | I47: =SUM(LARM:RM!I47) -> 0 | J47: =SUM(LARM:RM!J47) -> 0 | K47: =SUM(LARM:RM!K47) -> 0 | L47: =SUM(LARM:RM!L47) -> 0 | ... AI47: =SUM(LARM:RM!AI47) -> 0 | AJ47: =SUM(E47:AI47) -> 0 | AK47: =SUM(LARM:RM!AK47) -> 0 | AL47: =SUM(LARM:RM!AL47) -> 0 | AM47: =SUM(LARM:RM!AM47) -> 0 | AN47: =SUM(LARM:RM!AN47) -> 0 | AO47: =SUM(LARM:RM!AO47) -> 0 | AP47: =SUM(LARM:RM!AP47) -> 0 | AQ47: =SUM(LARM:RM!AQ47) -> 0 | AR47: =SUM(LARM:RM!AR47) -> 0 | ... BO47: =SUM(LARM:RM!BO47) -> 0 | BP47: =SUM(AK47:BO47) -> 0 | BQ47: =SUM(LARM:RM!BQ47) -> 0 | BR47: =SUM(LARM:RM!BR47) -> 0 | BS47: =SUM(LARM:RM!BS47) -> 0 | BT47: =SUM(LARM:RM!BT47) -> 0 | BU47: =SUM(LARM:RM!BU47) -> 0 | BV47: =SUM(LARM:RM!BV47) -> 0 | BW47: =SUM(LARM:RM!BW47) -> 0 | BX47: =SUM(LARM:RM!BX47) -> 0 | ... CU47: =SUM(LARM:RM!CU47) -> 0 | CV47: =SUM(BQ47:CU47) -> 0 | CW47: =SUM(LARM:RM!CW47) -> 0 | CX47: =SUM(LARM:RM!CX47) -> 0 | CY47: =SUM(LARM:RM!CY47) -> 0 | CZ47: =SUM(LARM:RM!CZ47) -> 0 | DA47: =SUM(LARM:RM!DA47) -> 0 | DB47: =SUM(LARM:RM!DB47) -> 0 | DC47: =SUM(LARM:RM!DC47) -> 0 | DD47: =SUM(LARM:RM!DD47) -> 0 | ... EA47: =SUM(LARM:RM!EA47) -> 0 | EB47: =SUM(CW47:EA47) -> 0 | EC47: =SUM(LARM:RM!EC47) -> 0 | ED47: =SUM(LARM:RM!ED47) -> 0 | EE47: =SUM(LARM:RM!EE47) -> 0 | EF47: =SUM(LARM:RM!EF47) -> 0 | EG47: =SUM(LARM:RM!EG47) -> 0 | EH47: =SUM(LARM:RM!EH47) -> 0 | EI47: =SUM(LARM:RM!EI47) -> 0 | EJ47: =SUM(LARM:RM!EJ47) -> 0 | ... FG47: =SUM(LARM:RM!FG47) -> 0 | FH47: =SUM(EC47:FG47) -> 0 | FI47: =SUM(LARM:RM!FI47) -> 0 | FJ47: =SUM(LARM:RM!FJ47) -> 0 | FK47: =SUM(LARM:RM!FK47) -> 0 | FL47: =SUM(LARM:RM!FL47) -> 0 | FM47: =SUM(LARM:RM!FM47) -> 0 | FN47: =SUM(LARM:RM!FN47) -> 0 | FO47: =SUM(LARM:RM!FO47) -> 0 | FP47: =SUM(LARM:RM!FP47) -> 0 | ... GM47: =SUM(LARM:RM!GM47) -> 0 | GN47: =SUM(FI47:GM47) -> 0 | GO47: =SUM(LARM:RM!GO47) -> 0 | GP47: =SUM(LARM:RM!GP47) -> 0 | GQ47: =SUM(LARM:RM!GQ47) -> 0 | GR47: =SUM(LARM:RM!GR47) -> 0 | GS47: =SUM(LARM:RM!GS47) -> 0 | GT47: =SUM(LARM:RM!GT47) -> 0 | GU47: =SUM(LARM:RM!GU47) -> 0 | GV47: =SUM(LARM:RM!GV47) -> 0 | ... HS47: =SUM(LARM:RM!HS47) -> 0 | HT47: =SUM(GO47:HS47) -> 0 | HU47: =SUM(LARM:RM!HU47) -> 0 | HV47: =SUM(LARM:RM!HV47) -> 0 | HW47: =SUM(LARM:RM!HW47) -> 0 | HX47: =SUM(LARM:RM!HX47) -> 0 | HY47: =SUM(LARM:RM!HY47) -> 0 | HZ47: =SUM(LARM:RM!HZ47) -> 0 | IA47: =SUM(LARM:RM!IA47) -> 0 | IB47: =SUM(LARM:RM!IB47) -> 0 | ... IY47: =SUM(LARM:RM!IY47) -> 0 | IZ47: =SUM(HU47:IY47) -> 0 | JA47: =SUM(LARM:RM!JA47) -> 0 | JB47: =SUM(LARM:RM!JB47) -> 0 | JC47: =SUM(LARM:RM!JC47) -> 0 | JD47: =SUM(LARM:RM!JD47) -> 0 | JE47: =SUM(LARM:RM!JE47) -> 0 | JF47: =SUM(LARM:RM!JF47) -> 0 | JG47: =SUM(LARM:RM!JG47) -> 0 | JH47: =SUM(LARM:RM!JH47) -> 0 | ... KE47: =SUM(LARM:RM!KE47) -> 0 | KF47: =SUM(JA47:KE47) -> 0 | KG47: =SUM(LARM:RM!KG47) -> 0 | KH47: =SUM(LARM:RM!KH47) -> 0 | KI47: =SUM(LARM:RM!KI47) -> 0 | KJ47: =SUM(LARM:RM!KJ47) -> 0 | KK47: =SUM(LARM:RM!KK47) -> 0 | KL47: =SUM(LARM:RM!KL47) -> 0 | KM47: =SUM(LARM:RM!KM47) -> 0 | KN47: =SUM(LARM:RM!KN47) -> 0 | ... LK47: =SUM(LARM:RM!LK47) -> 0 | LL47: =SUM(KG47:LK47) -> 0 | LM47: =SUM(LARM:RM!LM47) -> 0 | LN47: =SUM(LARM:RM!LN47) -> 0 | LO47: =SUM(LARM:RM!LO47) -> 0 | LP47: =SUM(LARM:RM!LP47) -> 0 | LQ47: =SUM(LARM:RM!LQ47) -> 0 | LR47: =SUM(LARM:RM!LR47) -> 0 | LS47: =SUM(LARM:RM!LS47) -> 0 | LT47: =SUM(LARM:RM!LT47) -> 0 | ... MQ47: =SUM(LARM:RM!MQ47) -> 0 | MR47: =SUM(LM47:MQ47) -> 0 | MS47: =SUM(LARM:RM!MS47) -> 0 | MT47: =SUM(LARM:RM!MT47) -> 0 | MU47: =SUM(LARM:RM!MU47) -> 0 | MV47: =SUM(LARM:RM!MV47) -> 0 | MW47: =SUM(LARM:RM!MW47) -> 0 | MX47: =SUM(LARM:RM!MX47) -> 0 | MY47: =SUM(LARM:RM!MY47) -> 0 | MZ47: =SUM(LARM:RM!MZ47) -> 0 | ... NW47: =SUM(LARM:RM!NW47) -> 0 | NX47: =SUM(MS47:NW47) -> 0 | NZ47: =AJ47+BP47+CV47+EB47+FH47+GN47+HT47+IZ47+KF47+LL47+MR47+NX47 -> 0 | OA47: =SUM(OI47:OP47) -> 0 | OB47: =IF(NZ47=0,"",(OA47/NZ47)-1) | OG47: ED. FCO. MELAO-CJ 23 | OI47: =SUM(LARM:RM!OI47) -> 0 | OJ47: =SUM(LARM:RM!OJ47) -> 0 | OK47: =SUM(LARM:RM!OK47) -> 0 | OL47: =SUM(LARM:RM!OL47) -> 0 | OM47: =SUM(LARM:RM!OM47) -> 0 | ON47: =SUM(LARM:RM!ON47) -> 0 | OO47: =SUM(LARM:RM!OO47) -> 0 | OP47: =SUM(LARM:RM!OP47) -> 0 | ... OT47: =SUM(LARM:RM!OT47) -> 0 | OV47: =SUM(OI47:OT47) -> 0
B48: 8.2 | C48: ED. VENDOME-AP 131 | E48: =SUM(LARM:RM!E48) -> 0 | F48: =SUM(LARM:RM!F48) -> 0 | G48: =SUM(LARM:RM!G48) -> 0 | H48: =SUM(LARM:RM!H48) -> 0 | I48: =SUM(LARM:RM!I48) -> 0 | J48: =SUM(LARM:RM!J48) -> 0 | K48: =SUM(LARM:RM!K48) -> 0 | L48: =SUM(LARM:RM!L48) -> 0 | ... AI48: =SUM(LARM:RM!AI48) -> 0 | AJ48: =SUM(E48:AI48) -> 0 | AK48: =SUM(LARM:RM!AK48) -> 0 | AL48: =SUM(LARM:RM!AL48) -> 0 | AM48: =SUM(LARM:RM!AM48) -> 0 | AN48: =SUM(LARM:RM!AN48) -> 0 | AO48: =SUM(LARM:RM!AO48) -> 0 | AP48: =SUM(LARM:RM!AP48) -> 0 | AQ48: =SUM(LARM:RM!AQ48) -> 0 | AR48: =SUM(LARM:RM!AR48) -> 0 | ... BO48: =SUM(LARM:RM!BO48) -> 0 | BP48: =SUM(AK48:BO48) -> 0 | BQ48: =SUM(LARM:RM!BQ48) -> 0 | BR48: =SUM(LARM:RM!BR48) -> 0 | BS48: =SUM(LARM:RM!BS48) -> 0 | BT48: =SUM(LARM:RM!BT48) -> 0 | BU48: =SUM(LARM:RM!BU48) -> 0 | BV48: =SUM(LARM:RM!BV48) -> 0 | BW48: =SUM(LARM:RM!BW48) -> 0 | BX48: =SUM(LARM:RM!BX48) -> 0 | ... CU48: =SUM(LARM:RM!CU48) -> 0 | CV48: =SUM(BQ48:CU48) -> 0 | CW48: =SUM(LARM:RM!CW48) -> 0 | CX48: =SUM(LARM:RM!CX48) -> 0 | CY48: =SUM(LARM:RM!CY48) -> 0 | CZ48: =SUM(LARM:RM!CZ48) -> 0 | DA48: =SUM(LARM:RM!DA48) -> 0 | DB48: =SUM(LARM:RM!DB48) -> 0 | DC48: =SUM(LARM:RM!DC48) -> 0 | DD48: =SUM(LARM:RM!DD48) -> 0 | ... EA48: =SUM(LARM:RM!EA48) -> 0 | EB48: =SUM(CW48:EA48) -> 0 | EC48: =SUM(LARM:RM!EC48) -> 0 | ED48: =SUM(LARM:RM!ED48) -> 0 | EE48: =SUM(LARM:RM!EE48) -> 0 | EF48: =SUM(LARM:RM!EF48) -> 0 | EG48: =SUM(LARM:RM!EG48) -> 0 | EH48: =SUM(LARM:RM!EH48) -> 0 | EI48: =SUM(LARM:RM!EI48) -> 0 | EJ48: =SUM(LARM:RM!EJ48) -> 0 | ... FG48: =SUM(LARM:RM!FG48) -> 0 | FH48: =SUM(EC48:FG48) -> 0 | FI48: =SUM(LARM:RM!FI48) -> 0 | FJ48: =SUM(LARM:RM!FJ48) -> 0 | FK48: =SUM(LARM:RM!FK48) -> 0 | FL48: =SUM(LARM:RM!FL48) -> 0 | FM48: =SUM(LARM:RM!FM48) -> 0 | FN48: =SUM(LARM:RM!FN48) -> 0 | FO48: =SUM(LARM:RM!FO48) -> 0 | FP48: =SUM(LARM:RM!FP48) -> 0 | ... GM48: =SUM(LARM:RM!GM48) -> 0 | GN48: =SUM(FI48:GM48) -> 0 | GO48: =SUM(LARM:RM!GO48) -> 0 | GP48: =SUM(LARM:RM!GP48) -> 0 | GQ48: =SUM(LARM:RM!GQ48) -> 0 | GR48: =SUM(LARM:RM!GR48) -> 0 | GS48: =SUM(LARM:RM!GS48) -> 0 | GT48: =SUM(LARM:RM!GT48) -> 0 | GU48: =SUM(LARM:RM!GU48) -> 0 | GV48: =SUM(LARM:RM!GV48) -> 0 | ... HS48: =SUM(LARM:RM!HS48) -> 0 | HT48: =SUM(GO48:HS48) -> 0 | HU48: =SUM(LARM:RM!HU48) -> 0 | HV48: =SUM(LARM:RM!HV48) -> 0 | HW48: =SUM(LARM:RM!HW48) -> 0 | HX48: =SUM(LARM:RM!HX48) -> 0 | HY48: =SUM(LARM:RM!HY48) -> 0 | HZ48: =SUM(LARM:RM!HZ48) -> 0 | IA48: =SUM(LARM:RM!IA48) -> 0 | IB48: =SUM(LARM:RM!IB48) -> 0 | ... IY48: =SUM(LARM:RM!IY48) -> 0 | IZ48: =SUM(HU48:IY48) -> 0 | JA48: =SUM(LARM:RM!JA48) -> 0 | JB48: =SUM(LARM:RM!JB48) -> 0 | JC48: =SUM(LARM:RM!JC48) -> 0 | JD48: =SUM(LARM:RM!JD48) -> 0 | JE48: =SUM(LARM:RM!JE48) -> 0 | JF48: =SUM(LARM:RM!JF48) -> 0 | JG48: =SUM(LARM:RM!JG48) -> 0 | JH48: =SUM(LARM:RM!JH48) -> 0 | ... KE48: =SUM(LARM:RM!KE48) -> 0 | KF48: =SUM(JA48:KE48) -> 0 | KG48: =SUM(LARM:RM!KG48) -> 0 | KH48: =SUM(LARM:RM!KH48) -> 0 | KI48: =SUM(LARM:RM!KI48) -> 0 | KJ48: =SUM(LARM:RM!KJ48) -> 0 | KK48: =SUM(LARM:RM!KK48) -> 0 | KL48: =SUM(LARM:RM!KL48) -> 0 | KM48: =SUM(LARM:RM!KM48) -> 0 | KN48: =SUM(LARM:RM!KN48) -> 0 | ... LK48: =SUM(LARM:RM!LK48) -> 0 | LL48: =SUM(KG48:LK48) -> 0 | LM48: =SUM(LARM:RM!LM48) -> 0 | LN48: =SUM(LARM:RM!LN48) -> 0 | LO48: =SUM(LARM:RM!LO48) -> 0 | LP48: =SUM(LARM:RM!LP48) -> 0 | LQ48: =SUM(LARM:RM!LQ48) -> 0 | LR48: =SUM(LARM:RM!LR48) -> 0 | LS48: =SUM(LARM:RM!LS48) -> 0 | LT48: =SUM(LARM:RM!LT48) -> 0 | ... MQ48: =SUM(LARM:RM!MQ48) -> 0 | MR48: =SUM(LM48:MQ48) -> 0 | MS48: =SUM(LARM:RM!MS48) -> 0 | MT48: =SUM(LARM:RM!MT48) -> 0 | MU48: =SUM(LARM:RM!MU48) -> 0 | MV48: =SUM(LARM:RM!MV48) -> 0 | MW48: =SUM(LARM:RM!MW48) -> 0 | MX48: =SUM(LARM:RM!MX48) -> 0 | MY48: =SUM(LARM:RM!MY48) -> 0 | MZ48: =SUM(LARM:RM!MZ48) -> 0 | ... NW48: =SUM(LARM:RM!NW48) -> 0 | NX48: =SUM(MS48:NW48) -> 0 | NZ48: =AJ48+BP48+CV48+EB48+FH48+GN48+HT48+IZ48+KF48+LL48+MR48+NX48 -> 0 | OA48: =SUM(OI48:OP48) -> 0 | OB48: =IF(NZ48=0,"",(OA48/NZ48)-1) | OG48: ED. VENDOME-AP 131 | OI48: =SUM(LARM:RM!OI48) -> 0 | OJ48: =SUM(LARM:RM!OJ48) -> 0 | OK48: =SUM(LARM:RM!OK48) -> 0 | OL48: =SUM(LARM:RM!OL48) -> 0 | OM48: =SUM(LARM:RM!OM48) -> 0 | ON48: =SUM(LARM:RM!ON48) -> 0 | OO48: =SUM(LARM:RM!OO48) -> 0 | OP48: =SUM(LARM:RM!OP48) -> 0 | ... OT48: =SUM(LARM:RM!OT48) -> 0 | OV48: =SUM(OI48:OT48) -> 0
B49: 8.3 | C49: FAZENDA-SÃO MANOEL | E49: =SUM(LARM:RM!E49) -> 0 | F49: =SUM(LARM:RM!F49) -> 0 | G49: =SUM(LARM:RM!G49) -> 0 | H49: =SUM(LARM:RM!H49) -> 0 | I49: =SUM(LARM:RM!I49) -> 0 | J49: =SUM(LARM:RM!J49) -> 0 | K49: =SUM(LARM:RM!K49) -> 0 | L49: =SUM(LARM:RM!L49) -> 0 | ... AI49: =SUM(LARM:RM!AI49) -> 0 | AJ49: =SUM(E49:AI49) -> 0 | AK49: =SUM(LARM:RM!AK49) -> 0 | AL49: =SUM(LARM:RM!AL49) -> 0 | AM49: =SUM(LARM:RM!AM49) -> 0 | AN49: =SUM(LARM:RM!AN49) -> 0 | AO49: =SUM(LARM:RM!AO49) -> 0 | AP49: =SUM(LARM:RM!AP49) -> 0 | AQ49: =SUM(LARM:RM!AQ49) -> 0 | AR49: =SUM(LARM:RM!AR49) -> 0 | ... BO49: =SUM(LARM:RM!BO49) -> 0 | BP49: =SUM(AK49:BO49) -> 0 | BQ49: =SUM(LARM:RM!BQ49) -> 0 | BR49: =SUM(LARM:RM!BR49) -> 0 | BS49: =SUM(LARM:RM!BS49) -> 0 | BT49: =SUM(LARM:RM!BT49) -> 0 | BU49: =SUM(LARM:RM!BU49) -> 0 | BV49: =SUM(LARM:RM!BV49) -> 0 | BW49: =SUM(LARM:RM!BW49) -> 0 | BX49: =SUM(LARM:RM!BX49) -> 0 | ... CU49: =SUM(LARM:RM!CU49) -> 0 | CV49: =SUM(BQ49:CU49) -> 0 | CW49: =SUM(LARM:RM!CW49) -> 0 | CX49: =SUM(LARM:RM!CX49) -> 0 | CY49: =SUM(LARM:RM!CY49) -> 0 | CZ49: =SUM(LARM:RM!CZ49) -> 0 | DA49: =SUM(LARM:RM!DA49) -> 0 | DB49: =SUM(LARM:RM!DB49) -> 0 | DC49: =SUM(LARM:RM!DC49) -> 0 | DD49: =SUM(LARM:RM!DD49) -> 0 | ... EA49: =SUM(LARM:RM!EA49) -> 0 | EB49: =SUM(CW49:EA49) -> 0 | EC49: =SUM(LARM:RM!EC49) -> 0 | ED49: =SUM(LARM:RM!ED49) -> 0 | EE49: =SUM(LARM:RM!EE49) -> 0 | EF49: =SUM(LARM:RM!EF49) -> 0 | EG49: =SUM(LARM:RM!EG49) -> 0 | EH49: =SUM(LARM:RM!EH49) -> 0 | EI49: =SUM(LARM:RM!EI49) -> 0 | EJ49: =SUM(LARM:RM!EJ49) -> 0 | ... FG49: =SUM(LARM:RM!FG49) -> 0 | FH49: =SUM(EC49:FG49) -> 0 | FI49: =SUM(LARM:RM!FI49) -> 0 | FJ49: =SUM(LARM:RM!FJ49) -> 0 | FK49: =SUM(LARM:RM!FK49) -> 0 | FL49: =SUM(LARM:RM!FL49) -> 0 | FM49: =SUM(LARM:RM!FM49) -> 0 | FN49: =SUM(LARM:RM!FN49) -> 0 | FO49: =SUM(LARM:RM!FO49) -> 0 | FP49: =SUM(LARM:RM!FP49) -> 0 | ... GM49: =SUM(LARM:RM!GM49) -> 0 | GN49: =SUM(FI49:GM49) -> 0 | GO49: =SUM(LARM:RM!GO49) -> 0 | GP49: =SUM(LARM:RM!GP49) -> 0 | GQ49: =SUM(LARM:RM!GQ49) -> 0 | GR49: =SUM(LARM:RM!GR49) -> 0 | GS49: =SUM(LARM:RM!GS49) -> 0 | GT49: =SUM(LARM:RM!GT49) -> 0 | GU49: =SUM(LARM:RM!GU49) -> 0 | GV49: =SUM(LARM:RM!GV49) -> 0 | ... HS49: =SUM(LARM:RM!HS49) -> 0 | HT49: =SUM(GO49:HS49) -> 0 | HU49: =SUM(LARM:RM!HU49) -> 0 | HV49: =SUM(LARM:RM!HV49) -> 0 | HW49: =SUM(LARM:RM!HW49) -> 0 | HX49: =SUM(LARM:RM!HX49) -> 0 | HY49: =SUM(LARM:RM!HY49) -> 0 | HZ49: =SUM(LARM:RM!HZ49) -> 0 | IA49: =SUM(LARM:RM!IA49) -> 0 | IB49: =SUM(LARM:RM!IB49) -> 0 | ... IY49: =SUM(LARM:RM!IY49) -> 0 | IZ49: =SUM(HU49:IY49) -> 0 | JA49: =SUM(LARM:RM!JA49) -> 0 | JB49: =SUM(LARM:RM!JB49) -> 0 | JC49: =SUM(LARM:RM!JC49) -> 0 | JD49: =SUM(LARM:RM!JD49) -> 0 | JE49: =SUM(LARM:RM!JE49) -> 0 | JF49: =SUM(LARM:RM!JF49) -> 0 | JG49: =SUM(LARM:RM!JG49) -> 0 | JH49: =SUM(LARM:RM!JH49) -> 0 | ... KE49: =SUM(LARM:RM!KE49) -> 0 | KF49: =SUM(JA49:KE49) -> 0 | KG49: =SUM(LARM:RM!KG49) -> 0 | KH49: =SUM(LARM:RM!KH49) -> 0 | KI49: =SUM(LARM:RM!KI49) -> 0 | KJ49: =SUM(LARM:RM!KJ49) -> 0 | KK49: =SUM(LARM:RM!KK49) -> 0 | KL49: =SUM(LARM:RM!KL49) -> 0 | KM49: =SUM(LARM:RM!KM49) -> 0 | KN49: =SUM(LARM:RM!KN49) -> 0 | ... LK49: =SUM(LARM:RM!LK49) -> 0 | LL49: =SUM(KG49:LK49) -> 0 | LM49: =SUM(LARM:RM!LM49) -> 0 | LN49: =SUM(LARM:RM!LN49) -> 0 | LO49: =SUM(LARM:RM!LO49) -> 0 | LP49: =SUM(LARM:RM!LP49) -> 0 | LQ49: =SUM(LARM:RM!LQ49) -> 0 | LR49: =SUM(LARM:RM!LR49) -> 0 | LS49: =SUM(LARM:RM!LS49) -> 0 | LT49: =SUM(LARM:RM!LT49) -> 0 | ... MQ49: =SUM(LARM:RM!MQ49) -> 0 | MR49: =SUM(LM49:MQ49) -> 0 | MS49: =SUM(LARM:RM!MS49) -> 0 | MT49: =SUM(LARM:RM!MT49) -> 0 | MU49: =SUM(LARM:RM!MU49) -> 0 | MV49: =SUM(LARM:RM!MV49) -> 0 | MW49: =SUM(LARM:RM!MW49) -> 0 | MX49: =SUM(LARM:RM!MX49) -> 0 | MY49: =SUM(LARM:RM!MY49) -> 0 | MZ49: =SUM(LARM:RM!MZ49) -> 0 | ... NW49: =SUM(LARM:RM!NW49) -> 0 | NX49: =SUM(MS49:NW49) -> 0 | NZ49: =AJ49+BP49+CV49+EB49+FH49+GN49+HT49+IZ49+KF49+LL49+MR49+NX49 -> 0 | OA49: =SUM(OI49:OP49) -> 0 | OB49: =IF(NZ49=0,"",(OA49/NZ49)-1) | OG49: FAZENDA-SÃO MANOEL | OI49: =SUM(LARM:RM!OI49) -> 0 | OJ49: =SUM(LARM:RM!OJ49) -> 0 | OK49: =SUM(LARM:RM!OK49) -> 0 | OL49: =SUM(LARM:RM!OL49) -> 0 | OM49: =SUM(LARM:RM!OM49) -> 0 | ON49: =SUM(LARM:RM!ON49) -> 0 | OO49: =SUM(LARM:RM!OO49) -> 0 | OP49: =SUM(LARM:RM!OP49) -> 0 | ... OT49: =SUM(LARM:RM!OT49) -> 0 | OV49: =SUM(OI49:OT49) -> 0
B50: 8.4 | C50: LOTEAMENTO-RES. SANTA CLARA | E50: =SUM(LARM:RM!E50) -> 0 | F50: =SUM(LARM:RM!F50) -> 0 | G50: =SUM(LARM:RM!G50) -> 0 | H50: =SUM(LARM:RM!H50) -> 0 | I50: =SUM(LARM:RM!I50) -> 0 | J50: =SUM(LARM:RM!J50) -> 0 | K50: =SUM(LARM:RM!K50) -> 0 | L50: =SUM(LARM:RM!L50) -> 0 | ... AI50: =SUM(LARM:RM!AI50) -> 0 | AJ50: =SUM(E50:AI50) -> 0 | AK50: =SUM(LARM:RM!AK50) -> 0 | AL50: =SUM(LARM:RM!AL50) -> 0 | AM50: =SUM(LARM:RM!AM50) -> 0 | AN50: =SUM(LARM:RM!AN50) -> 0 | AO50: =SUM(LARM:RM!AO50) -> 0 | AP50: =SUM(LARM:RM!AP50) -> 0 | AQ50: =SUM(LARM:RM!AQ50) -> 0 | AR50: =SUM(LARM:RM!AR50) -> 0 | ... BO50: =SUM(LARM:RM!BO50) -> 0 | BP50: =SUM(AK50:BO50) -> 0 | BQ50: =SUM(LARM:RM!BQ50) -> 0 | BR50: =SUM(LARM:RM!BR50) -> 0 | BS50: =SUM(LARM:RM!BS50) -> 0 | BT50: =SUM(LARM:RM!BT50) -> 0 | BU50: =SUM(LARM:RM!BU50) -> 0 | BV50: =SUM(LARM:RM!BV50) -> 0 | BW50: =SUM(LARM:RM!BW50) -> 0 | BX50: =SUM(LARM:RM!BX50) -> 0 | ... CU50: =SUM(LARM:RM!CU50) -> 0 | CV50: =SUM(BQ50:CU50) -> 0 | CW50: =SUM(LARM:RM!CW50) -> 0 | CX50: =SUM(LARM:RM!CX50) -> 0 | CY50: =SUM(LARM:RM!CY50) -> 0 | CZ50: =SUM(LARM:RM!CZ50) -> 0 | DA50: =SUM(LARM:RM!DA50) -> 0 | DB50: =SUM(LARM:RM!DB50) -> 0 | DC50: =SUM(LARM:RM!DC50) -> 0 | DD50: =SUM(LARM:RM!DD50) -> 0 | ... EA50: =SUM(LARM:RM!EA50) -> 0 | EB50: =SUM(CW50:EA50) -> 0 | EC50: =SUM(LARM:RM!EC50) -> 0 | ED50: =SUM(LARM:RM!ED50) -> 0 | EE50: =SUM(LARM:RM!EE50) -> 0 | EF50: =SUM(LARM:RM!EF50) -> 0 | EG50: =SUM(LARM:RM!EG50) -> 0 | EH50: =SUM(LARM:RM!EH50) -> 0 | EI50: =SUM(LARM:RM!EI50) -> 0 | EJ50: =SUM(LARM:RM!EJ50) -> 0 | ... FG50: =SUM(LARM:RM!FG50) -> 0 | FH50: =SUM(EC50:FG50) -> 0 | FI50: =SUM(LARM:RM!FI50) -> 0 | FJ50: =SUM(LARM:RM!FJ50) -> 0 | FK50: =SUM(LARM:RM!FK50) -> 0 | FL50: =SUM(LARM:RM!FL50) -> 0 | FM50: =SUM(LARM:RM!FM50) -> 0 | FN50: =SUM(LARM:RM!FN50) -> 0 | FO50: =SUM(LARM:RM!FO50) -> 0 | FP50: =SUM(LARM:RM!FP50) -> 0 | ... GM50: =SUM(LARM:RM!GM50) -> 0 | GN50: =SUM(FI50:GM50) -> 0 | GO50: =SUM(LARM:RM!GO50) -> 0 | GP50: =SUM(LARM:RM!GP50) -> 0 | GQ50: =SUM(LARM:RM!GQ50) -> 0 | GR50: =SUM(LARM:RM!GR50) -> 0 | GS50: =SUM(LARM:RM!GS50) -> 0 | GT50: =SUM(LARM:RM!GT50) -> 0 | GU50: =SUM(LARM:RM!GU50) -> 0 | GV50: =SUM(LARM:RM!GV50) -> 0 | ... HS50: =SUM(LARM:RM!HS50) -> 0 | HT50: =SUM(GO50:HS50) -> 0 | HU50: =SUM(LARM:RM!HU50) -> 0 | HV50: =SUM(LARM:RM!HV50) -> 0 | HW50: =SUM(LARM:RM!HW50) -> 0 | HX50: =SUM(LARM:RM!HX50) -> 0 | HY50: =SUM(LARM:RM!HY50) -> 0 | HZ50: =SUM(LARM:RM!HZ50) -> 0 | IA50: =SUM(LARM:RM!IA50) -> 0 | IB50: =SUM(LARM:RM!IB50) -> 0 | ... IY50: =SUM(LARM:RM!IY50) -> 0 | IZ50: =SUM(HU50:IY50) -> 0 | JA50: =SUM(LARM:RM!JA50) -> 0 | JB50: =SUM(LARM:RM!JB50) -> 0 | JC50: =SUM(LARM:RM!JC50) -> 0 | JD50: =SUM(LARM:RM!JD50) -> 0 | JE50: =SUM(LARM:RM!JE50) -> 0 | JF50: =SUM(LARM:RM!JF50) -> 0 | JG50: =SUM(LARM:RM!JG50) -> 0 | JH50: =SUM(LARM:RM!JH50) -> 0 | ... KE50: =SUM(LARM:RM!KE50) -> 0 | KF50: =SUM(JA50:KE50) -> 0 | KG50: =SUM(LARM:RM!KG50) -> 0 | KH50: =SUM(LARM:RM!KH50) -> 0 | KI50: =SUM(LARM:RM!KI50) -> 0 | KJ50: =SUM(LARM:RM!KJ50) -> 0 | KK50: =SUM(LARM:RM!KK50) -> 0 | KL50: =SUM(LARM:RM!KL50) -> 0 | KM50: =SUM(LARM:RM!KM50) -> 0 | KN50: =SUM(LARM:RM!KN50) -> 0 | ... LK50: =SUM(LARM:RM!LK50) -> 0 | LL50: =SUM(KG50:LK50) -> 0 | LM50: =SUM(LARM:RM!LM50) -> 0 | LN50: =SUM(LARM:RM!LN50) -> 0 | LO50: =SUM(LARM:RM!LO50) -> 0 | LP50: =SUM(LARM:RM!LP50) -> 0 | LQ50: =SUM(LARM:RM!LQ50) -> 0 | LR50: =SUM(LARM:RM!LR50) -> 0 | LS50: =SUM(LARM:RM!LS50) -> 0 | LT50: =SUM(LARM:RM!LT50) -> 0 | ... MQ50: =SUM(LARM:RM!MQ50) -> 0 | MR50: =SUM(LM50:MQ50) -> 0 | MS50: =SUM(LARM:RM!MS50) -> 0 | MT50: =SUM(LARM:RM!MT50) -> 0 | MU50: =SUM(LARM:RM!MU50) -> 0 | MV50: =SUM(LARM:RM!MV50) -> 0 | MW50: =SUM(LARM:RM!MW50) -> 0 | MX50: =SUM(LARM:RM!MX50) -> 0 | MY50: =SUM(LARM:RM!MY50) -> 0 | MZ50: =SUM(LARM:RM!MZ50) -> 0 | ... NW50: =SUM(LARM:RM!NW50) -> 0 | NX50: =SUM(MS50:NW50) -> 0 | NZ50: =AJ50+BP50+CV50+EB50+FH50+GN50+HT50+IZ50+KF50+LL50+MR50+NX50 -> 0 | OA50: =SUM(OI50:OP50) -> 0 | OB50: =IF(NZ50=0,"",(OA50/NZ50)-1) | OG50: LOTEAMENTO-RES. SANTA CLARA | OI50: =SUM(LARM:RM!OI50) -> 0 | OJ50: =SUM(LARM:RM!OJ50) -> 0 | OK50: =SUM(LARM:RM!OK50) -> 0 | OL50: =SUM(LARM:RM!OL50) -> 0 | OM50: =SUM(LARM:RM!OM50) -> 0 | ON50: =SUM(LARM:RM!ON50) -> 0 | OO50: =SUM(LARM:RM!OO50) -> 0 | OP50: =SUM(LARM:RM!OP50) -> 0 | ... OT50: =SUM(LARM:RM!OT50) -> 0 | OV50: =SUM(OI50:OT50) -> 0
B51: 8.5 | C51: LOTEAMENTO-RES. SANTA CLARA QY | E51: =SUM(LARM:RM!E51) -> 0 | F51: =SUM(LARM:RM!F51) -> 0 | G51: =SUM(LARM:RM!G51) -> 0 | H51: =SUM(LARM:RM!H51) -> 0 | I51: =SUM(LARM:RM!I51) -> 0 | J51: =SUM(LARM:RM!J51) -> 0 | K51: =SUM(LARM:RM!K51) -> 0 | L51: =SUM(LARM:RM!L51) -> 0 | ... AI51: =SUM(LARM:RM!AI51) -> 0 | AJ51: =SUM(E51:AI51) -> 0 | AK51: =SUM(LARM:RM!AK51) -> 0 | AL51: =SUM(LARM:RM!AL51) -> 0 | AM51: =SUM(LARM:RM!AM51) -> 0 | AN51: =SUM(LARM:RM!AN51) -> 0 | AO51: =SUM(LARM:RM!AO51) -> 0 | AP51: =SUM(LARM:RM!AP51) -> 0 | AQ51: =SUM(LARM:RM!AQ51) -> 0 | AR51: =SUM(LARM:RM!AR51) -> 0 | ... BO51: =SUM(LARM:RM!BO51) -> 0 | BP51: =SUM(AK51:BO51) -> 0 | BQ51: =SUM(LARM:RM!BQ51) -> 0 | BR51: =SUM(LARM:RM!BR51) -> 0 | BS51: =SUM(LARM:RM!BS51) -> 0 | BT51: =SUM(LARM:RM!BT51) -> 0 | BU51: =SUM(LARM:RM!BU51) -> 0 | BV51: =SUM(LARM:RM!BV51) -> 0 | BW51: =SUM(LARM:RM!BW51) -> 0 | BX51: =SUM(LARM:RM!BX51) -> 0 | ... CU51: =SUM(LARM:RM!CU51) -> 0 | CV51: =SUM(BQ51:CU51) -> 0 | CW51: =SUM(LARM:RM!CW51) -> 0 | CX51: =SUM(LARM:RM!CX51) -> 0 | CY51: =SUM(LARM:RM!CY51) -> 0 | CZ51: =SUM(LARM:RM!CZ51) -> 0 | DA51: =SUM(LARM:RM!DA51) -> 0 | DB51: =SUM(LARM:RM!DB51) -> 0 | DC51: =SUM(LARM:RM!DC51) -> 0 | DD51: =SUM(LARM:RM!DD51) -> 0 | ... EA51: =SUM(LARM:RM!EA51) -> 0 | EB51: =SUM(CW51:EA51) -> 0 | EC51: =SUM(LARM:RM!EC51) -> 0 | ED51: =SUM(LARM:RM!ED51) -> 0 | EE51: =SUM(LARM:RM!EE51) -> 0 | EF51: =SUM(LARM:RM!EF51) -> 0 | EG51: =SUM(LARM:RM!EG51) -> 0 | EH51: =SUM(LARM:RM!EH51) -> 0 | EI51: =SUM(LARM:RM!EI51) -> 0 | EJ51: =SUM(LARM:RM!EJ51) -> 0 | ... FG51: =SUM(LARM:RM!FG51) -> 0 | FH51: =SUM(EC51:FG51) -> 0 | FI51: =SUM(LARM:RM!FI51) -> 0 | FJ51: =SUM(LARM:RM!FJ51) -> 0 | FK51: =SUM(LARM:RM!FK51) -> 0 | FL51: =SUM(LARM:RM!FL51) -> 0 | FM51: =SUM(LARM:RM!FM51) -> 0 | FN51: =SUM(LARM:RM!FN51) -> 0 | FO51: =SUM(LARM:RM!FO51) -> 0 | FP51: =SUM(LARM:RM!FP51) -> 0 | ... GM51: =SUM(LARM:RM!GM51) -> 0 | GN51: =SUM(FI51:GM51) -> 0 | GO51: =SUM(LARM:RM!GO51) -> 0 | GP51: =SUM(LARM:RM!GP51) -> 0 | GQ51: =SUM(LARM:RM!GQ51) -> 0 | GR51: =SUM(LARM:RM!GR51) -> 0 | GS51: =SUM(LARM:RM!GS51) -> 0 | GT51: =SUM(LARM:RM!GT51) -> 0 | GU51: =SUM(LARM:RM!GU51) -> 0 | GV51: =SUM(LARM:RM!GV51) -> 0 | ... HS51: =SUM(LARM:RM!HS51) -> 0 | HT51: =SUM(GO51:HS51) -> 0 | HU51: =SUM(LARM:RM!HU51) -> 0 | HV51: =SUM(LARM:RM!HV51) -> 0 | HW51: =SUM(LARM:RM!HW51) -> 0 | HX51: =SUM(LARM:RM!HX51) -> 0 | HY51: =SUM(LARM:RM!HY51) -> 0 | HZ51: =SUM(LARM:RM!HZ51) -> 0 | IA51: =SUM(LARM:RM!IA51) -> 0 | IB51: =SUM(LARM:RM!IB51) -> 0 | ... IY51: =SUM(LARM:RM!IY51) -> 0 | IZ51: =SUM(HU51:IY51) -> 0 | JA51: =SUM(LARM:RM!JA51) -> 0 | JB51: =SUM(LARM:RM!JB51) -> 0 | JC51: =SUM(LARM:RM!JC51) -> 0 | JD51: =SUM(LARM:RM!JD51) -> 0 | JE51: =SUM(LARM:RM!JE51) -> 0 | JF51: =SUM(LARM:RM!JF51) -> 0 | JG51: =SUM(LARM:RM!JG51) -> 0 | JH51: =SUM(LARM:RM!JH51) -> 0 | ... KE51: =SUM(LARM:RM!KE51) -> 0 | KF51: =SUM(JA51:KE51) -> 0 | KG51: =SUM(LARM:RM!KG51) -> 0 | KH51: =SUM(LARM:RM!KH51) -> 0 | KI51: =SUM(LARM:RM!KI51) -> 0 | KJ51: =SUM(LARM:RM!KJ51) -> 0 | KK51: =SUM(LARM:RM!KK51) -> 0 | KL51: =SUM(LARM:RM!KL51) -> 0 | KM51: =SUM(LARM:RM!KM51) -> 0 | KN51: =SUM(LARM:RM!KN51) -> 0 | ... LK51: =SUM(LARM:RM!LK51) -> 0 | LL51: =SUM(KG51:LK51) -> 0 | LM51: =SUM(LARM:RM!LM51) -> 0 | LN51: =SUM(LARM:RM!LN51) -> 0 | LO51: =SUM(LARM:RM!LO51) -> 0 | LP51: =SUM(LARM:RM!LP51) -> 0 | LQ51: =SUM(LARM:RM!LQ51) -> 0 | LR51: =SUM(LARM:RM!LR51) -> 0 | LS51: =SUM(LARM:RM!LS51) -> 0 | LT51: =SUM(LARM:RM!LT51) -> 0 | ... MQ51: =SUM(LARM:RM!MQ51) -> 0 | MR51: =SUM(LM51:MQ51) -> 0 | MS51: =SUM(LARM:RM!MS51) -> 0 | MT51: =SUM(LARM:RM!MT51) -> 0 | MU51: =SUM(LARM:RM!MU51) -> 0 | MV51: =SUM(LARM:RM!MV51) -> 0 | MW51: =SUM(LARM:RM!MW51) -> 0 | MX51: =SUM(LARM:RM!MX51) -> 0 | MY51: =SUM(LARM:RM!MY51) -> 0 | MZ51: =SUM(LARM:RM!MZ51) -> 0 | ... NW51: =SUM(LARM:RM!NW51) -> 0 | NX51: =SUM(MS51:NW51) -> 0 | NZ51: =AJ51+BP51+CV51+EB51+FH51+GN51+HT51+IZ51+KF51+LL51+MR51+NX51 -> 0 | OA51: =SUM(OI51:OP51) -> 0 | OB51: =IF(NZ51=0,"",(OA51/NZ51)-1) | OG51: LOTEAMENTO-RES. SANTA CLARA QY | OI51: =SUM(LARM:RM!OI51) -> 0 | OJ51: =SUM(LARM:RM!OJ51) -> 0 | OK51: =SUM(LARM:RM!OK51) -> 0 | OL51: =SUM(LARM:RM!OL51) -> 0 | OM51: =SUM(LARM:RM!OM51) -> 0 | ON51: =SUM(LARM:RM!ON51) -> 0 | OO51: =SUM(LARM:RM!OO51) -> 0 | OP51: =SUM(LARM:RM!OP51) -> 0 | ... OT51: =SUM(LARM:RM!OT51) -> 0 | OV51: =SUM(OI51:OT51) -> 0
B52: 8.6 | C52: LOTEAMENTO-RES. SANTA CLARA QZ | E52: =SUM(LARM:RM!E52) -> 0 | F52: =SUM(LARM:RM!F52) -> 0 | G52: =SUM(LARM:RM!G52) -> 0 | H52: =SUM(LARM:RM!H52) -> 0 | I52: =SUM(LARM:RM!I52) -> 0 | J52: =SUM(LARM:RM!J52) -> 0 | K52: =SUM(LARM:RM!K52) -> 0 | L52: =SUM(LARM:RM!L52) -> 0 | ... AI52: =SUM(LARM:RM!AI52) -> 0 | AJ52: =SUM(E52:AI52) -> 0 | AK52: =SUM(LARM:RM!AK52) -> 0 | AL52: =SUM(LARM:RM!AL52) -> 0 | AM52: =SUM(LARM:RM!AM52) -> 0 | AN52: =SUM(LARM:RM!AN52) -> 0 | AO52: =SUM(LARM:RM!AO52) -> 0 | AP52: =SUM(LARM:RM!AP52) -> 0 | AQ52: =SUM(LARM:RM!AQ52) -> 0 | AR52: =SUM(LARM:RM!AR52) -> 0 | ... BO52: =SUM(LARM:RM!BO52) -> 0 | BP52: =SUM(AK52:BO52) -> 0 | BQ52: =SUM(LARM:RM!BQ52) -> 0 | BR52: =SUM(LARM:RM!BR52) -> 0 | BS52: =SUM(LARM:RM!BS52) -> 0 | BT52: =SUM(LARM:RM!BT52) -> 0 | BU52: =SUM(LARM:RM!BU52) -> 0 | BV52: =SUM(LARM:RM!BV52) -> 0 | BW52: =SUM(LARM:RM!BW52) -> 0 | BX52: =SUM(LARM:RM!BX52) -> 0 | ... CU52: =SUM(LARM:RM!CU52) -> 0 | CV52: =SUM(BQ52:CU52) -> 0 | CW52: =SUM(LARM:RM!CW52) -> 0 | CX52: =SUM(LARM:RM!CX52) -> 0 | CY52: =SUM(LARM:RM!CY52) -> 0 | CZ52: =SUM(LARM:RM!CZ52) -> 0 | DA52: =SUM(LARM:RM!DA52) -> 0 | DB52: =SUM(LARM:RM!DB52) -> 0 | DC52: =SUM(LARM:RM!DC52) -> 0 | DD52: =SUM(LARM:RM!DD52) -> 0 | ... EA52: =SUM(LARM:RM!EA52) -> 0 | EB52: =SUM(CW52:EA52) -> 0 | EC52: =SUM(LARM:RM!EC52) -> 0 | ED52: =SUM(LARM:RM!ED52) -> 0 | EE52: =SUM(LARM:RM!EE52) -> 0 | EF52: =SUM(LARM:RM!EF52) -> 0 | EG52: =SUM(LARM:RM!EG52) -> 0 | EH52: =SUM(LARM:RM!EH52) -> 0 | EI52: =SUM(LARM:RM!EI52) -> 0 | EJ52: =SUM(LARM:RM!EJ52) -> 0 | ... FG52: =SUM(LARM:RM!FG52) -> 0 | FH52: =SUM(EC52:FG52) -> 0 | FI52: =SUM(LARM:RM!FI52) -> 0 | FJ52: =SUM(LARM:RM!FJ52) -> 0 | FK52: =SUM(LARM:RM!FK52) -> 0 | FL52: =SUM(LARM:RM!FL52) -> 0 | FM52: =SUM(LARM:RM!FM52) -> 0 | FN52: =SUM(LARM:RM!FN52) -> 0 | FO52: =SUM(LARM:RM!FO52) -> 0 | FP52: =SUM(LARM:RM!FP52) -> 0 | ... GM52: =SUM(LARM:RM!GM52) -> 0 | GN52: =SUM(FI52:GM52) -> 0 | GO52: =SUM(LARM:RM!GO52) -> 0 | GP52: =SUM(LARM:RM!GP52) -> 0 | GQ52: =SUM(LARM:RM!GQ52) -> 0 | GR52: =SUM(LARM:RM!GR52) -> 0 | GS52: =SUM(LARM:RM!GS52) -> 0 | GT52: =SUM(LARM:RM!GT52) -> 0 | GU52: =SUM(LARM:RM!GU52) -> 0 | GV52: =SUM(LARM:RM!GV52) -> 0 | ... HS52: =SUM(LARM:RM!HS52) -> 0 | HT52: =SUM(GO52:HS52) -> 0 | HU52: =SUM(LARM:RM!HU52) -> 0 | HV52: =SUM(LARM:RM!HV52) -> 0 | HW52: =SUM(LARM:RM!HW52) -> 0 | HX52: =SUM(LARM:RM!HX52) -> 0 | HY52: =SUM(LARM:RM!HY52) -> 0 | HZ52: =SUM(LARM:RM!HZ52) -> 0 | IA52: =SUM(LARM:RM!IA52) -> 0 | IB52: =SUM(LARM:RM!IB52) -> 0 | ... IY52: =SUM(LARM:RM!IY52) -> 0 | IZ52: =SUM(HU52:IY52) -> 0 | JA52: =SUM(LARM:RM!JA52) -> 0 | JB52: =SUM(LARM:RM!JB52) -> 0 | JC52: =SUM(LARM:RM!JC52) -> 0 | JD52: =SUM(LARM:RM!JD52) -> 0 | JE52: =SUM(LARM:RM!JE52) -> 0 | JF52: =SUM(LARM:RM!JF52) -> 0 | JG52: =SUM(LARM:RM!JG52) -> 0 | JH52: =SUM(LARM:RM!JH52) -> 0 | ... KE52: =SUM(LARM:RM!KE52) -> 0 | KF52: =SUM(JA52:KE52) -> 0 | KG52: =SUM(LARM:RM!KG52) -> 0 | KH52: =SUM(LARM:RM!KH52) -> 0 | KI52: =SUM(LARM:RM!KI52) -> 0 | KJ52: =SUM(LARM:RM!KJ52) -> 0 | KK52: =SUM(LARM:RM!KK52) -> 0 | KL52: =SUM(LARM:RM!KL52) -> 0 | KM52: =SUM(LARM:RM!KM52) -> 0 | KN52: =SUM(LARM:RM!KN52) -> 0 | ... LK52: =SUM(LARM:RM!LK52) -> 0 | LL52: =SUM(KG52:LK52) -> 0 | LM52: =SUM(LARM:RM!LM52) -> 0 | LN52: =SUM(LARM:RM!LN52) -> 0 | LO52: =SUM(LARM:RM!LO52) -> 0 | LP52: =SUM(LARM:RM!LP52) -> 0 | LQ52: =SUM(LARM:RM!LQ52) -> 0 | LR52: =SUM(LARM:RM!LR52) -> 0 | LS52: =SUM(LARM:RM!LS52) -> 0 | LT52: =SUM(LARM:RM!LT52) -> 0 | ... MQ52: =SUM(LARM:RM!MQ52) -> 0 | MR52: =SUM(LM52:MQ52) -> 0 | MS52: =SUM(LARM:RM!MS52) -> 0 | MT52: =SUM(LARM:RM!MT52) -> 0 | MU52: =SUM(LARM:RM!MU52) -> 0 | MV52: =SUM(LARM:RM!MV52) -> 0 | MW52: =SUM(LARM:RM!MW52) -> 0 | MX52: =SUM(LARM:RM!MX52) -> 0 | MY52: =SUM(LARM:RM!MY52) -> 0 | MZ52: =SUM(LARM:RM!MZ52) -> 0 | ... NW52: =SUM(LARM:RM!NW52) -> 0 | NX52: =SUM(MS52:NW52) -> 0 | NZ52: =AJ52+BP52+CV52+EB52+FH52+GN52+HT52+IZ52+KF52+LL52+MR52+NX52 -> 0 | OA52: =SUM(OI52:OP52) -> 0 | OB52: =IF(NZ52=0,"",(OA52/NZ52)-1) | OG52: LOTEAMENTO-RES. SANTA CLARA QZ | OI52: =SUM(LARM:RM!OI52) -> 0 | OJ52: =SUM(LARM:RM!OJ52) -> 0 | OK52: =SUM(LARM:RM!OK52) -> 0 | OL52: =SUM(LARM:RM!OL52) -> 0 | OM52: =SUM(LARM:RM!OM52) -> 0 | ON52: =SUM(LARM:RM!ON52) -> 0 | OO52: =SUM(LARM:RM!OO52) -> 0 | OP52: =SUM(LARM:RM!OP52) -> 0 | ... OT52: =SUM(LARM:RM!OT52) -> 0 | OV52: =SUM(OI52:OT52) -> 0
B53: 8.7 | C53: LOTEAMENTO-RES. SANTA CLARA II | E53: =SUM(LARM:RM!E53) -> 0 | F53: =SUM(LARM:RM!F53) -> 0 | G53: =SUM(LARM:RM!G53) -> 0 | H53: =SUM(LARM:RM!H53) -> 0 | I53: =SUM(LARM:RM!I53) -> 0 | J53: =SUM(LARM:RM!J53) -> 0 | K53: =SUM(LARM:RM!K53) -> 0 | L53: =SUM(LARM:RM!L53) -> 0 | ... AI53: =SUM(LARM:RM!AI53) -> 0 | AJ53: =SUM(E53:AI53) -> -14077.5 | AK53: =SUM(LARM:RM!AK53) -> 0 | AL53: =SUM(LARM:RM!AL53) -> 0 | AM53: =SUM(LARM:RM!AM53) -> 0 | AN53: =SUM(LARM:RM!AN53) -> 0 | AO53: =SUM(LARM:RM!AO53) -> 0 | AP53: =SUM(LARM:RM!AP53) -> 0 | AQ53: =SUM(LARM:RM!AQ53) -> 0 | AR53: =SUM(LARM:RM!AR53) -> 0 | ... BO53: =SUM(LARM:RM!BO53) -> 0 | BP53: =SUM(AK53:BO53) -> -9500 | BQ53: =SUM(LARM:RM!BQ53) -> 0 | BR53: =SUM(LARM:RM!BR53) -> 0 | BS53: =SUM(LARM:RM!BS53) -> 0 | BT53: =SUM(LARM:RM!BT53) -> 0 | BU53: =SUM(LARM:RM!BU53) -> 0 | BV53: =SUM(LARM:RM!BV53) -> 0 | BW53: =SUM(LARM:RM!BW53) -> 0 | BX53: =SUM(LARM:RM!BX53) -> 0 | ... CU53: =SUM(LARM:RM!CU53) -> 0 | CV53: =SUM(BQ53:CU53) -> -14077.5 | CW53: =SUM(LARM:RM!CW53) -> 0 | CX53: =SUM(LARM:RM!CX53) -> 0 | CY53: =SUM(LARM:RM!CY53) -> 0 | CZ53: =SUM(LARM:RM!CZ53) -> 0 | DA53: =SUM(LARM:RM!DA53) -> 0 | DB53: =SUM(LARM:RM!DB53) -> 0 | DC53: =SUM(LARM:RM!DC53) -> 0 | DD53: =SUM(LARM:RM!DD53) -> 0 | ... EA53: =SUM(LARM:RM!EA53) -> 0 | EB53: =SUM(CW53:EA53) -> -7038.75 | EC53: =SUM(LARM:RM!EC53) -> 0 | ED53: =SUM(LARM:RM!ED53) -> 0 | EE53: =SUM(LARM:RM!EE53) -> 0 | EF53: =SUM(LARM:RM!EF53) -> 0 | EG53: =SUM(LARM:RM!EG53) -> 0 | EH53: =SUM(LARM:RM!EH53) -> 0 | EI53: =SUM(LARM:RM!EI53) -> 0 | EJ53: =SUM(LARM:RM!EJ53) -> 0 | ... FG53: =SUM(LARM:RM!FG53) -> 0 | FH53: =SUM(EC53:FG53) -> -47373.33 | FI53: =SUM(LARM:RM!FI53) -> 0 | FJ53: =SUM(LARM:RM!FJ53) -> 0 | FK53: =SUM(LARM:RM!FK53) -> 0 | FL53: =SUM(LARM:RM!FL53) -> 0 | FM53: =SUM(LARM:RM!FM53) -> 0 | FN53: =SUM(LARM:RM!FN53) -> 0 | FO53: =SUM(LARM:RM!FO53) -> 0 | FP53: =SUM(LARM:RM!FP53) -> 0 | ... GM53: =SUM(LARM:RM!GM53) -> 0 | GN53: =SUM(FI53:GM53) -> -47373.33 | GO53: =SUM(LARM:RM!GO53) -> 0 | GP53: =SUM(LARM:RM!GP53) -> 0 | GQ53: =SUM(LARM:RM!GQ53) -> 0 | GR53: =SUM(LARM:RM!GR53) -> 0 | GS53: =SUM(LARM:RM!GS53) -> 0 | GT53: =SUM(LARM:RM!GT53) -> 0 | GU53: =SUM(LARM:RM!GU53) -> 0 | GV53: =SUM(LARM:RM!GV53) -> 0 | ... HS53: =SUM(LARM:RM!HS53) -> 0 | HT53: =SUM(GO53:HS53) -> -47373.33 | HU53: =SUM(LARM:RM!HU53) -> 0 | HV53: =SUM(LARM:RM!HV53) -> 0 | HW53: =SUM(LARM:RM!HW53) -> 0 | HX53: =SUM(LARM:RM!HX53) -> 0 | HY53: =SUM(LARM:RM!HY53) -> 0 | HZ53: =SUM(LARM:RM!HZ53) -> 0 | IA53: =SUM(LARM:RM!IA53) -> 0 | IB53: =SUM(LARM:RM!IB53) -> 0 | ... IY53: =SUM(LARM:RM!IY53) -> 0 | IZ53: =SUM(HU53:IY53) -> -47373.33 | JA53: =SUM(LARM:RM!JA53) -> 0 | JB53: =SUM(LARM:RM!JB53) -> 0 | JC53: =SUM(LARM:RM!JC53) -> 0 | JD53: =SUM(LARM:RM!JD53) -> 0 | JE53: =SUM(LARM:RM!JE53) -> 0 | JF53: =SUM(LARM:RM!JF53) -> 0 | JG53: =SUM(LARM:RM!JG53) -> 0 | JH53: =SUM(LARM:RM!JH53) -> 0 | ... KE53: =SUM(LARM:RM!KE53) -> 0 | KF53: =SUM(JA53:KE53) -> -47373.33 | KG53: =SUM(LARM:RM!KG53) -> 0 | KH53: =SUM(LARM:RM!KH53) -> 0 | KI53: =SUM(LARM:RM!KI53) -> 0 | KJ53: =SUM(LARM:RM!KJ53) -> 0 | KK53: =SUM(LARM:RM!KK53) -> 0 | KL53: =SUM(LARM:RM!KL53) -> 0 | KM53: =SUM(LARM:RM!KM53) -> 0 | KN53: =SUM(LARM:RM!KN53) -> 0 | ... LK53: =SUM(LARM:RM!LK53) -> 0 | LL53: =SUM(KG53:LK53) -> -47373.33 | LM53: =SUM(LARM:RM!LM53) -> 0 | LN53: =SUM(LARM:RM!LN53) -> 0 | LO53: =SUM(LARM:RM!LO53) -> 0 | LP53: =SUM(LARM:RM!LP53) -> 0 | LQ53: =SUM(LARM:RM!LQ53) -> 0 | LR53: =SUM(LARM:RM!LR53) -> 0 | LS53: =SUM(LARM:RM!LS53) -> 0 | LT53: =SUM(LARM:RM!LT53) -> 0 | ... MQ53: =SUM(LARM:RM!MQ53) -> 0 | MR53: =SUM(LM53:MQ53) -> -47373.33 | MS53: =SUM(LARM:RM!MS53) -> 0 | MT53: =SUM(LARM:RM!MT53) -> 0 | MU53: =SUM(LARM:RM!MU53) -> 0 | MV53: =SUM(LARM:RM!MV53) -> 0 | MW53: =SUM(LARM:RM!MW53) -> 0 | MX53: =SUM(LARM:RM!MX53) -> 0 | MY53: =SUM(LARM:RM!MY53) -> 0 | MZ53: =SUM(LARM:RM!MZ53) -> 0 | ... NW53: =SUM(LARM:RM!NW53) -> 0 | NX53: =SUM(MS53:NW53) -> -47373.33 | NZ53: =AJ53+BP53+CV53+EB53+FH53+GN53+HT53+IZ53+KF53+LL53+MR53+NX53 -> -423680.39 | OA53: =SUM(OI53:OP53) -> 0 | OB53: =IF(NZ53=0,"",(OA53/NZ53)-1) -> -1 | OG53: SEMOVENTES | OI53: =SUM(LARM:RM!OI52) -> 0 | OJ53: =SUM(LARM:RM!OJ52) -> 0 | OK53: =SUM(LARM:RM!OK52) -> 0 | OL53: =SUM(LARM:RM!OL52) -> 0 | OM53: =SUM(LARM:RM!OM52) -> 0 | ON53: =SUM(LARM:RM!ON52) -> 0 | OO53: =SUM(LARM:RM!OO52) -> 0 | OP53: =SUM(LARM:RM!OP52) -> 0 | ... OT53: =SUM(LARM:RM!OT52) -> 0 | OV53: =SUM(OI53:OT53) -> 0
B54: 8.10 | C54: SEMOVENTES | E54: =SUM(LARM:RM!E54) -> 0 | F54: =SUM(LARM:RM!F54) -> 0 | G54: =SUM(LARM:RM!G54) -> 0 | H54: =SUM(LARM:RM!H54) -> 0 | I54: =SUM(LARM:RM!I54) -> 0 | J54: =SUM(LARM:RM!J54) -> 0 | K54: =SUM(LARM:RM!K54) -> 0 | L54: =SUM(LARM:RM!L54) -> 0 | ... AI54: =SUM(LARM:RM!AI54) -> 0 | AJ54: =SUM(E54:AI54) -> 0 | AK54: =SUM(LARM:RM!AK54) -> 0 | AL54: =SUM(LARM:RM!AL54) -> 0 | AM54: =SUM(LARM:RM!AM54) -> 0 | AN54: =SUM(LARM:RM!AN54) -> 0 | AO54: =SUM(LARM:RM!AO54) -> 0 | AP54: =SUM(LARM:RM!AP54) -> 0 | AQ54: =SUM(LARM:RM!AQ54) -> 0 | AR54: =SUM(LARM:RM!AR54) -> 0 | ... BO54: =SUM(LARM:RM!BO54) -> 0 | BP54: =SUM(AK54:BO54) -> 0 | BQ54: =SUM(LARM:RM!BQ54) -> 0 | BR54: =SUM(LARM:RM!BR54) -> 0 | BS54: =SUM(LARM:RM!BS54) -> 0 | BT54: =SUM(LARM:RM!BT54) -> 0 | BU54: =SUM(LARM:RM!BU54) -> 0 | BV54: =SUM(LARM:RM!BV54) -> 0 | BW54: =SUM(LARM:RM!BW54) -> 0 | BX54: =SUM(LARM:RM!BX54) -> 0 | ... CU54: =SUM(LARM:RM!CU54) -> 0 | CV54: =SUM(BQ54:CU54) -> 0 | CW54: =SUM(LARM:RM!CW54) -> 0 | CX54: =SUM(LARM:RM!CX54) -> 0 | CY54: =SUM(LARM:RM!CY54) -> 0 | CZ54: =SUM(LARM:RM!CZ54) -> 0 | DA54: =SUM(LARM:RM!DA54) -> 0 | DB54: =SUM(LARM:RM!DB54) -> 0 | DC54: =SUM(LARM:RM!DC54) -> 0 | DD54: =SUM(LARM:RM!DD54) -> 0 | ... EA54: =SUM(LARM:RM!EA54) -> 0 | EB54: =SUM(CW54:EA54) -> 0 | EC54: =SUM(LARM:RM!EC54) -> 0 | ED54: =SUM(LARM:RM!ED54) -> 0 | EE54: =SUM(LARM:RM!EE54) -> 0 | EF54: =SUM(LARM:RM!EF54) -> 0 | EG54: =SUM(LARM:RM!EG54) -> 0 | EH54: =SUM(LARM:RM!EH54) -> 0 | EI54: =SUM(LARM:RM!EI54) -> 0 | EJ54: =SUM(LARM:RM!EJ54) -> 0 | ... FG54: =SUM(LARM:RM!FG54) -> 0 | FH54: =SUM(EC54:FG54) -> 0 | FI54: =SUM(LARM:RM!FI54) -> 0 | FJ54: =SUM(LARM:RM!FJ54) -> 0 | FK54: =SUM(LARM:RM!FK54) -> 0 | FL54: =SUM(LARM:RM!FL54) -> 0 | FM54: =SUM(LARM:RM!FM54) -> 0 | FN54: =SUM(LARM:RM!FN54) -> 0 | FO54: =SUM(LARM:RM!FO54) -> 0 | FP54: =SUM(LARM:RM!FP54) -> 0 | ... GM54: =SUM(LARM:RM!GM54) -> 0 | GN54: =SUM(FI54:GM54) -> 0 | GO54: =SUM(LARM:RM!GO54) -> 0 | GP54: =SUM(LARM:RM!GP54) -> 0 | GQ54: =SUM(LARM:RM!GQ54) -> 0 | GR54: =SUM(LARM:RM!GR54) -> 0 | GS54: =SUM(LARM:RM!GS54) -> 0 | GT54: =SUM(LARM:RM!GT54) -> 0 | GU54: =SUM(LARM:RM!GU54) -> 0 | GV54: =SUM(LARM:RM!GV54) -> 0 | ... HS54: =SUM(LARM:RM!HS54) -> 0 | HT54: =SUM(GO54:HS54) -> 0 | HU54: =SUM(LARM:RM!HU54) -> 0 | HV54: =SUM(LARM:RM!HV54) -> 0 | HW54: =SUM(LARM:RM!HW54) -> 0 | HX54: =SUM(LARM:RM!HX54) -> 0 | HY54: =SUM(LARM:RM!HY54) -> 0 | HZ54: =SUM(LARM:RM!HZ54) -> 0 | IA54: =SUM(LARM:RM!IA54) -> 0 | IB54: =SUM(LARM:RM!IB54) -> 0 | ... IY54: =SUM(LARM:RM!IY54) -> 0 | IZ54: =SUM(HU54:IY54) -> 0 | JA54: =SUM(LARM:RM!JA54) -> 0 | JB54: =SUM(LARM:RM!JB54) -> 0 | JC54: =SUM(LARM:RM!JC54) -> 0 | JD54: =SUM(LARM:RM!JD54) -> 0 | JE54: =SUM(LARM:RM!JE54) -> 0 | JF54: =SUM(LARM:RM!JF54) -> 0 | JG54: =SUM(LARM:RM!JG54) -> 0 | JH54: =SUM(LARM:RM!JH54) -> 0 | ... KE54: =SUM(LARM:RM!KE54) -> 0 | KF54: =SUM(JA54:KE54) -> 0 | KG54: =SUM(LARM:RM!KG54) -> 0 | KH54: =SUM(LARM:RM!KH54) -> 0 | KI54: =SUM(LARM:RM!KI54) -> 0 | KJ54: =SUM(LARM:RM!KJ54) -> 0 | KK54: =SUM(LARM:RM!KK54) -> 0 | KL54: =SUM(LARM:RM!KL54) -> 0 | KM54: =SUM(LARM:RM!KM54) -> 0 | KN54: =SUM(LARM:RM!KN54) -> 0 | ... LK54: =SUM(LARM:RM!LK54) -> 0 | LL54: =SUM(KG54:LK54) -> 0 | LM54: =SUM(LARM:RM!LM54) -> 0 | LN54: =SUM(LARM:RM!LN54) -> 0 | LO54: =SUM(LARM:RM!LO54) -> 0 | LP54: =SUM(LARM:RM!LP54) -> 0 | LQ54: =SUM(LARM:RM!LQ54) -> 0 | LR54: =SUM(LARM:RM!LR54) -> 0 | LS54: =SUM(LARM:RM!LS54) -> 0 | LT54: =SUM(LARM:RM!LT54) -> 0 | ... MQ54: =SUM(LARM:RM!MQ54) -> 0 | MR54: =SUM(LM54:MQ54) -> 0 | MS54: =SUM(LARM:RM!MS54) -> 0 | MT54: =SUM(LARM:RM!MT54) -> 0 | MU54: =SUM(LARM:RM!MU54) -> 0 | MV54: =SUM(LARM:RM!MV54) -> 0 | MW54: =SUM(LARM:RM!MW54) -> 0 | MX54: =SUM(LARM:RM!MX54) -> 0 | MY54: =SUM(LARM:RM!MY54) -> 0 | MZ54: =SUM(LARM:RM!MZ54) -> 0 | ... NW54: =SUM(LARM:RM!NW54) -> 0 | NX54: =SUM(MS54:NW54) -> 0 | NZ54: =AJ54+BP54+CV54+EB54+FH54+GN54+HT54+IZ54+KF54+LL54+MR54+NX54 -> 0 | OA54: =SUM(OI54:OP54) -> -585480 | OB54: =IF(NZ54=0,"",(OA54/NZ54)-1) | OG54: SEMOVENTES | OI54: =SUM(LARM:RM!OI53) -> -17000 | OJ54: =SUM(LARM:RM!OJ53) -> -142120 | OK54: =SUM(LARM:RM!OK53) -> -142120 | OL54: =SUM(LARM:RM!OL53) -> -142120 | OM54: =SUM(LARM:RM!OM53) -> -35530 | ON54: =SUM(LARM:RM!ON53) -> -35530 | OO54: =SUM(LARM:RM!OO53) -> -35530 | OP54: =SUM(LARM:RM!OP53) -> -35530 | ... OT54: =SUM(LARM:RM!OT53) -> -35530 | OV54: =SUM(OI54:OT54) -> -727600
B55: 8.11 | C55: CASA2-ESPERANÇA | E55: =SUM(LARM:RM!E55) -> 0 | F55: =SUM(LARM:RM!F55) -> 0 | G55: =SUM(LARM:RM!G55) -> 0 | H55: =SUM(LARM:RM!H55) -> 0 | I55: =SUM(LARM:RM!I55) -> 0 | J55: =SUM(LARM:RM!J55) -> 0 | K55: =SUM(LARM:RM!K55) -> 0 | L55: =SUM(LARM:RM!L55) -> 0 | ... AI55: =SUM(LARM:RM!AI55) -> 0 | AJ55: =SUM(E55:AI55) -> 0 | AK55: =SUM(LARM:RM!AK55) -> 0 | AL55: =SUM(LARM:RM!AL55) -> 0 | AM55: =SUM(LARM:RM!AM55) -> 0 | AN55: =SUM(LARM:RM!AN55) -> 0 | AO55: =SUM(LARM:RM!AO55) -> 0 | AP55: =SUM(LARM:RM!AP55) -> 0 | AQ55: =SUM(LARM:RM!AQ55) -> 0 | AR55: =SUM(LARM:RM!AR55) -> 0 | ... BO55: =SUM(LARM:RM!BO55) -> 0 | BP55: =SUM(AK55:BO55) -> 0 | BQ55: =SUM(LARM:RM!BQ55) -> 0 | BR55: =SUM(LARM:RM!BR55) -> 0 | BS55: =SUM(LARM:RM!BS55) -> 0 | BT55: =SUM(LARM:RM!BT55) -> 0 | BU55: =SUM(LARM:RM!BU55) -> 0 | BV55: =SUM(LARM:RM!BV55) -> 0 | BW55: =SUM(LARM:RM!BW55) -> 0 | BX55: =SUM(LARM:RM!BX55) -> 0 | ... CU55: =SUM(LARM:RM!CU55) -> 0 | CV55: =SUM(BQ55:CU55) -> 0 | CW55: =SUM(LARM:RM!CW55) -> 0 | CX55: =SUM(LARM:RM!CX55) -> 0 | CY55: =SUM(LARM:RM!CY55) -> 0 | CZ55: =SUM(LARM:RM!CZ55) -> 0 | DA55: =SUM(LARM:RM!DA55) -> 0 | DB55: =SUM(LARM:RM!DB55) -> 0 | DC55: =SUM(LARM:RM!DC55) -> 0 | DD55: =SUM(LARM:RM!DD55) -> 0 | ... EA55: =SUM(LARM:RM!EA55) -> 0 | EB55: =SUM(CW55:EA55) -> 0 | EC55: =SUM(LARM:RM!EC55) -> 0 | ED55: =SUM(LARM:RM!ED55) -> 0 | EE55: =SUM(LARM:RM!EE55) -> 0 | EF55: =SUM(LARM:RM!EF55) -> 0 | EG55: =SUM(LARM:RM!EG55) -> 0 | EH55: =SUM(LARM:RM!EH55) -> 0 | EI55: =SUM(LARM:RM!EI55) -> 0 | EJ55: =SUM(LARM:RM!EJ55) -> 0 | ... FG55: =SUM(LARM:RM!FG55) -> 0 | FH55: =SUM(EC55:FG55) -> 0 | FI55: =SUM(LARM:RM!FI55) -> 0 | FJ55: =SUM(LARM:RM!FJ55) -> 0 | FK55: =SUM(LARM:RM!FK55) -> 0 | FL55: =SUM(LARM:RM!FL55) -> 0 | FM55: =SUM(LARM:RM!FM55) -> 0 | FN55: =SUM(LARM:RM!FN55) -> 0 | FO55: =SUM(LARM:RM!FO55) -> 0 | FP55: =SUM(LARM:RM!FP55) -> 0 | ... GM55: =SUM(LARM:RM!GM55) -> 0 | GN55: =SUM(FI55:GM55) -> 0 | GO55: =SUM(LARM:RM!GO55) -> 0 | GP55: =SUM(LARM:RM!GP55) -> 0 | GQ55: =SUM(LARM:RM!GQ55) -> 0 | GR55: =SUM(LARM:RM!GR55) -> 0 | GS55: =SUM(LARM:RM!GS55) -> 0 | GT55: =SUM(LARM:RM!GT55) -> 0 | GU55: =SUM(LARM:RM!GU55) -> 0 | GV55: =SUM(LARM:RM!GV55) -> 0 | ... HS55: =SUM(LARM:RM!HS55) -> 0 | HT55: =SUM(GO55:HS55) -> 0 | HU55: =SUM(LARM:RM!HU55) -> 0 | HV55: =SUM(LARM:RM!HV55) -> 0 | HW55: =SUM(LARM:RM!HW55) -> 0 | HX55: =SUM(LARM:RM!HX55) -> 0 | HY55: =SUM(LARM:RM!HY55) -> 0 | HZ55: =SUM(LARM:RM!HZ55) -> 0 | IA55: =SUM(LARM:RM!IA55) -> 0 | IB55: =SUM(LARM:RM!IB55) -> 0 | ... IY55: =SUM(LARM:RM!IY55) -> 0 | IZ55: =SUM(HU55:IY55) -> 0 | JA55: =SUM(LARM:RM!JA55) -> 0 | JB55: =SUM(LARM:RM!JB55) -> 0 | JC55: =SUM(LARM:RM!JC55) -> 0 | JD55: =SUM(LARM:RM!JD55) -> 0 | JE55: =SUM(LARM:RM!JE55) -> 0 | JF55: =SUM(LARM:RM!JF55) -> 0 | JG55: =SUM(LARM:RM!JG55) -> 0 | JH55: =SUM(LARM:RM!JH55) -> 0 | ... KE55: =SUM(LARM:RM!KE55) -> 0 | KF55: =SUM(JA55:KE55) -> 0 | KG55: =SUM(LARM:RM!KG55) -> 0 | KH55: =SUM(LARM:RM!KH55) -> 0 | KI55: =SUM(LARM:RM!KI55) -> 0 | KJ55: =SUM(LARM:RM!KJ55) -> 0 | KK55: =SUM(LARM:RM!KK55) -> 0 | KL55: =SUM(LARM:RM!KL55) -> 0 | KM55: =SUM(LARM:RM!KM55) -> 0 | KN55: =SUM(LARM:RM!KN55) -> 0 | ... LK55: =SUM(LARM:RM!LK55) -> 0 | LL55: =SUM(KG55:LK55) -> 0 | LM55: =SUM(LARM:RM!LM55) -> 0 | LN55: =SUM(LARM:RM!LN55) -> 0 | LO55: =SUM(LARM:RM!LO55) -> 0 | LP55: =SUM(LARM:RM!LP55) -> 0 | LQ55: =SUM(LARM:RM!LQ55) -> 0 | LR55: =SUM(LARM:RM!LR55) -> 0 | LS55: =SUM(LARM:RM!LS55) -> 0 | LT55: =SUM(LARM:RM!LT55) -> 0 | ... MQ55: =SUM(LARM:RM!MQ55) -> 0 | MR55: =SUM(LM55:MQ55) -> 0 | MS55: =SUM(LARM:RM!MS55) -> 0 | MT55: =SUM(LARM:RM!MT55) -> 0 | MU55: =SUM(LARM:RM!MU55) -> 0 | MV55: =SUM(LARM:RM!MV55) -> 0 | MW55: =SUM(LARM:RM!MW55) -> 0 | MX55: =SUM(LARM:RM!MX55) -> 0 | MY55: =SUM(LARM:RM!MY55) -> 0 | MZ55: =SUM(LARM:RM!MZ55) -> 0 | ... NW55: =SUM(LARM:RM!NW55) -> 0 | NX55: =SUM(MS55:NW55) -> 0 | NZ55: =AJ55+BP55+CV55+EB55+FH55+GN55+HT55+IZ55+KF55+LL55+MR55+NX55 -> 0 | OA55: =SUM(OI55:OP55) -> 0 | OB55: =IF(NZ55=0,"",(OA55/NZ55)-1) | OG55: FAZENDA ESPERANÇA | OI55: =SUM(LARM:RM!OI54) -> 0 | OJ55: =SUM(LARM:RM!OJ54) -> 0 | OK55: =SUM(LARM:RM!OK54) -> 0 | OL55: =SUM(LARM:RM!OL54) -> 0 | OM55: =SUM(LARM:RM!OM54) -> 0 | ON55: =SUM(LARM:RM!ON54) -> 0 | OO55: =SUM(LARM:RM!OO54) -> 0 | OP55: =SUM(LARM:RM!OP54) -> 0 | ... OT55: =SUM(LARM:RM!OT54) -> 0 | OV55: =SUM(OI55:OT55) -> 0
B56: 8.12 | C56: BRASIL AGRO II | E56: =SUM(LARM:RM!E56) -> 0 | F56: =SUM(LARM:RM!F56) -> 0 | G56: =SUM(LARM:RM!G56) -> 0 | H56: =SUM(LARM:RM!H56) -> 0 | I56: =SUM(LARM:RM!I56) -> 0 | J56: =SUM(LARM:RM!J56) -> 0 | K56: =SUM(LARM:RM!K56) -> 0 | L56: =SUM(LARM:RM!L56) -> 0 | ... AI56: =SUM(LARM:RM!AI56) -> 0 | AJ56: =SUM(E56:AI56) -> 0 | AK56: =SUM(LARM:RM!AK56) -> 0 | AL56: =SUM(LARM:RM!AL56) -> 0 | AM56: =SUM(LARM:RM!AM56) -> 0 | AN56: =SUM(LARM:RM!AN56) -> 0 | AO56: =SUM(LARM:RM!AO56) -> 0 | AP56: =SUM(LARM:RM!AP56) -> 0 | AQ56: =SUM(LARM:RM!AQ56) -> 0 | AR56: =SUM(LARM:RM!AR56) -> 0 | ... BO56: =SUM(LARM:RM!BO56) -> 0 | BP56: =SUM(AK56:BO56) -> 0 | BQ56: =SUM(LARM:RM!BQ56) -> 0 | BR56: =SUM(LARM:RM!BR56) -> 0 | BS56: =SUM(LARM:RM!BS56) -> 0 | BT56: =SUM(LARM:RM!BT56) -> 0 | BU56: =SUM(LARM:RM!BU56) -> 0 | BV56: =SUM(LARM:RM!BV56) -> 0 | BW56: =SUM(LARM:RM!BW56) -> 0 | BX56: =SUM(LARM:RM!BX56) -> 0 | ... CU56: =SUM(LARM:RM!CU56) -> 0 | CV56: =SUM(BQ56:CU56) -> 0 | CW56: =SUM(LARM:RM!CW56) -> 0 | CX56: =SUM(LARM:RM!CX56) -> 0 | CY56: =SUM(LARM:RM!CY56) -> 0 | CZ56: =SUM(LARM:RM!CZ56) -> 0 | DA56: =SUM(LARM:RM!DA56) -> 0 | DB56: =SUM(LARM:RM!DB56) -> 0 | DC56: =SUM(LARM:RM!DC56) -> 0 | DD56: =SUM(LARM:RM!DD56) -> 0 | ... EA56: =SUM(LARM:RM!EA56) -> 0 | EB56: =SUM(CW56:EA56) -> 0 | EC56: =SUM(LARM:RM!EC56) -> 0 | ED56: =SUM(LARM:RM!ED56) -> 0 | EE56: =SUM(LARM:RM!EE56) -> 0 | EF56: =SUM(LARM:RM!EF56) -> 334987.72 | EG56: =SUM(LARM:RM!EG56) -> 0 | EH56: =SUM(LARM:RM!EH56) -> 0 | EI56: =SUM(LARM:RM!EI56) -> 0 | EJ56: =SUM(LARM:RM!EJ56) -> 0 | ... FG56: =SUM(LARM:RM!FG56) -> 0 | FH56: =SUM(EC56:FG56) -> 334987.72 | FI56: =SUM(LARM:RM!FI56) -> 0 | FJ56: =SUM(LARM:RM!FJ56) -> 0 | FK56: =SUM(LARM:RM!FK56) -> 0 | FL56: =SUM(LARM:RM!FL56) -> 0 | FM56: =SUM(LARM:RM!FM56) -> 0 | FN56: =SUM(LARM:RM!FN56) -> 0 | FO56: =SUM(LARM:RM!FO56) -> 0 | FP56: =SUM(LARM:RM!FP56) -> 0 | ... GM56: =SUM(LARM:RM!GM56) -> 0 | GN56: =SUM(FI56:GM56) -> 0 | GO56: =SUM(LARM:RM!GO56) -> 0 | GP56: =SUM(LARM:RM!GP56) -> 0 | GQ56: =SUM(LARM:RM!GQ56) -> 0 | GR56: =SUM(LARM:RM!GR56) -> 0 | GS56: =SUM(LARM:RM!GS56) -> 0 | GT56: =SUM(LARM:RM!GT56) -> 0 | GU56: =SUM(LARM:RM!GU56) -> 0 | GV56: =SUM(LARM:RM!GV56) -> 0 | ... HS56: =SUM(LARM:RM!HS56) -> 0 | HT56: =SUM(GO56:HS56) -> 0 | HU56: =SUM(LARM:RM!HU56) -> 0 | HV56: =SUM(LARM:RM!HV56) -> 0 | HW56: =SUM(LARM:RM!HW56) -> 0 | HX56: =SUM(LARM:RM!HX56) -> 0 | HY56: =SUM(LARM:RM!HY56) -> 0 | HZ56: =SUM(LARM:RM!HZ56) -> 0 | IA56: =SUM(LARM:RM!IA56) -> 0 | IB56: =SUM(LARM:RM!IB56) -> 0 | ... IY56: =SUM(LARM:RM!IY56) -> 0 | IZ56: =SUM(HU56:IY56) -> 0 | JA56: =SUM(LARM:RM!JA56) -> 0 | JB56: =SUM(LARM:RM!JB56) -> 0 | JC56: =SUM(LARM:RM!JC56) -> 0 | JD56: =SUM(LARM:RM!JD56) -> 0 | JE56: =SUM(LARM:RM!JE56) -> 0 | JF56: =SUM(LARM:RM!JF56) -> 0 | JG56: =SUM(LARM:RM!JG56) -> 0 | JH56: =SUM(LARM:RM!JH56) -> 0 | ... KE56: =SUM(LARM:RM!KE56) -> 0 | KF56: =SUM(JA56:KE56) -> 0 | KG56: =SUM(LARM:RM!KG56) -> 0 | KH56: =SUM(LARM:RM!KH56) -> 0 | KI56: =SUM(LARM:RM!KI56) -> 0 | KJ56: =SUM(LARM:RM!KJ56) -> 0 | KK56: =SUM(LARM:RM!KK56) -> 0 | KL56: =SUM(LARM:RM!KL56) -> 0 | KM56: =SUM(LARM:RM!KM56) -> 0 | KN56: =SUM(LARM:RM!KN56) -> 0 | ... LK56: =SUM(LARM:RM!LK56) -> 0 | LL56: =SUM(KG56:LK56) -> 0 | LM56: =SUM(LARM:RM!LM56) -> 0 | LN56: =SUM(LARM:RM!LN56) -> 0 | LO56: =SUM(LARM:RM!LO56) -> 0 | LP56: =SUM(LARM:RM!LP56) -> 0 | LQ56: =SUM(LARM:RM!LQ56) -> 0 | LR56: =SUM(LARM:RM!LR56) -> 0 | LS56: =SUM(LARM:RM!LS56) -> 0 | LT56: =SUM(LARM:RM!LT56) -> 0 | ... MQ56: =SUM(LARM:RM!MQ56) -> 0 | MR56: =SUM(LM56:MQ56) -> 0 | MS56: =SUM(LARM:RM!MS56) -> 0 | MT56: =SUM(LARM:RM!MT56) -> 0 | MU56: =SUM(LARM:RM!MU56) -> 0 | MV56: =SUM(LARM:RM!MV56) -> 0 | MW56: =SUM(LARM:RM!MW56) -> 0 | MX56: =SUM(LARM:RM!MX56) -> 0 | MY56: =SUM(LARM:RM!MY56) -> 0 | MZ56: =SUM(LARM:RM!MZ56) -> 0 | ... NW56: =SUM(LARM:RM!NW56) -> 0 | NX56: =SUM(MS56:NW56) -> 0 | NZ56: =AJ56+BP56+CV56+EB56+FH56+GN56+HT56+IZ56+KF56+LL56+MR56+NX56 -> 334987.72 | OA56: =SUM(OI56:OP56) -> 0 | OB56: =IF(NZ56=0,"",(OA56/NZ56)-1) -> -1 | OG56: BRASIL AGRO II | OI56: =SUM(LARM:RM!OI55) -> 0 | OJ56: =SUM(LARM:RM!OJ55) -> 0 | OK56: =SUM(LARM:RM!OK55) -> 0 | OL56: =SUM(LARM:RM!OL55) -> 0 | OM56: =SUM(LARM:RM!OM55) -> 0 | ON56: =SUM(LARM:RM!ON55) -> 0 | OO56: =SUM(LARM:RM!OO55) -> 0 | OP56: =SUM(LARM:RM!OP55) -> 0 | ... OT56: =SUM(LARM:RM!OT55) -> 0 | OV56: =SUM(OI56:OT56) -> 0
B57: 8.13 | C57: BRASIL AGRO III | E57: =SUM(LARM:RM!E57) -> 0 | F57: =SUM(LARM:RM!F57) -> 0 | G57: =SUM(LARM:RM!G57) -> 0 | H57: =SUM(LARM:RM!H57) -> 0 | I57: =SUM(LARM:RM!I57) -> 0 | J57: =SUM(LARM:RM!J57) -> 0 | K57: =SUM(LARM:RM!K57) -> 0 | L57: =SUM(LARM:RM!L57) -> 0 | ... AI57: =SUM(LARM:RM!AI57) -> 0 | AJ57: =SUM(E57:AI57) -> 0 | AK57: =SUM(LARM:RM!AK57) -> 0 | AL57: =SUM(LARM:RM!AL57) -> 0 | AM57: =SUM(LARM:RM!AM57) -> 0 | AN57: =SUM(LARM:RM!AN57) -> 0 | AO57: =SUM(LARM:RM!AO57) -> 0 | AP57: =SUM(LARM:RM!AP57) -> 0 | AQ57: =SUM(LARM:RM!AQ57) -> 0 | AR57: =SUM(LARM:RM!AR57) -> 0 | ... BO57: =SUM(LARM:RM!BO57) -> 0 | BP57: =SUM(AK57:BO57) -> 0 | BQ57: =SUM(LARM:RM!BQ57) -> 0 | BR57: =SUM(LARM:RM!BR57) -> 0 | BS57: =SUM(LARM:RM!BS57) -> 0 | BT57: =SUM(LARM:RM!BT57) -> 0 | BU57: =SUM(LARM:RM!BU57) -> 0 | BV57: =SUM(LARM:RM!BV57) -> 0 | BW57: =SUM(LARM:RM!BW57) -> 0 | BX57: =SUM(LARM:RM!BX57) -> 0 | ... CU57: =SUM(LARM:RM!CU57) -> 0 | CV57: =SUM(BQ57:CU57) -> 0 | CW57: =SUM(LARM:RM!CW57) -> 0 | CX57: =SUM(LARM:RM!CX57) -> 0 | CY57: =SUM(LARM:RM!CY57) -> 0 | CZ57: =SUM(LARM:RM!CZ57) -> 0 | DA57: =SUM(LARM:RM!DA57) -> 0 | DB57: =SUM(LARM:RM!DB57) -> 0 | DC57: =SUM(LARM:RM!DC57) -> 0 | DD57: =SUM(LARM:RM!DD57) -> 0 | ... EA57: =SUM(LARM:RM!EA57) -> 0 | EB57: =SUM(CW57:EA57) -> 0 | EC57: =SUM(LARM:RM!EC57) -> 0 | ED57: =SUM(LARM:RM!ED57) -> 0 | EE57: =SUM(LARM:RM!EE57) -> 0 | EF57: =SUM(LARM:RM!EF57) -> 0 | EG57: =SUM(LARM:RM!EG57) -> 0 | EH57: =SUM(LARM:RM!EH57) -> 0 | EI57: =SUM(LARM:RM!EI57) -> 0 | EJ57: =SUM(LARM:RM!EJ57) -> 0 | ... FG57: =SUM(LARM:RM!FG57) -> 0 | FH57: =SUM(EC57:FG57) -> 0 | FI57: =SUM(LARM:RM!FI57) -> 0 | FJ57: =SUM(LARM:RM!FJ57) -> 0 | FK57: =SUM(LARM:RM!FK57) -> 0 | FL57: =SUM(LARM:RM!FL57) -> 0 | FM57: =SUM(LARM:RM!FM57) -> 0 | FN57: =SUM(LARM:RM!FN57) -> 0 | FO57: =SUM(LARM:RM!FO57) -> 0 | FP57: =SUM(LARM:RM!FP57) -> 0 | ... GM57: =SUM(LARM:RM!GM57) -> 0 | GN57: =SUM(FI57:GM57) -> 0 | GO57: =SUM(LARM:RM!GO57) -> 0 | GP57: =SUM(LARM:RM!GP57) -> 0 | GQ57: =SUM(LARM:RM!GQ57) -> 0 | GR57: =SUM(LARM:RM!GR57) -> 0 | GS57: =SUM(LARM:RM!GS57) -> 0 | GT57: =SUM(LARM:RM!GT57) -> 0 | GU57: =SUM(LARM:RM!GU57) -> 0 | GV57: =SUM(LARM:RM!GV57) -> 0 | ... HS57: =SUM(LARM:RM!HS57) -> 0 | HT57: =SUM(GO57:HS57) -> 0 | HU57: =SUM(LARM:RM!HU57) -> 0 | HV57: =SUM(LARM:RM!HV57) -> 0 | HW57: =SUM(LARM:RM!HW57) -> 0 | HX57: =SUM(LARM:RM!HX57) -> 0 | HY57: =SUM(LARM:RM!HY57) -> 0 | HZ57: =SUM(LARM:RM!HZ57) -> 0 | IA57: =SUM(LARM:RM!IA57) -> 0 | IB57: =SUM(LARM:RM!IB57) -> 0 | ... IY57: =SUM(LARM:RM!IY57) -> 0 | IZ57: =SUM(HU57:IY57) -> 0 | JA57: =SUM(LARM:RM!JA57) -> 0 | JB57: =SUM(LARM:RM!JB57) -> 0 | JC57: =SUM(LARM:RM!JC57) -> 0 | JD57: =SUM(LARM:RM!JD57) -> 0 | JE57: =SUM(LARM:RM!JE57) -> 0 | JF57: =SUM(LARM:RM!JF57) -> 0 | JG57: =SUM(LARM:RM!JG57) -> 0 | JH57: =SUM(LARM:RM!JH57) -> 0 | ... KE57: =SUM(LARM:RM!KE57) -> 0 | KF57: =SUM(JA57:KE57) -> 0 | KG57: =SUM(LARM:RM!KG57) -> 0 | KH57: =SUM(LARM:RM!KH57) -> 0 | KI57: =SUM(LARM:RM!KI57) -> 0 | KJ57: =SUM(LARM:RM!KJ57) -> 0 | KK57: =SUM(LARM:RM!KK57) -> 0 | KL57: =SUM(LARM:RM!KL57) -> 0 | KM57: =SUM(LARM:RM!KM57) -> 0 | KN57: =SUM(LARM:RM!KN57) -> 0 | ... LK57: =SUM(LARM:RM!LK57) -> 0 | LL57: =SUM(KG57:LK57) -> 0 | LM57: =SUM(LARM:RM!LM57) -> 0 | LN57: =SUM(LARM:RM!LN57) -> 0 | LO57: =SUM(LARM:RM!LO57) -> 0 | LP57: =SUM(LARM:RM!LP57) -> 0 | LQ57: =SUM(LARM:RM!LQ57) -> 0 | LR57: =SUM(LARM:RM!LR57) -> 0 | LS57: =SUM(LARM:RM!LS57) -> 0 | LT57: =SUM(LARM:RM!LT57) -> 0 | ... MQ57: =SUM(LARM:RM!MQ57) -> 0 | MR57: =SUM(LM57:MQ57) -> 0 | MS57: =SUM(LARM:RM!MS57) -> 0 | MT57: =SUM(LARM:RM!MT57) -> 0 | MU57: =SUM(LARM:RM!MU57) -> 0 | MV57: =SUM(LARM:RM!MV57) -> 0 | MW57: =SUM(LARM:RM!MW57) -> 0 | MX57: =SUM(LARM:RM!MX57) -> 0 | MY57: =SUM(LARM:RM!MY57) -> 0 | MZ57: =SUM(LARM:RM!MZ57) -> 0 | ... NW57: =SUM(LARM:RM!NW57) -> 0 | NX57: =SUM(MS57:NW57) -> 0 | NZ57: =AJ57+BP57+CV57+EB57+FH57+GN57+HT57+IZ57+KF57+LL57+MR57+NX57 -> 0 | OA57: =SUM(OI57:OP57) -> 0 | OB57: =IF(NZ57=0,"",(OA57/NZ57)-1) | OG57: BRASIL AGRO III | OI57: =SUM(LARM:RM!OI56) -> 0 | OJ57: =SUM(LARM:RM!OJ56) -> 0 | OK57: =SUM(LARM:RM!OK56) -> 0 | OL57: =SUM(LARM:RM!OL56) -> 0 | OM57: =SUM(LARM:RM!OM56) -> 0 | ON57: =SUM(LARM:RM!ON56) -> 0 | OO57: =SUM(LARM:RM!OO56) -> 0 | OP57: =SUM(LARM:RM!OP56) -> 0 | ... OT57: =SUM(LARM:RM!OT56) -> 0 | OV57: =SUM(OI57:OT57) -> 0
C59: Distribuição de Lucros | E59: =SUM(E60) -> 0 | F59: =SUM(F60) -> -30000 | G59: =SUM(G60) -> 0 | H59: =SUM(H60) -> 0 | I59: =SUM(I60) -> 0 | J59: =SUM(J60) -> 0 | K59: =SUM(K60) -> 0 | L59: =SUM(L60) -> -70000 | ... NX59: =SUM(NX60) -> -100000 | NZ59: =SUM(NZ60) -> -1230000 | OA59: =SUM(OA60:OA64) -> 7734939.7 | OB59: =IF(OA59=0,"",((NZ59/OA59)-1)*-1) -> 1.1590187 | OG59: Distribuição de Lucros | OI59: =SUM(OI60) -> -100000 | OJ59: =SUM(OJ60) -> -100000 | OK59: =SUM(OK60) -> -100000 | OL59: =SUM(OL60) -> -100000 | OM59: =SUM(OM60) -> -100000 | ON59: =SUM(ON60) -> -100000 | OO59: =SUM(OO60) -> -100000 | OP59: =SUM(OP60) -> -100000 | ... OT59: =SUM(OT60) -> -100000 | OV59: =SUM(OV60) -> -1200000
B60: 9.1 | C60: Lucros distribuidos | E60: =SUM(LARM:RM!E60) -> 0 | F60: =SUM(LARM:RM!F60) -> -30000 | G60: =SUM(LARM:RM!G60) -> 0 | H60: =SUM(LARM:RM!H60) -> 0 | I60: =SUM(LARM:RM!I60) -> 0 | J60: =SUM(LARM:RM!J60) -> 0 | K60: =SUM(LARM:RM!K60) -> 0 | L60: =SUM(LARM:RM!L60) -> -70000 | ... AI60: =SUM(LARM:RM!AI60) -> 0 | AJ60: =SUM(E60:AI60) -> -100000 | AK60: =SUM(LARM:RM!AK60) -> 0 | AL60: =SUM(LARM:RM!AL60) -> -30000 | AM60: =SUM(LARM:RM!AM60) -> 0 | AN60: =SUM(LARM:RM!AN60) -> 0 | AO60: =SUM(LARM:RM!AO60) -> 0 | AP60: =SUM(LARM:RM!AP60) -> 0 | AQ60: =SUM(LARM:RM!AQ60) -> 0 | AR60: =SUM(LARM:RM!AR60) -> 0 | ... BO60: =SUM(LARM:RM!BO60) -> 0 | BP60: =SUM(AK60:BO60) -> -130000 | BQ60: =SUM(LARM:RM!BQ60) -> 0 | BR60: =SUM(LARM:RM!BR60) -> -100000 | BS60: =SUM(LARM:RM!BS60) -> 0 | BT60: =SUM(LARM:RM!BT60) -> 0 | BU60: =SUM(LARM:RM!BU60) -> 0 | BV60: =SUM(LARM:RM!BV60) -> 0 | BW60: =SUM(LARM:RM!BW60) -> 0 | BX60: =SUM(LARM:RM!BX60) -> 0 | ... CU60: =SUM(LARM:RM!CU60) -> 0 | CV60: =SUM(BQ60:CU60) -> -100000 | CW60: =SUM(LARM:RM!CW60) -> -100000 | CX60: =SUM(LARM:RM!CX60) -> 0 | CY60: =SUM(LARM:RM!CY60) -> 0 | CZ60: =SUM(LARM:RM!CZ60) -> 0 | DA60: =SUM(LARM:RM!DA60) -> 0 | DB60: =SUM(LARM:RM!DB60) -> 0 | DC60: =SUM(LARM:RM!DC60) -> 0 | DD60: =SUM(LARM:RM!DD60) -> 0 | ... EA60: =SUM(LARM:RM!EA60) -> 0 | EB60: =SUM(CW60:EA60) -> -200000 | EC60: =SUM(LARM:RM!EC60) -> 0 | ED60: =SUM(LARM:RM!ED60) -> 0 | EE60: =SUM(LARM:RM!EE60) -> 0 | EF60: =SUM(LARM:RM!EF60) -> 0 | EG60: =SUM(LARM:RM!EG60) -> 0 | EH60: =SUM(LARM:RM!EH60) -> 0 | EI60: =SUM(LARM:RM!EI60) -> 0 | EJ60: =SUM(LARM:RM!EJ60) -> 0 | ... FG60: =SUM(LARM:RM!FG60) -> 0 | FH60: =SUM(EC60:FG60) -> 0 | FI60: =SUM(LARM:RM!FI60) -> 0 | FJ60: =SUM(LARM:RM!FJ60) -> 0 | FK60: =SUM(LARM:RM!FK60) -> 0 | FL60: =SUM(LARM:RM!FL60) -> 0 | FM60: =SUM(LARM:RM!FM60) -> 0 | FN60: =SUM(LARM:RM!FN60) -> 0 | FO60: =SUM(LARM:RM!FO60) -> 0 | FP60: =SUM(LARM:RM!FP60) -> 0 | ... GM60: =SUM(LARM:RM!GM60) -> 0 | GN60: =SUM(FI60:GM60) -> -100000 | GO60: =SUM(LARM:RM!GO60) -> 0 | GP60: =SUM(LARM:RM!GP60) -> 0 | GQ60: =SUM(LARM:RM!GQ60) -> 0 | GR60: =SUM(LARM:RM!GR60) -> -100000 | GS60: =SUM(LARM:RM!GS60) -> 0 | GT60: =SUM(LARM:RM!GT60) -> 0 | GU60: =SUM(LARM:RM!GU60) -> 0 | GV60: =SUM(LARM:RM!GV60) -> 0 | ... HS60: =SUM(LARM:RM!HS60) -> 0 | HT60: =SUM(GO60:HS60) -> -100000 | HU60: =SUM(LARM:RM!HU60) -> 0 | HV60: =SUM(LARM:RM!HV60) -> 0 | HW60: =SUM(LARM:RM!HW60) -> 0 | HX60: =SUM(LARM:RM!HX60) -> -100000 | HY60: =SUM(LARM:RM!HY60) -> 0 | HZ60: =SUM(LARM:RM!HZ60) -> 0 | IA60: =SUM(LARM:RM!IA60) -> 0 | IB60: =SUM(LARM:RM!IB60) -> 0 | ... IY60: =SUM(LARM:RM!IY60) -> 0 | IZ60: =SUM(HU60:IY60) -> -100000 | JA60: =SUM(LARM:RM!JA60) -> 0 | JB60: =SUM(LARM:RM!JB60) -> 0 | JC60: =SUM(LARM:RM!JC60) -> 0 | JD60: =SUM(LARM:RM!JD60) -> 0 | JE60: =SUM(LARM:RM!JE60) -> 0 | JF60: =SUM(LARM:RM!JF60) -> 0 | JG60: =SUM(LARM:RM!JG60) -> 0 | JH60: =SUM(LARM:RM!JH60) -> -100000 | ... KE60: =SUM(LARM:RM!KE60) -> 0 | KF60: =SUM(JA60:KE60) -> -100000 | KG60: =SUM(LARM:RM!KG60) -> 0 | KH60: =SUM(LARM:RM!KH60) -> 0 | KI60: =SUM(LARM:RM!KI60) -> 0 | KJ60: =SUM(LARM:RM!KJ60) -> 0 | KK60: =SUM(LARM:RM!KK60) -> 0 | KL60: =SUM(LARM:RM!KL60) -> 0 | KM60: =SUM(LARM:RM!KM60) -> 0 | KN60: =SUM(LARM:RM!KN60) -> 0 | ... LK60: =SUM(LARM:RM!LK60) -> 0 | LL60: =SUM(KG60:LK60) -> -100000 | LM60: =SUM(LARM:RM!LM60) -> 0 | LN60: =SUM(LARM:RM!LN60) -> 0 | LO60: =SUM(LARM:RM!LO60) -> 0 | LP60: =SUM(LARM:RM!LP60) -> 0 | LQ60: =SUM(LARM:RM!LQ60) -> 0 | LR60: =SUM(LARM:RM!LR60) -> 0 | LS60: =SUM(LARM:RM!LS60) -> 0 | LT60: =SUM(LARM:RM!LT60) -> 0 | ... MQ60: =SUM(LARM:RM!MQ60) -> 0 | MR60: =SUM(LM60:MQ60) -> -100000 | MS60: =SUM(LARM:RM!MS60) -> 0 | MT60: =SUM(LARM:RM!MT60) -> 0 | MU60: =SUM(LARM:RM!MU60) -> 0 | MV60: =SUM(LARM:RM!MV60) -> 0 | MW60: =SUM(LARM:RM!MW60) -> 0 | MX60: =SUM(LARM:RM!MX60) -> 0 | MY60: =SUM(LARM:RM!MY60) -> 0 | MZ60: =SUM(LARM:RM!MZ60) -> 0 | ... NW60: =SUM(LARM:RM!NW60) -> 0 | NX60: =SUM(MS60:NW60) -> -100000 | NZ60: =AJ60+BP60+CV60+EB60+FH60+GN60+HT60+IZ60+KF60+LL60+MR60+NX60 -> -1230000 | OA60: =SUM(OI60:OP60) -> -800000 | OB60: =IF(OA60=0,"",((NZ60/OA60)-1)*-1) -> -0.5375 | OG60: Lucros distribuidos | OI60: =SUM(LARM:RM!OI59) -> -100000 | OJ60: =SUM(LARM:RM!OJ59) -> -100000 | OK60: =SUM(LARM:RM!OK59) -> -100000 | OL60: =SUM(LARM:RM!OL59) -> -100000 | OM60: =SUM(LARM:RM!OM59) -> -100000 | ON60: =SUM(LARM:RM!ON59) -> -100000 | OO60: =SUM(LARM:RM!OO59) -> -100000 | OP60: =SUM(LARM:RM!OP59) -> -100000 | ... OT60: =SUM(LARM:RM!OT59) -> -100000 | OV60: =SUM(LARM:RM!OV59) -> -1200000
C62: Sucessão | E62: =SUM(E63) -> 0 | F62: =SUM(F63) -> 0 | G62: =SUM(G63) -> 0 | H62: =SUM(H63) -> 0 | I62: =SUM(I63) -> 0 | J62: =SUM(J63) -> 0 | K62: =SUM(K63) -> 0 | L62: =SUM(L63) -> 0 | ... NX62: =SUM(NX63) -> 0 | NZ62: =SUM(NZ63) -> 0 | OA62: =SUM(OA63:OA67) -> 8534939.7 | OB62: =IF(OA62=0,"",((NZ62/OA62)-1)*-1) -> 1 | OG62: Sucessão | OI62: =SUM(OI63) -> 0 | OJ62: =SUM(OJ63) -> 0 | OK62: =SUM(OK63) -> 0 | OL62: =SUM(OL63) -> 0 | OM62: =SUM(OM63) -> 0 | ON62: =SUM(ON63) -> 0 | OO62: =SUM(OO63) -> 0 | OP62: =SUM(OP63) -> 0 | ... OT62: =SUM(OT63) -> 0 | OV62: =SUM(OV63) -> 0
B63: 10.1 | C63: Impostos/ Taxas / Comissões | E63: =SUM(LARM:RM!E63) -> 0 | F63: =SUM(LARM:RM!F63) -> 0 | G63: =SUM(LARM:RM!G63) -> 0 | H63: =SUM(LARM:RM!H63) -> 0 | I63: =SUM(LARM:RM!I63) -> 0 | J63: =SUM(LARM:RM!J63) -> 0 | K63: =SUM(LARM:RM!K63) -> 0 | L63: =SUM(LARM:RM!L63) -> 0 | ... AI63: =SUM(LARM:RM!AI63) -> 0 | AJ63: =SUM(E63:AI63) -> 0 | AK63: =SUM(LARM:RM!AK63) -> 0 | AL63: =SUM(LARM:RM!AL63) -> 0 | AM63: =SUM(LARM:RM!AM63) -> 0 | AN63: =SUM(LARM:RM!AN63) -> 0 | AO63: =SUM(LARM:RM!AO63) -> 0 | AP63: =SUM(LARM:RM!AP63) -> 0 | AQ63: =SUM(LARM:RM!AQ63) -> 0 | AR63: =SUM(LARM:RM!AR63) -> 0 | ... BO63: =SUM(LARM:RM!BO63) -> 0 | BP63: =SUM(AK63:BO63) -> 0 | BQ63: =SUM(LARM:RM!BQ63) -> 0 | BR63: =SUM(LARM:RM!BR63) -> 0 | BS63: =SUM(LARM:RM!BS63) -> 0 | BT63: =SUM(LARM:RM!BT63) -> 0 | BU63: =SUM(LARM:RM!BU63) -> 0 | BV63: =SUM(LARM:RM!BV63) -> 0 | BW63: =SUM(LARM:RM!BW63) -> 0 | BX63: =SUM(LARM:RM!BX63) -> 0 | ... CU63: =SUM(LARM:RM!CU63) -> 0 | CV63: =SUM(BQ63:CU63) -> 0 | CW63: =SUM(LARM:RM!CW63) -> 0 | CX63: =SUM(LARM:RM!CX63) -> 0 | CY63: =SUM(LARM:RM!CY63) -> 0 | CZ63: =SUM(LARM:RM!CZ63) -> 0 | DA63: =SUM(LARM:RM!DA63) -> 0 | DB63: =SUM(LARM:RM!DB63) -> 0 | DC63: =SUM(LARM:RM!DC63) -> 0 | DD63: =SUM(LARM:RM!DD63) -> 0 | ... EA63: =SUM(LARM:RM!EA63) -> 0 | EB63: =SUM(CW63:EA63) -> 0 | EC63: =SUM(LARM:RM!EC63) -> 0 | ED63: =SUM(LARM:RM!ED63) -> 0 | EE63: =SUM(LARM:RM!EE63) -> 0 | EF63: =SUM(LARM:RM!EF63) -> 0 | EG63: =SUM(LARM:RM!EG63) -> 0 | EH63: =SUM(LARM:RM!EH63) -> 0 | EI63: =SUM(LARM:RM!EI63) -> 0 | EJ63: =SUM(LARM:RM!EJ63) -> 0 | ... FG63: =SUM(LARM:RM!FG63) -> 0 | FH63: =SUM(EC63:FG63) -> 0 | FI63: =SUM(LARM:RM!FI63) -> 0 | FJ63: =SUM(LARM:RM!FJ63) -> 0 | FK63: =SUM(LARM:RM!FK63) -> 0 | FL63: =SUM(LARM:RM!FL63) -> 0 | FM63: =SUM(LARM:RM!FM63) -> 0 | FN63: =SUM(LARM:RM!FN63) -> 0 | FO63: =SUM(LARM:RM!FO63) -> 0 | FP63: =SUM(LARM:RM!FP63) -> 0 | ... GM63: =SUM(LARM:RM!GM63) -> 0 | GN63: =SUM(FI63:GM63) -> 0 | GO63: =SUM(LARM:RM!GO63) -> 0 | GP63: =SUM(LARM:RM!GP63) -> 0 | GQ63: =SUM(LARM:RM!GQ63) -> 0 | GR63: =SUM(LARM:RM!GR63) -> 0 | GS63: =SUM(LARM:RM!GS63) -> 0 | GT63: =SUM(LARM:RM!GT63) -> 0 | GU63: =SUM(LARM:RM!GU63) -> 0 | GV63: =SUM(LARM:RM!GV63) -> 0 | ... HS63: =SUM(LARM:RM!HS63) -> 0 | HT63: =SUM(GO63:HS63) -> 0 | HU63: =SUM(LARM:RM!HU63) -> 0 | HV63: =SUM(LARM:RM!HV63) -> 0 | HW63: =SUM(LARM:RM!HW63) -> 0 | HX63: =SUM(LARM:RM!HX63) -> 0 | HY63: =SUM(LARM:RM!HY63) -> 0 | HZ63: =SUM(LARM:RM!HZ63) -> 0 | IA63: =SUM(LARM:RM!IA63) -> 0 | IB63: =SUM(LARM:RM!IB63) -> 0 | ... IY63: =SUM(LARM:RM!IY63) -> 0 | IZ63: =SUM(HU63:IY63) -> 0 | JA63: =SUM(LARM:RM!JA63) -> 0 | JB63: =SUM(LARM:RM!JB63) -> 0 | JC63: =SUM(LARM:RM!JC63) -> 0 | JD63: =SUM(LARM:RM!JD63) -> 0 | JE63: =SUM(LARM:RM!JE63) -> 0 | JF63: =SUM(LARM:RM!JF63) -> 0 | JG63: =SUM(LARM:RM!JG63) -> 0 | JH63: =SUM(LARM:RM!JH63) -> 0 | ... KE63: =SUM(LARM:RM!KE63) -> 0 | KF63: =SUM(JA63:KE63) -> 0 | KG63: =SUM(LARM:RM!KG63) -> 0 | KH63: =SUM(LARM:RM!KH63) -> 0 | KI63: =SUM(LARM:RM!KI63) -> 0 | KJ63: =SUM(LARM:RM!KJ63) -> 0 | KK63: =SUM(LARM:RM!KK63) -> 0 | KL63: =SUM(LARM:RM!KL63) -> 0 | KM63: =SUM(LARM:RM!KM63) -> 0 | KN63: =SUM(LARM:RM!KN63) -> 0 | ... LK63: =SUM(LARM:RM!LK63) -> 0 | LL63: =SUM(KG63:LK63) -> 0 | LM63: =SUM(LARM:RM!LM63) -> 0 | LN63: =SUM(LARM:RM!LN63) -> 0 | LO63: =SUM(LARM:RM!LO63) -> 0 | LP63: =SUM(LARM:RM!LP63) -> 0 | LQ63: =SUM(LARM:RM!LQ63) -> 0 | LR63: =SUM(LARM:RM!LR63) -> 0 | LS63: =SUM(LARM:RM!LS63) -> 0 | LT63: =SUM(LARM:RM!LT63) -> 0 | ... MQ63: =SUM(LARM:RM!MQ63) -> 0 | MR63: =SUM(LM63:MQ63) -> 0 | MS63: =SUM(LARM:RM!MS63) -> 0 | MT63: =SUM(LARM:RM!MT63) -> 0 | MU63: =SUM(LARM:RM!MU63) -> 0 | MV63: =SUM(LARM:RM!MV63) -> 0 | MW63: =SUM(LARM:RM!MW63) -> 0 | MX63: =SUM(LARM:RM!MX63) -> 0 | MY63: =SUM(LARM:RM!MY63) -> 0 | MZ63: =SUM(LARM:RM!MZ63) -> 0 | ... NW63: =SUM(LARM:RM!NW63) -> 0 | NX63: =SUM(MS63:NW63) -> 0 | NZ63: =AJ63+BP63+CV63+EB63+FH63+GN63+HT63+IZ63+KF63+LL63+MR63+NX63 -> 0 | OA63: =SUM(OI63:OP63) -> 0 | OB63: =IF(OA63=0,"",((NZ63/OA63)-1)*-1) | OG63: Impostos/ Taxas / Comissões | OI63: =SUM(LARM:RM!OI62) -> 0 | OJ63: =SUM(LARM:RM!OJ62) -> 0 | OK63: =SUM(LARM:RM!OK62) -> 0 | OL63: =SUM(LARM:RM!OL62) -> 0 | OM63: =SUM(LARM:RM!OM62) -> 0 | ON63: =SUM(LARM:RM!ON62) -> 0 | OO63: =SUM(LARM:RM!OO62) -> 0 | OP63: =SUM(LARM:RM!OP62) -> 0 | ... OT63: =SUM(LARM:RM!OT62) -> 0 | OV63: =SUM(LARM:RM!OV62) -> 0
C66: SALDO FINAL | E66: =E5+E42+E44+E59+E62 -> 9666474 | F66: =F5+F42+F44+F59+F62 -> 9557534 | G66: =G5+G42+G44+G59+G62 -> 9557534 | H66: =H5+H42+H44+H59+H62 -> 9557534 | I66: =I5+I42+I44+I59+I62 -> 9568564.6 | J66: =J5+J42+J44+J59+J62 -> 9610003.3 | K66: =K5+K42+K44+K59+K62 -> 9600051.9 | L66: =L5+L42+L44+L59+L62 -> 9504902 | ... NX66: =NX5+NX42+NX44+NX59+NX62 -> 6461935.8 | NZ66: =NZ5+NZ42+NZ44+NZ59+NZ62 -> 6461935.8 | OA66: =OA5+OA42+OA44 -> 8534939.7 | OB66: =IF(OA66=0,"",((NZ66/OA66)-1)) -> -0.24288442 | OG66: SALDO FINAL | OI66: =OI5+OI42+OI44+OI59+OI62 -> 9318743 | OJ66: =OJ5+OJ42+OJ44+OJ59+OJ62 -> 8870547.8 | OK66: =OK5+OK42+OK44+OK59+OK62 -> 8557368.7 | OL66: =OL5+OL42+OL44+OL59+OL62 -> 8201602.8 | OM66: =OM5+OM42+OM44+OM59+OM62 -> 8044399.7 | ON66: =ON5+ON42+ON44+ON59+ON62 -> 7825930.4 | OO66: =OO5+OO42+OO44+OO59+OO62 -> 7637207.4 | OP66: =OP5+OP42+OP44+OP59+OP62 -> 7531380.1 | ... OT66: =OT5+OT42+OT44+OT59+OT62 -> 6625042.7 | OV66: =OV5+OV42+OV44+OV59+OV62 -> 6625042.7
NZ67: =NZ66-AJ5 -> -3204538.1 | OV67: =OV66-OV5 -> -3041431.2
C68: Saldos Bancários em C/C | E68: =E66-E69 -> 591387.27 | F68: =F66-F69 -> 482447.31 | G68: =G66-G69 -> 482447.31 | H68: =H66-H69 -> 482447.31 | I68: =I66-I69 -> 493477.96 | J68: =J66-J69 -> 534916.63 | K68: =K66-K69 -> 524965.22 | L68: =L66-L69 -> 429815.33 | ... NX68: =NX66-NX69 -> -1559525.1 | NZ68: =NZ66-NZ69 -> -1559525.1
C69: Aplicações Financeiras | E69: =E71+E77 -> 9075086.7 | F69: =F71+F77 -> 9075086.7 | G69: =G71+G77 -> 9075086.7 | H69: =H71+H77 -> 9075086.7 | I69: =I71+I77 -> 9075086.7 | J69: =J71+J77 -> 9075086.7 | K69: =K71+K77 -> 9075086.7 | L69: =L71+L77 -> 9075086.7 | ... NX69: =NX71+NX77 -> 8021461 | NZ69: =NZ71+NZ77 -> 8021461
C71: Curto Prazo | E71: =SUM(E72:E76) -> 1042853.2 | F71: =SUM(F72:F76) -> 1042853.2 | G71: =SUM(G72:G76) -> 1042853.2 | H71: =SUM(H72:H76) -> 1042853.2 | I71: =SUM(I72:I76) -> 1042853.2 | J71: =SUM(J72:J76) -> 1042853.2 | K71: =SUM(K72:K76) -> 1042853.2 | L71: =SUM(L72:L76) -> 1042853.2 | ... NX71: =SUM(NX72:NX76) -> 671533.59 | NZ71: =SUM(NZ72:NZ76) -> 671533.59
B72: CDB1 | C72: CDB CEF | E72: =SUM(LARM:RM!E72) -> 0 | F72: =SUM(LARM:RM!F72) -> 0 | G72: =SUM(LARM:RM!G72) -> 0 | H72: =SUM(LARM:RM!H72) -> 0 | I72: =SUM(LARM:RM!I72) -> 0 | J72: =SUM(LARM:RM!J72) -> 0 | K72: =SUM(LARM:RM!K72) -> 0 | L72: =SUM(LARM:RM!L72) -> 0 | ... NZ72: =SUM(LARM:RM!NZ72) -> 1041.31
B73: CDB2 | C73: CDB Daycoval | E73: =SUM(LARM:RM!E73) -> 1042853.2 | F73: =SUM(LARM:RM!F73) -> 1042853.2 | G73: =SUM(LARM:RM!G73) -> 1042853.2 | H73: =SUM(LARM:RM!H73) -> 1042853.2 | I73: =SUM(LARM:RM!I73) -> 1042853.2 | J73: =SUM(LARM:RM!J73) -> 1042853.2 | K73: =SUM(LARM:RM!K73) -> 1042853.2 | L73: =SUM(LARM:RM!L73) -> 1042853.2 | ... NZ73: =SUM(LARM:RM!NZ73) -> 670492.28
B74: LCA2 | C74: LCA Daycoval - Pós | E74: =SUM(LARM:RM!E74) -> 0 | F74: =SUM(LARM:RM!F74) -> 0 | G74: =SUM(LARM:RM!G74) -> 0 | H74: =SUM(LARM:RM!H74) -> 0 | I74: =SUM(LARM:RM!I74) -> 0 | J74: =SUM(LARM:RM!J74) -> 0 | K74: =SUM(LARM:RM!K74) -> 0 | L74: =SUM(LARM:RM!L74) -> 0 | ... NZ74: =SUM(LARM:RM!NZ74) -> 0
B75: LCI Pós | C75: LCI Pós | E75: =SUM(LARM:RM!E75) -> 0 | F75: =SUM(LARM:RM!F75) -> 0 | G75: =SUM(LARM:RM!G75) -> 0 | H75: =SUM(LARM:RM!H75) -> 0 | I75: =SUM(LARM:RM!I75) -> 0 | J75: =SUM(LARM:RM!J75) -> 0 | K75: =SUM(LARM:RM!K75) -> 0 | L75: =SUM(LARM:RM!L75) -> 0 | ... NZ75: =SUM(LARM:RM!NZ75) -> 0
B76: FI | C76: DAYCOVAL CLASSIC F.I. R.F. C.P | E76: =SUM(LARM:RM!E76) -> 0 | F76: =SUM(LARM:RM!F76) -> 0 | G76: =SUM(LARM:RM!G76) -> 0 | H76: =SUM(LARM:RM!H76) -> 0 | I76: =SUM(LARM:RM!I76) -> 0 | J76: =SUM(LARM:RM!J76) -> 0 | K76: =SUM(LARM:RM!K76) -> 0 | L76: =SUM(LARM:RM!L76) -> 0 | ... NZ76: =SUM(LARM:RM!NZ76) -> 0
C77: Longo Prazo | E77: =SUM(E78:E81) -> 8032233.5 | F77: =SUM(F78:F81) -> 8032233.5 | G77: =SUM(G78:G81) -> 8032233.5 | H77: =SUM(H78:H81) -> 8032233.5 | I77: =SUM(I78:I81) -> 8032233.5 | J77: =SUM(J78:J81) -> 8032233.5 | K77: =SUM(K78:K81) -> 8032233.5 | L77: =SUM(L78:L81) -> 8032233.5 | ... NX77: =SUM(NX78:NX81) -> 7349927.4 | NZ77: =SUM(NZ78:NZ81) -> 7349927.4
B78: LCA | C78: LCA Daycoval - Pós | E78: =SUM(LARM:RM!E78) -> 0 | F78: =SUM(LARM:RM!F78) -> 0 | G78: =SUM(LARM:RM!G78) -> 0 | H78: =SUM(LARM:RM!H78) -> 0 | I78: =SUM(LARM:RM!I78) -> 0 | J78: =SUM(LARM:RM!J78) -> 0 | K78: =SUM(LARM:RM!K78) -> 0 | L78: =SUM(LARM:RM!L78) -> 0 | ... NZ78: =SUM(LARM:RM!NZ78) -> 0
B79: LCA V | C79: LCA Brasil Agro - F.I.P | E79: =SUM(LARM:RM!E79) -> 6607392 | F79: =SUM(LARM:RM!F79) -> 6607392 | G79: =SUM(LARM:RM!G79) -> 6607392 | H79: =SUM(LARM:RM!H79) -> 6607392 | I79: =SUM(LARM:RM!I79) -> 6607392 | J79: =SUM(LARM:RM!J79) -> 6607392 | K79: =SUM(LARM:RM!K79) -> 6607392 | L79: =SUM(LARM:RM!L79) -> 6607392 | ... NZ79: =SUM(LARM:RM!NZ79) -> 6000000
B80: CDBG | C80: CDB Daycoval (Garantido) | E80: =SUM(LARM:RM!E80) -> 1424841.5 | F80: =SUM(LARM:RM!F80) -> 1424841.5 | G80: =SUM(LARM:RM!G80) -> 1424841.5 | H80: =SUM(LARM:RM!H80) -> 1424841.5 | I80: =SUM(LARM:RM!I80) -> 1424841.5 | J80: =SUM(LARM:RM!J80) -> 1424841.5 | K80: =SUM(LARM:RM!K80) -> 1424841.5 | L80: =SUM(LARM:RM!L80) -> 1424841.5 | ... NZ80: =SUM(LARM:RM!NZ80) -> 1349927.4
B81: LCI | C81: Debêntures | E81: =SUM(LARM:RM!E81) -> 0 | F81: =SUM(LARM:RM!F81) -> 0 | G81: =SUM(LARM:RM!G81) -> 0 | H81: =SUM(LARM:RM!H81) -> 0 | I81: =SUM(LARM:RM!I81) -> 0 | J81: =SUM(LARM:RM!J81) -> 0 | K81: =SUM(LARM:RM!K81) -> 0 | L81: =SUM(LARM:RM!L81) -> 0 | ... NZ81: =SUM(LARM:RM!NZ81) -> 0
EC83: =EC82-#REF! -> #REF!
NZ84: =LM!NZ84+LUCKY!NZ84 -> 7349927.4 | OD84: Aplicação longo prazo

Sheet LARM
C2: CashFlow | OG2: ORÇADO
C3: LARM | E3: 46023 | F3: =E3+1 -> 46024 | G3: =F3+1 -> 46025 | H3: =G3+1 -> 46026 | I3: =H3+1 -> 46027 | J3: =I3+1 -> 46028 | K3: =J3+1 -> 46029 | L3: =K3+1 -> 46030 | M3: =L3+1 -> 46031 | ... AI3: =AH3+1 -> 46053 | AJ3: Jan-26 | AK3: =AI3+1 -> 46054 | AL3: =AK3+1 -> 46055 | AM3: =AL3+1 -> 46056 | AN3: =AM3+1 -> 46057 | AO3: =AN3+1 -> 46058 | AP3: =AO3+1 -> 46059 | AQ3: =AP3+1 -> 46060 | AR3: =AQ3+1 -> 46061 | AS3: =AR3+1 -> 46062 | ... BL3: =BK3+1 -> 46081 | BP3: Fev-26 | BQ3: =BL3+1 -> 46082 | BR3: =BQ3+1 -> 46083 | BS3: =BR3+1 -> 46084 | BT3: =BS3+1 -> 46085 | BU3: =BT3+1 -> 46086 | BV3: =BU3+1 -> 46087 | BW3: =BV3+1 -> 46088 | BX3: =BW3+1 -> 46089 | BY3: =BX3+1 -> 46090 | ... CU3: =CT3+1 -> 46112 | CV3: Mar-26 | CW3: =CU3+1 -> 46113 | CX3: =CW3+1 -> 46114 | CY3: =CX3+1 -> 46115 | CZ3: =CY3+1 -> 46116 | DA3: =CZ3+1 -> 46117 | DB3: =DA3+1 -> 46118 | DC3: =DB3+1 -> 46119 | DD3: =DC3+1 -> 46120 | DE3: =DD3+1 -> 46121 | ... DZ3: =DY3+1 -> 46142 | EB3: Abr-26 | EC3: =DZ3+1 -> 46143 | ED3: =EC3+1 -> 46144 | EE3: =ED3+1 -> 46145 | EF3: =EE3+1 -> 46146 | EG3: =EF3+1 -> 46147 | EH3: =EG3+1 -> 46148 | EI3: =EH3+1 -> 46149 | EJ3: =EI3+1 -> 46150 | EK3: =EJ3+1 -> 46151 | ... FG3: =FF3+1 -> 46173 | FH3: Mai-26 | FI3: =FG3+1 -> 46174 | FJ3: =FI3+1 -> 46175 | FK3: =FJ3+1 -> 46176 | FL3: =FK3+1 -> 46177 | FM3: =FL3+1 -> 46178 | FN3: =FM3+1 -> 46179 | FO3: =FN3+1 -> 46180 | FP3: =FO3+1 -> 46181 | FQ3: =FP3+1 -> 46182 | ... GL3: =GK3+1 -> 46203 | GN3: Jun-26 | GO3: =GL3+1 -> 46204 | GP3: =GO3+1 -> 46205 | GQ3: =GP3+1 -> 46206 | GR3: =GQ3+1 -> 46207 | GS3: =GR3+1 -> 46208 | GT3: =GS3+1 -> 46209 | GU3: =GT3+1 -> 46210 | GV3: =GU3+1 -> 46211 | GW3: =GV3+1 -> 46212 | ... HS3: =HR3+1 -> 46234 | HT3: Jul-26 | HU3: =HS3+1 -> 46235 | HV3: =HU3+1 -> 46236 | HW3: =HV3+1 -> 46237 | HX3: =HW3+1 -> 46238 | HY3: =HX3+1 -> 46239 | HZ3: =HY3+1 -> 46240 | IA3: =HZ3+1 -> 46241 | IB3: =IA3+1 -> 46242 | IC3: =IB3+1 -> 46243 | ... IY3: =IX3+1 -> 46265 | IZ3: Ago-26 | JA3: =IY3+1 -> 46266 | JB3: =JA3+1 -> 46267 | JC3: =JB3+1 -> 46268 | JD3: =JC3+1 -> 46269 | JE3: =JD3+1 -> 46270 | JF3: =JE3+1 -> 46271 | JG3: =JF3+1 -> 46272 | JH3: =JG3+1 -> 46273 | JI3: =JH3+1 -> 46274 | ... KD3: =KC3+1 -> 46295 | KF3: Set-26 | KG3: =KD3+1 -> 46296 | KH3: =KG3+1 -> 46297 | KI3: =KH3+1 -> 46298 | KJ3: =KI3+1 -> 46299 | KK3: =KJ3+1 -> 46300 | KL3: =KK3+1 -> 46301 | KM3: =KL3+1 -> 46302 | KN3: =KM3+1 -> 46303 | KO3: =KN3+1 -> 46304 | ... LK3: =LJ3+1 -> 46326 | LL3: Out-26 | LM3: =LK3+1 -> 46327 | LN3: =LM3+1 -> 46328 | LO3: =LN3+1 -> 46329 | LP3: =LO3+1 -> 46330 | LQ3: =LP3+1 -> 46331 | LR3: =LQ3+1 -> 46332 | LS3: =LR3+1 -> 46333 | LT3: =LS3+1 -> 46334 | LU3: =LT3+1 -> 46335 | ... MP3: =MO3+1 -> 46356 | MR3: Nov-26 | MS3: =MP3+1 -> 46357 | MT3: =MS3+1 -> 46358 | MU3: =MT3+1 -> 46359 | MV3: =MU3+1 -> 46360 | MW3: =MV3+1 -> 46361 | MX3: =MW3+1 -> 46362 | MY3: =MX3+1 -> 46363 | MZ3: =MY3+1 -> 46364 | NA3: =MZ3+1 -> 46365 | ... NW3: =NV3+1 -> 46387 | NX3: Dez-26 | NZ3: Acumulado | OA3: Orçado | OB3: Var% | OG3: LARM | OI3: Jan-26 | OJ3: Fev-26 | OK3: Mar-26 | OL3: Abr-26 | OM3: Mai-26 | ON3: Jun-26 | OO3: Jul-26 | OP3: Ago-26 | OQ3: Set-26 | OR3: Out-26 | OS3: Nov-26 | OT3: Dez-26 | OV3: Acumulado
C5: (A) Saldo Inicial | E5: =90391.48+2811.58 -> 93203.06 | F5: =E66 -> 93203.06 | G5: =F66 -> 99772.48 | H5: =G66 -> 99772.48 | I5: =H66 -> 99772.48 | J5: =I66 -> 104036.66 | K5: =J66 -> 123068.8 | L5: =K66 -> 116480.05 | M5: =L66 -> 50103.96 | ... AI5: =AH66 -> 100003.06 | AJ5: =E5 -> 93203.06 | AK5: =AJ66 -> 100003.06 | AL5: =AK66 -> 100003.06 | AM5: =AL66 -> 24554.24 | AN5: =AM66 -> 28458.43 | AO5: =AN66 -> 30140 | AP5: =AO66 -> 29929.5 | AQ5: =AP66 -> 46104.56 | AR5: =AQ66 -> 46104.56 | ... BO5: =BN66 -> 135893.3 | BP5: =AK5 -> 100003.06 | BQ5: =BP66 -> 135893.3 | BR5: =BQ66 -> 135893.3 | BS5: =BR66 -> 193399.83 | BT5: =BS66 -> 200187.04 | BU5: =BT66 -> 202137.55 | BV5: =BU66 -> 201726.97 | BW5: =BV66 -> 217768.96 | BX5: =BW66 -> 217768.96 | ... CU5: =CT66 -> 171455.83 | CV5: =BQ5 -> 135893.3 | CW5: =CV66 -> 182744.9 | CX5: =CW66 -> 178489.89 | CY5: =CX66 -> 144213.18 | CZ5: =CY66 -> 144213.18 | DA5: =CZ66 -> 144213.18 | DB5: =DA66 -> 144213.18 | DC5: =DB66 -> 141399.55 | DD5: =DC66 -> 162331.16 | ... EA5: =DZ66 -> 112663.4 | EB5: =CW5 -> 182744.9 | EC5: =EB66 -> 112663.4 | ED5: =EC66 -> 112663.4 | EE5: =ED66 -> 112663.4 | EF5: =EE66 -> 112663.4 | EG5: =EF66 -> 66060.48 | EH5: =EG66 -> 69657.56 | EI5: =EH66 -> 99481.29 | EJ5: =EI66 -> 99481.29 | ... FG5: =FF66 -> 45692.733 | FH5: =EC5 -> 112663.4 | FI5: =FH66 -> 45692.733 | FJ5: =FI66 -> 45692.733 | FK5: =FJ66 -> -409.75667 | FL5: =FK66 -> 1701.4333 | FM5: =FL66 -> 1701.4333 | FN5: =FM66 -> 6449.9933 | FO5: =FN66 -> 15815.143 | FP5: =FO66 -> 15815.143 | ... GM5: =GL66 -> 19050.767 | GN5: =FI5 -> 45692.733 | GO5: =GN66 -> 19050.767 | GP5: =GO66 -> -28784.793 | GQ5: =GP66 -> -25334.793 | GR5: =GQ66 -> -23223.603 | GS5: =GR66 -> -123223.6 | GT5: =GS66 -> -118270.6 | GU5: =GT66 -> -118270.6 | GV5: =GU66 -> -120838.93 | ... HS5: =HR66 -> -8920.02 | HT5: =GO5 -> 19050.767 | HU5: =HT66 -> -8920.02 | HV5: =HU66 -> -57541.12 | HW5: =HV66 -> -54091.12 | HX5: =HW66 -> -52497.86 | HY5: =HX66 -> -3158.56 | HZ5: =HY66 -> 821.98 | IA5: =HZ66 -> 10573.43 | IB5: =IA66 -> 9846.85 | ... IY5: =IX66 -> -30854.227 | IZ5: =HU5 -> -8920.02 | JA5: =IZ66 -> -30854.227 | JB5: =JA66 -> -78578.957 | JC5: =JB66 -> -75517.157 | JD5: =JC66 -> -73923.897 | JE5: =JD66 -> -73923.897 | JF5: =JE66 -> -69181.397 | JG5: =JF66 -> -59429.947 | JH5: =JG66 -> -59429.947 | ... KE5: =KD66 -> 769.76667 | KF5: =JA5 -> -30854.227 | KG5: =KF66 -> 769.76667 | KH5: =KG66 -> -45174.473 | KI5: =KH66 -> -41724.473 | KJ5: =KI66 -> -40241.113 | KK5: =KJ66 -> -40241.113 | KL5: =KK66 -> -35288.113 | KM5: =KL66 -> -27895.273 | KN5: =KM66 -> -27895.273 | ... LK5: =LJ66 -> 14569.503 | LL5: =KG5 -> 769.76667 | LM5: =LL66 -> 14569.503 | LN5: =LM66 -> 14569.503 | LO5: =LN66 -> 18019.503 | LP5: =LO66 -> -26579.967 | LQ5: =LP66 -> -26579.967 | LR5: =LQ66 -> -23276.217 | LS5: =LR66 -> -13524.767 | LT5: =LS66 -> -13524.767 | ... MQ5: =MP66 -> 53029.623 | MR5: =LM5 -> 14569.503 | MS5: =MR66 -> 53029.623 | MT5: =MS66 -> 52079.623 | MU5: =MT66 -> 22698.483 | MV5: =MU66 -> -22504.847 | MW5: =MV66 -> -22654.847 | MX5: =MW66 -> -17906.287 | MY5: =MX66 -> -8154.8367 | MZ5: =MY66 -> -8929.2767 | ... NW5: =NV66 -> 21311.907 | NX5: =MS5 -> 53029.623 | NZ5: =AJ5 -> 93203.06 | OA5: =NZ5 -> 93203.06 | OG5: (A) Saldo Inicial | OI5: =AJ5 -> 93203.06 | OJ5: =OI66 -> 39525.24 | OK5: =OJ66 -> 53522.347 | OL5: =OK66 -> 49418.827 | OM5: =OL66 -> 92066.843 | ON5: =OM66 -> 73341.313 | OO5: =ON66 -> 68938.063 | OP5: =OO66 -> 49473.283 | OQ5: =OP66 -> 44865.563 | ... OT5: =OS66 -> 144251.81 | OV5: =OI5 -> 93203.06
B7: 1. | C7: Receitas Brutas | E7: =SUM(E8:E11) -> 0 | F7: =SUM(F8:F11) -> 1648.04 | G7: =SUM(G8:G11) -> 0 | H7: =SUM(H8:H11) -> 0 | I7: =SUM(I8:I11) -> 5442.42 | J7: =SUM(J8:J11) -> 19464.08 | K7: =SUM(K8:K11) -> 0 | L7: =SUM(L8:L11) -> 0 | ... NX7: =SUM(NX8:NX11) -> 72635.95 | NZ7: =SUM(NZ8:NZ11) -> 1139894.9 | OA7: =SUM(OA8:OA12) -> 589545.09 | OB7: =IF(NZ7=0,"",(OA7/NZ7)-1) -> -0.48280753 | OG7: Receitas Brutas | OI7: =SUM(OI8:OI11) -> 105120.45 | OJ7: =SUM(OJ8:OJ11) -> 92132.14 | OK7: =SUM(OK8:OK11) -> 82637.05 | OL7: =SUM(OL8:OL11) -> 92332.73 | OM7: =SUM(OM8:OM11) -> 70996.91 | ON7: =SUM(ON8:ON11) -> 70547.38 | OO7: =SUM(OO8:OO11) -> 70038.05 | OP7: =SUM(OP8:OP11) -> 78588.89 | ... OT7: =SUM(OT8:OT11) -> 72522.74 | OV7: =SUM(OV8:OV11) -> 961980.7
